Workbook
Name _1_200_CTCONTROL_PROY: '[1]202 TCONTROL_TOTAL_PROY'!#REF!
Name codestado: [2]!Tabla6[Código]
Name codmes: [2]!Tabla7[Código]
Name codrec: [2]!Tabla5[Código]
Name codselec: [2]!Modalidades[Código]
Name codvigencias: [2]!Tabla8[¿Se requieren vigencias futuras?]
Name DEPENDENCIA: '[3]Anexo 2.'!$B$416:$B$441
Name estado: [2]!Tabla6[Estado de solicitud de vigencias futuras]
Name EstadoContrato: '[3]Anexo 2.'!$B$446:$B$452
Name FUENTE: '[3]Anexo 2.'!$D$449:$D$453
Name gobernacion: '[4]Anexo 2.'!$D$391:$D$394
Name intervalos: [2]!Tabla4[Duración estimada del contrato (intervalo: días, meses, años)]
Name l: '[5]Anexo 2.'!$D$357:$D$387
Name ll: '[5]Anexo 2.'!$D$357:$D$387
Name meses: [2]!Tabla7[Mes]
Name MODALIDAD: '[6]Anexo 2.'!$D$322:$D$349
Name modselec: [2]!Modalidades[[Modalidad de selección ]]
Name MODSELECCION: '[3]Anexo 2.'!$D$416:$D$446
Name MUJERES: '[7]Anexo 2.'!$B$319:$B$344
Name Municipios: Table1[]
Name Municipios: Table1[#Data]
Name Municipios: Table1[]
Name Municipios: Table1[]
Name NECESIDAD: '2.BDN (backup)'!$B$2:$U$330
Name NECESIDAD: #REF!
Name NECESIDAD: '2.BDN'!$B$2:$P$327
Name Nombproducto: [8]!Articulacion[NOMBRE PRODUCTO]
Name NombPrograma: [8]!Articulacion[NOMBRE PROGRAMA]
Name Nombproyecto: [8]!Articulacion[NOMBRE PROYECTO]
Name PEP: [8]!Articulacion[ELEMENTO PEP]
Name PROGRAMAS: '[3]Anexo 2.'!$F$423:$F$551
Name recursos: [2]!Tabla5[Fuente de los recursos]
Name secretaira: '[4]Anexo 2.'!$B$351:$B$376
Name TIPOSUPER: '[9]Anexo 2.'!$F$579:$F$583
Name VIGENCIAS: '[10]Anexo 2.'!$E$404:$E$407

Sheet 1.RADICADOS
A1: ID_RADICADOS | B1: RADICADO | C1: FECHA | D1: DIAS TRANSCURRIDOS | E1: SUBREGIÓN (BLOQUEAR) | F1: MUNICIPIO | G1: ID PROYECTOS | H1: PROYECTOS | I1: TIPO DE SOLICITUD | J1: PRESUPUESTO (ELIMINAR) | K1: OBSERVACIONES
A2: =ROW() - ROW(radicados[[#Headers],[ID_RADICADOS]]) -> 1 | B2: 2024010048235 | C2: 45327 | D2: =+TODAY()-radicados[[#This Row],[FECHA]] -> 669 | E2: =+_xlfn.XLOOKUP(radicados[[#This Row],[MUNICIPIO]],MUNICIPIOS!A:A,MUNICIPIOS!E:E,0,0,1) -> Nordeste | F2: Vegachí | G2: 1 | H2: CONSTRUCCIÓN DE PARQUES DEL RIO, ETAPA 1, EN EL MUNICIPIO DE VEGACHÍ, ANTIOQUIA” | I2: Ajuste proyecto | J2: 666322545
A3: =ROW() - ROW(radicados[[#Headers],[ID_RADICADOS]]) -> 2 | B3: 2024010031666 | C3: 45316 | D3: =+TODAY()-radicados[[#This Row],[FECHA]] -> 680 | E3: =+_xlfn.XLOOKUP(radicados[[#This Row],[MUNICIPIO]],MUNICIPIOS!A:A,MUNICIPIOS!E:E,0,0,1) -> Magdalena Medio | F3: Puerto Triunfo | G3: 2 | H3: Construcción de muelle Malecón turístico en la Cabecera municipal de Puerto Triunfo Antioquia | I3: Ajuste proyecto | J3: 496406918
A4: =ROW() - ROW(radicados[[#Headers],[ID_RADICADOS]]) -> 3 | B4: 2024010111694 | C4: 45629 | D4: =+TODAY()-radicados[[#This Row],[FECHA]] -> 367 | E4: =+_xlfn.XLOOKUP(radicados[[#This Row],[MUNICIPIO]],MUNICIPIOS!A:A,MUNICIPIOS!E:E,0,0,1) -> Valle de Aburrá | F4: Barbosa | G4: 3 | H4: Intercambio vial sector 3 | I4: Proyecto nuevo | J4: 54654511129
A5: =ROW() - ROW(radicados[[#Headers],[ID_RADICADOS]]) -> 4 | B5: 2024010110440 | C5: 45599 | D5: =+TODAY()-radicados[[#This Row],[FECHA]] -> 397 | E5: =+_xlfn.XLOOKUP(radicados[[#This Row],[MUNICIPIO]],MUNICIPIOS!A:A,MUNICIPIOS!E:E,0,0,1) -> Oriente | F5: El Retiro | G5: 145 | H5: Parque lineal, Bosques urbanos | I5: Proyecto nuevo | J5: 20074758933
A6: =ROW() - ROW(radicados[[#Headers],[ID_RADICADOS]]) -> 5 | B6: 2024010118992 | C6: 45366 | D6: =+TODAY()-radicados[[#This Row],[FECHA]] -> 630 | E6: =+_xlfn.XLOOKUP(radicados[[#This Row],[MUNICIPIO]],MUNICIPIOS!A:A,MUNICIPIOS!E:E,0,0,1) -> Suroeste | F6: Urrao | G6: 109 | H6: Construcción de pavimento rígido en vías urbanas y rurales del municipio de Urrao | I6: Proyecto nuevo | J6: 0
A7: =ROW() - ROW(radicados[[#Headers],[ID_RADICADOS]]) -> 6 | B7: 2024010105045 | C7: 45476 | D7: =+TODAY()-radicados[[#This Row],[FECHA]] -> 520 | E7: =+_xlfn.XLOOKUP(radicados[[#This Row],[MUNICIPIO]],MUNICIPIOS!A:A,MUNICIPIOS!E:E,0,0,1) -> Oriente | F7: Rionegro | G7: 4 | H7: Construcción del Puente Biblioteca en el municipio de Rionegro | I7: Ajuste proyecto | J7: 8594513471
A8: =ROW() - ROW(radicados[[#Headers],[ID_RADICADOS]]) -> 7 | B8: 2024010070587 | C8: 45338 | D8: =+TODAY()-radicados[[#This Row],[FECHA]] -> 658 | E8: =+_xlfn.XLOOKUP(radicados[[#This Row],[MUNICIPIO]],MUNICIPIOS!A:A,MUNICIPIOS!E:E,0,0,1) -> Suroeste | F8: Santa Bárbara | G8: 5 | H8: Pavimentación de la vía Santa Bárbara - Fredonia (ruta 25) Fredonia Código 25AN02 en el Plan de Desarrollo Departamental 2024 - 2027 | I8: Proyecto nuevo | J8: 0
A9: =ROW() - ROW(radicados[[#Headers],[ID_RADICADOS]]) -> 8 | B9: 2024010071479 | C9: 45341 | D9: =+TODAY()-radicados[[#This Row],[FECHA]] -> 655 | E9: =+_xlfn.XLOOKUP(radicados[[#This Row],[MUNICIPIO]],MUNICIPIOS!A:A,MUNICIPIOS!E:E,0,0,1) -> Oriente | F9: Abejorral | G9: 6 | H9: Placa huella Abejorral - Purima | I9: Proyecto nuevo | J9: 6800000000
A10: =ROW() - ROW(radicados[[#Headers],[ID_RADICADOS]]) -> 9 | B10: 2024010019030 | C10: 45308 | D10: =+TODAY()-radicados[[#This Row],[FECHA]] -> 688 | E10: =+_xlfn.XLOOKUP(radicados[[#This Row],[MUNICIPIO]],MUNICIPIOS!A:A,MUNICIPIOS!E:E,0,0,1) -> Norte | F10: Donmatías | G10: 7 | H10: Pavimentación de 11km de la vía Riogrande - Bellavista (05237VT073) | I10: Proyecto nuevo | J10: 0
A11: =ROW() - ROW(radicados[[#Headers],[ID_RADICADOS]]) -> 10 | B11: 2024010020020 | C11: 45308 | D11: =+TODAY()-radicados[[#This Row],[FECHA]] -> 688 | E11: =+_xlfn.XLOOKUP(radicados[[#This Row],[MUNICIPIO]],MUNICIPIOS!A:A,MUNICIPIOS!E:E,0,0,1) -> Urabá | F11: Carepa | G11: 8 | H11: Solicitud de apoyo y acompañamiento integral a la Gestión territorial - Remitido por el ministerio de ambiente | J11: 0
A12: =ROW() - ROW(radicados[[#Headers],[ID_RADICADOS]]) -> 11 | B12: 2024010048752 | C12: 45414 | D12: =+TODAY()-radicados[[#This Row],[FECHA]] -> 582 | E12: =+_xlfn.XLOOKUP(radicados[[#This Row],[MUNICIPIO]],MUNICIPIOS!A:A,MUNICIPIOS!E:E,0,0,1) -> Nordeste | F12: Vegachí | G12: 9 | H12: Pavimentación de la vía que conduce al corregimiento portachuelo en Amalfí desde el municipio de Vegachí (05858VT61) "Alejandría - Cascajo" | I12: Proyecto nuevo | J12: 0
A13: =ROW() - ROW(radicados[[#Headers],[ID_RADICADOS]]) -> 12 | B13: 2024010043395 | C13: 45293 | D13: =+TODAY()-radicados[[#This Row],[FECHA]] -> 703 | E13: =+_xlfn.XLOOKUP(radicados[[#This Row],[MUNICIPIO]],MUNICIPIOS!A:A,MUNICIPIOS!E:E,0,0,1) -> Bajo Cauca | F13: Caucasia | G13: 10 | H13: Aeropuerto Regional - Parque Lineal (Ciclo vía) - Peopuesta proyectos en desarrollo Bajo Cauca Antioqueño. Finca la Mariela - Caucasía, Antioquia | I13: Proyecto nuevo | J13: 0
A14: =ROW() - ROW(radicados[[#Headers],[ID_RADICADOS]]) -> 13 | B14: 2024010068835 | C14: 45338 | D14: =+TODAY()-radicados[[#This Row],[FECHA]] -> 658 | E14: =+_xlfn.XLOOKUP(radicados[[#This Row],[MUNICIPIO]],MUNICIPIOS!A:A,MUNICIPIOS!E:E,0,0,1) -> Occidente | F14: Armenia | G14: 11 | H14: Recuperación, pavimentación y mantenimiento a la malla vial que comunica al municipio de Armenia con el municipio de Titiribí | J14: 0
A15: =ROW() - ROW(radicados[[#Headers],[ID_RADICADOS]]) -> 14 | B15: 2024010033632 | C15: 45316 | D15: =+TODAY()-radicados[[#This Row],[FECHA]] -> 680 | E15: =+_xlfn.XLOOKUP(radicados[[#This Row],[MUNICIPIO]],MUNICIPIOS!A:A,MUNICIPIOS!E:E,0,0,1) -> 0 | G15: 12 | H15: Incluir el plan de negocios del PTI, en el plan de Desarrollo de Antioquia Firme financiación para la terminación de los estudios de la pre-factibilidad y el acompañamiento del lincenciamiento ante la ANI. | I15: Petición | J15: 0
A16: =ROW() - ROW(radicados[[#Headers],[ID_RADICADOS]]) -> 15 | B16: 2024010078784 | C16: 45344 | D16: =+TODAY()-radicados[[#This Row],[FECHA]] -> 652 | E16: =+_xlfn.XLOOKUP(radicados[[#This Row],[MUNICIPIO]],MUNICIPIOS!A:A,MUNICIPIOS!E:E,0,0,1) -> Suroeste | F16: Támesis | G16: 54 | H16: Vía entre corregimiento de San Pablo y vereda Naranjal (Codigo 05856VT104) | I16: Proyecto nuevo | J16: 0
A17: =ROW() - ROW(radicados[[#Headers],[ID_RADICADOS]]) -> 16 | B17: 2024010084216 | C17: 45348 | D17: =+TODAY()-radicados[[#This Row],[FECHA]] -> 648 | E17: =+_xlfn.XLOOKUP(radicados[[#This Row],[MUNICIPIO]],MUNICIPIOS!A:A,MUNICIPIOS!E:E,0,0,1) -> Suroeste | F17: Tarso | G17: 14 | H17: Solicitud de Pavimentación vía Peñalisa - La Bodega - Tarso, La Bodega - Pueblorico con codigo 25BAN03-1 | I17: Petición | J17: 51682398
A18: =ROW() - ROW(radicados[[#Headers],[ID_RADICADOS]]) -> 17 | B18: 2024010041849 | C18: 45322 | D18: =+TODAY()-radicados[[#This Row],[FECHA]] -> 674 | E18: =+_xlfn.XLOOKUP(radicados[[#This Row],[MUNICIPIO]],MUNICIPIOS!A:A,MUNICIPIOS!E:E,0,0,1) -> Norte | F18: San José de la Montaña | G18: 15 | H18: Mejoramiento de la red vial urbana Municipio de San josé de la Montaña | I18: Ajuste proyecto | J18: 294694981
A19: =ROW() - ROW(radicados[[#Headers],[ID_RADICADOS]]) -> 18 | B19: 2024010054228 | C19: 45475 | D19: =+TODAY()-radicados[[#This Row],[FECHA]] -> 521 | E19: =+_xlfn.XLOOKUP(radicados[[#This Row],[MUNICIPIO]],MUNICIPIOS!A:A,MUNICIPIOS!E:E,0,0,1) -> Norte | F19: San José de la Montaña | G19: 16 | H19: Mejoramiento de vías rurales en los municipios de Belmira y San José de la Montaña, Antioquia | I19: Proyecto nuevo | J19: 3142000000
A20: =ROW() - ROW(radicados[[#Headers],[ID_RADICADOS]]) -> 19 | B20: 2024010013378 | C20: 45306 | D20: =+TODAY()-radicados[[#This Row],[FECHA]] -> 690 | E20: =+_xlfn.XLOOKUP(radicados[[#This Row],[MUNICIPIO]],MUNICIPIOS!A:A,MUNICIPIOS!E:E,0,0,1) -> Suroeste | F20: Fredonia | G20: 17 | H20: Solicitud pavimentación vía corregimiento Marsella | I20: Proyecto nuevo | J20: 0
A21: =ROW() - ROW(radicados[[#Headers],[ID_RADICADOS]]) -> 20 | B21: 2024010179553 | C21: 45406 | D21: =+TODAY()-radicados[[#This Row],[FECHA]] -> 590 | E21: =+_xlfn.XLOOKUP(radicados[[#This Row],[MUNICIPIO]],MUNICIPIOS!A:A,MUNICIPIOS!E:E,0,0,1) -> Urabá | F21: San Pedro de Urabá | G21: 18 | H21: Construcción de pavimento rígido en vías del casco urbano del municipio de San Pedro de Urabá, Antiquia | I21: Proyecto nuevo | J21: 0
A22: =ROW() - ROW(radicados[[#Headers],[ID_RADICADOS]]) -> 21 | B22: 2024010178436 | C22: 45405 | D22: =+TODAY()-radicados[[#This Row],[FECHA]] -> 591 | E22: =+_xlfn.XLOOKUP(radicados[[#This Row],[MUNICIPIO]],MUNICIPIOS!A:A,MUNICIPIOS!E:E,0,0,1) -> Urabá | F22: San Juan de Urabá | G22: 19 | H22: Construcción de placa huella en la vía acceso al corregimiento de Belén Municipio de San Juan de Urabá, Antioquia | I22: Proyecto nuevo | J22: 2139964660
A23: =ROW() - ROW(radicados[[#Headers],[ID_RADICADOS]]) -> 22 | B23: 2024010178733 | C23: 45405 | D23: =+TODAY()-radicados[[#This Row],[FECHA]] -> 591 | E23: =+_xlfn.XLOOKUP(radicados[[#This Row],[MUNICIPIO]],MUNICIPIOS!A:A,MUNICIPIOS!E:E,0,0,1) -> Nordeste | F23: Yolombó | G23: 20 | H23: Mejoramiento vías urbanas municipio de Yolombó | I23: Ajuste proyecto | J23: 750000000
A24: =ROW() - ROW(radicados[[#Headers],[ID_RADICADOS]]) -> 23 | B24: 2024020016404 | C24: 45398 | D24: =+TODAY()-radicados[[#This Row],[FECHA]] -> 598 | E24: =+_xlfn.XLOOKUP(radicados[[#This Row],[MUNICIPIO]],MUNICIPIOS!A:A,MUNICIPIOS!E:E,0,0,1) -> Oriente | F24: Rionegro | G24: 21 | H24: Construcción del ámbito patrimonio del proyecto Paisajes del Agua en el Municipio de Rionegro | I24: Ajuste proyecto | J24: 1578945342
A25: =ROW() - ROW(radicados[[#Headers],[ID_RADICADOS]]) -> 24 | B25: 2024010171235 | C25: 45400 | D25: =+TODAY()-radicados[[#This Row],[FECHA]] -> 596 | E25: =+_xlfn.XLOOKUP(radicados[[#This Row],[MUNICIPIO]],MUNICIPIOS!A:A,MUNICIPIOS!E:E,0,0,1) -> Oriente | F25: Alejandría | G25: 22 | H25: Estudios y diseños para plaza de feria ganadera en el municipio de Alejandría - Antioquia | I25: Proyecto nuevo | J25: 112000000
A26: =ROW() - ROW(radicados[[#Headers],[ID_RADICADOS]]) -> 25 | B26: 2024010153392 | C26: 45569 | D26: =+TODAY()-radicados[[#This Row],[FECHA]] -> 427 | E26: =+_xlfn.XLOOKUP(radicados[[#This Row],[MUNICIPIO]],MUNICIPIOS!A:A,MUNICIPIOS!E:E,0,0,1) -> Norte | F26: Donmatías | G26: 23 | H26: Construcción del espacio público parques de la quebrada Donmatías, Antioquia - Etapa 1 | I26: Ajuste proyecto | J26: 764624487
A27: =ROW() - ROW(radicados[[#Headers],[ID_RADICADOS]]) -> 26 | B27: 2024010207402 | C27: 45509 | D27: =+TODAY()-radicados[[#This Row],[FECHA]] -> 487 | E27: =+_xlfn.XLOOKUP(radicados[[#This Row],[MUNICIPIO]],MUNICIPIOS!A:A,MUNICIPIOS!E:E,0,0,1) -> Urabá | F27: Turbo | G27: 24 | H27: Construcción de la fase dos del malecón turístico del Distrito de Turbo | I27: Proyecto nuevo | J27: 0
... A57: =ROW() - ROW(radicados[[#Headers],[ID_RADICADOS]]) -> 56 | B57: 2024010308857 | C57: 45633 | D57: =+TODAY()-radicados[[#This Row],[FECHA]] -> 363 | E57: =+_xlfn.XLOOKUP(radicados[[#This Row],[MUNICIPIO]],MUNICIPIOS!A:A,MUNICIPIOS!E:E,0,0,1) -> Urabá | F57: Chigorodó | G57: 51 | H57: Pavimentación en concreto rígido , andenes peatonales y silvicultura en la calle 97 entre carrera 101 y 112 del municipio de Chigorodó, Antioquia | I57: Proyecto nuevo | J57: 4215630027
A58: =ROW() - ROW(radicados[[#Headers],[ID_RADICADOS]]) -> 57 | B58: 2024010313514 | C58: 45358 | D58: =+TODAY()-radicados[[#This Row],[FECHA]] -> 638 | E58: =+_xlfn.XLOOKUP(radicados[[#This Row],[MUNICIPIO]],MUNICIPIOS!A:A,MUNICIPIOS!E:E,0,0,1) -> Norte | F58: Yarumal | G58: 52 | H58: Intervención de la vía terciaria de acceso al corregimiento cedeño y sus veredas aledañas en el municipio de Yarumal, Antioquia afectada por la ola invernal | J58: 0
A59: =ROW() - ROW(radicados[[#Headers],[ID_RADICADOS]]) -> 58 | B59: 2024010295409 | C59: 45603 | D59: =+TODAY()-radicados[[#This Row],[FECHA]] -> 393 | E59: =+_xlfn.XLOOKUP(radicados[[#This Row],[MUNICIPIO]],MUNICIPIOS!A:A,MUNICIPIOS!E:E,0,0,1) -> Occidente | F59: Sopetrán | G59: 53 | H59: Solicitud de pavimentación de vía Belmira Horizontes | I59: Petición | J59: 0
A60: =ROW() - ROW(radicados[[#Headers],[ID_RADICADOS]]) -> 59 | B60: 2024010309743 | C60: 45490 | D60: =+TODAY()-radicados[[#This Row],[FECHA]] -> 506 | E60: =+_xlfn.XLOOKUP(radicados[[#This Row],[MUNICIPIO]],MUNICIPIOS!A:A,MUNICIPIOS!E:E,0,0,1) -> Suroeste | F60: Támesis | G60: 54 | H60: Construcción de placa huella y obras complementarias en la vía Támesis - San Pablo en el municipio de Támesis - Antioquia | I60: Proyecto nuevo | J60: 3539562399
A61: =ROW() - ROW(radicados[[#Headers],[ID_RADICADOS]]) -> 60 | B61: 2024010319437 | C61: 45634 | D61: =+TODAY()-radicados[[#This Row],[FECHA]] -> 362 | E61: =+_xlfn.XLOOKUP(radicados[[#This Row],[MUNICIPIO]],MUNICIPIOS!A:A,MUNICIPIOS!E:E,0,0,1) -> Oriente | F61: Sonsón | G61: 55 | H61: Pavimentación de 700 metros de pavimento rígido en la vía La Danta - Autopista Medellín - Bogotá | I61: Proyecto nuevo | J61: 684345500
A62: =ROW() - ROW(radicados[[#Headers],[ID_RADICADOS]]) -> 61 | B62: 2024010361194 | C62: 45634 | D62: =+TODAY()-radicados[[#This Row],[FECHA]] -> 362 | E62: =+_xlfn.XLOOKUP(radicados[[#This Row],[MUNICIPIO]],MUNICIPIOS!A:A,MUNICIPIOS!E:E,0,0,1) -> Oriente | F62: Cocorná | G62: 56 | H62: Mejoramiento del corredor turístico Cocorná - Maria Parda con la construcción de 2.6 km de pavimento rígido, en el municipio de Cocorná, Antioquia ADJUNTO CON CONTRASEÑA | I62: Proyecto nuevo | J62: 0
A63: =ROW() - ROW(radicados[[#Headers],[ID_RADICADOS]]) -> 62 | B63: 2024010361554 | C63: 45504 | D63: =+TODAY()-radicados[[#This Row],[FECHA]] -> 492 | E63: =+_xlfn.XLOOKUP(radicados[[#This Row],[MUNICIPIO]],MUNICIPIOS!A:A,MUNICIPIOS!E:E,0,0,1) -> Suroeste | F63: Betania | G63: 57 | H63: PAVIMENTACIÓN DE VÍAS URBANAS Y OBRAS DE CONTENCIÓN EN EL MUNICIPIO DE BETANIA ANTIOQUIA | I63: Proyecto nuevo | J63: 4172739792
A64: =ROW() - ROW(radicados[[#Headers],[ID_RADICADOS]]) -> 63 | B64: 2024010344153 | C64: 45512 | D64: =+TODAY()-radicados[[#This Row],[FECHA]] -> 484 | E64: =+_xlfn.XLOOKUP(radicados[[#This Row],[MUNICIPIO]],MUNICIPIOS!A:A,MUNICIPIOS!E:E,0,0,1) -> Urabá | F64: Apartadó | G64: 48 | H64: Construcción de pavimento rigido en vias urbanas, Barrio obrero del municipio de Apartadó. | I64: Proyecto nuevo | J64: 7999391717
A65: =ROW() - ROW(radicados[[#Headers],[ID_RADICADOS]]) -> 64 | B65: 2024010356273 | C65: 45451 | D65: =+TODAY()-radicados[[#This Row],[FECHA]] -> 545 | E65: =+_xlfn.XLOOKUP(radicados[[#This Row],[MUNICIPIO]],MUNICIPIOS!A:A,MUNICIPIOS!E:E,0,0,1) -> Urabá | F65: Apartadó | G65: 58 | H65: Mejoramiento de vías terciarias en la vereda Churido Medio, zona rural del municipio de Apartadó, Antioquia. | I65: Proyecto nuevo | J65: 7500000000
A66: =ROW() - ROW(radicados[[#Headers],[ID_RADICADOS]]) -> 65 | B66: 2024010354533 | C66: 45518 | D66: =+TODAY()-radicados[[#This Row],[FECHA]] -> 478 | E66: =+_xlfn.XLOOKUP(radicados[[#This Row],[MUNICIPIO]],MUNICIPIOS!A:A,MUNICIPIOS!E:E,0,0,1) -> Valle de Aburrá | F66: Copacabana | G66: 59 | H66: Pavimentación de 2,2 Km vía Medellín-Bogotá y Vereda Peñolcito | I66: Proyecto nuevo | J66: 5661013100
A67: =ROW() - ROW(radicados[[#Headers],[ID_RADICADOS]]) -> 66 | B67: 2024010366485 | C67: 45451 | D67: =+TODAY()-radicados[[#This Row],[FECHA]] -> 545 | E67: =+_xlfn.XLOOKUP(radicados[[#This Row],[MUNICIPIO]],MUNICIPIOS!A:A,MUNICIPIOS!E:E,0,0,1) -> Occidente | F67: Sopetrán | G67: 60 | H67: REHABILITACIÓN Y MEJORAMIENTO DE 1.5 KILOMETROS DE PAVIMENTACIÓN FLEXIBLE DE VÍA RURAL QUE CONDUCE HACIA LA VEREDA EL RODEO, MUNICIPIO DE SOPETRAN, ANTIOQUIA | I67: Proyecto nuevo | J67: 3468415702
A68: =ROW() - ROW(radicados[[#Headers],[ID_RADICADOS]]) -> 67 | B68: 2024010353885 | C68: 45326 | D68: =+TODAY()-radicados[[#This Row],[FECHA]] -> 670 | E68: =+_xlfn.XLOOKUP(radicados[[#This Row],[MUNICIPIO]],MUNICIPIOS!A:A,MUNICIPIOS!E:E,0,0,1) -> Magdalena Medio | F68: Puerto Nare | G68: 61 | H68: MEJORAMIENTO DE LA RED VIAL URBANA DEL MUNICIO DE PUERTO NARE | I68: Proyecto nuevo | J68: 1500000000
A69: =ROW() - ROW(radicados[[#Headers],[ID_RADICADOS]]) -> 68 | B69: 2024010141962 | C69: 45525 | D69: =+TODAY()-radicados[[#This Row],[FECHA]] -> 471 | E69: =+_xlfn.XLOOKUP(radicados[[#This Row],[MUNICIPIO]],MUNICIPIOS!A:A,MUNICIPIOS!E:E,0,0,1) -> Norte | F69: Briceño | G69: 62 | H69: Mantenimiento de la vía terciaria que comunica la vereda El Roblal y el sector la Ye en el Municipio de Briceño, Antioquia. | I69: Proyecto nuevo | J69: 1104890715
A70: =ROW() - ROW(radicados[[#Headers],[ID_RADICADOS]]) -> 69 | B70: 2024010387133 | C70: 45512 | D70: =+TODAY()-radicados[[#This Row],[FECHA]] -> 484 | E70: =+_xlfn.XLOOKUP(radicados[[#This Row],[MUNICIPIO]],MUNICIPIOS!A:A,MUNICIPIOS!E:E,0,0,1) -> Norte | F70: Briceño | G70: 62 | H70: Mantenimiento de la vía terciaria que comunica la vereda El Roblal y el sector la Ye en el Municipio de Briceño, Antioquia. | I70: Proyecto nuevo | J70: 1104890715
... A98: =ROW() - ROW(radicados[[#Headers],[ID_RADICADOS]]) -> 97 | B98: 2024010318370 | C98: 45531 | D98: =+TODAY()-radicados[[#This Row],[FECHA]] -> 465 | E98: =+_xlfn.XLOOKUP(radicados[[#This Row],[MUNICIPIO]],MUNICIPIOS!A:A,MUNICIPIOS!E:E,0,0,1) -> Oriente | F98: Marinilla | G98: 84 | H98: PAVIMENTACIÓN DE VÍAS RURALES EN EL MUNCIPIO DE MARINILLA ANTIOQUIA - PLACAHUELLA | I98: Proyecto nuevo | J98: 5957178575
A99: =ROW() - ROW(radicados[[#Headers],[ID_RADICADOS]]) -> 98 | B99: 2024010414368 | C99: 45489 | D99: =+TODAY()-radicados[[#This Row],[FECHA]] -> 507 | E99: =+_xlfn.XLOOKUP(radicados[[#This Row],[MUNICIPIO]],MUNICIPIOS!A:A,MUNICIPIOS!E:E,0,0,1) -> Suroeste | F99: Tarso | G99: 85 | H99: SOLICITUD DE PAVIMENTACIÓN DE LA VÍA PEÑALISA – LA BODEGA, LA BODEGA – TARSO, LA BODEGA – PUEBLORRICO | I99: Proyecto nuevo
A100: =ROW() - ROW(radicados[[#Headers],[ID_RADICADOS]]) -> 99 | B100: 2024010398307 | C100: 45605 | D100: =+TODAY()-radicados[[#This Row],[FECHA]] -> 391 | E100: =+_xlfn.XLOOKUP(radicados[[#This Row],[MUNICIPIO]],MUNICIPIOS!A:A,MUNICIPIOS!E:E,0,0,1) -> Suroeste | F100: Tarso | G100: 85 | H100: SOLICITUD DE INTERVENCION DE LA VÍA PEÑALISA – LA BODEGA, LA BODEGA – TARSO, LA BODEGA – PUEBLORRICO | I100: Proyecto nuevo
A101: =ROW() - ROW(radicados[[#Headers],[ID_RADICADOS]]) -> 100 | B101: 2024010400738 | C101: 45360 | D101: =+TODAY()-radicados[[#This Row],[FECHA]] -> 636 | E101: =+_xlfn.XLOOKUP(radicados[[#This Row],[MUNICIPIO]],MUNICIPIOS!A:A,MUNICIPIOS!E:E,0,0,1) -> Occidente | F101: Cañasgordas | G101: 86 | H101: Construcción Parque Corregimiento Cestillal Municipio de Cañasgordas. | I101: Proyecto nuevo | J101: 1.5552567e+09
A102: =ROW() - ROW(radicados[[#Headers],[ID_RADICADOS]]) -> 101 | B102: 2024010415684 | C102: 45538 | D102: =+TODAY()-radicados[[#This Row],[FECHA]] -> 458 | E102: =+_xlfn.XLOOKUP(radicados[[#This Row],[MUNICIPIO]],MUNICIPIOS!A:A,MUNICIPIOS!E:E,0,0,1) -> Bajo Cauca | F102: Nechí | G102: 87 | H102: “CONSTRUCCIÓN DE PAVIMENTO RÍGIDO PARA MEJORAMIENTO DE LA VÍA HACIA LA VEREDA CORRENTOSO DESDE LA PARTIDA DE LONDRES, NECHÍ ANTIOQUIA”, | I102: Proyecto nuevo | J102: 4104136826
A103: =ROW() - ROW(radicados[[#Headers],[ID_RADICADOS]]) -> 102 | B103: 2024010415525 | C103: 45605 | D103: =+TODAY()-radicados[[#This Row],[FECHA]] -> 391 | E103: =+_xlfn.XLOOKUP(radicados[[#This Row],[MUNICIPIO]],MUNICIPIOS!A:A,MUNICIPIOS!E:E,0,0,1) -> Occidente | F103: Santa Fe de Antioquia | G103: 88 | H103: pavimentacion 2km vias urbanas municipio santa fe de antioquia | I103: Proyecto nuevo | J103: 8647258157
A104: =ROW() - ROW(radicados[[#Headers],[ID_RADICADOS]]) -> 103 | B104: 2024010404422 | C104: 45605 | D104: =+TODAY()-radicados[[#This Row],[FECHA]] -> 391 | E104: =+_xlfn.XLOOKUP(radicados[[#This Row],[MUNICIPIO]],MUNICIPIOS!A:A,MUNICIPIOS!E:E,0,0,1) -> Oriente | F104: La Unión | G104: 89 | H104: CONSTRUCCION Y MEJORAMIENTO DE VIAS TERCIARIA | I104: Proyecto nuevo | J104: 1.1889457e+10
A105: =ROW() - ROW(radicados[[#Headers],[ID_RADICADOS]]) -> 104 | B105: 2024010429627 | C105: 45421 | D105: =+TODAY()-radicados[[#This Row],[FECHA]] -> 575 | E105: =+_xlfn.XLOOKUP(radicados[[#This Row],[MUNICIPIO]],MUNICIPIOS!A:A,MUNICIPIOS!E:E,0,0,1) -> Norte | F105: Donmatías | G105: 90 | H105: MEJORAMIENTO DE LA ACCESIBILIDAD A LAS COMUNIDADES RURALES MEDIANTE LA CONSTRUCCIÓN DE PLACA HUELLA EN EL MUNICIPIO DE DONMATÍAS - ANTIOQUIA | I105: Proyecto nuevo | J105: 5823881298
A106: =ROW() - ROW(radicados[[#Headers],[ID_RADICADOS]]) -> 105 | B106: 2024010419609 | C106: 45554 | D106: =+TODAY()-radicados[[#This Row],[FECHA]] -> 442 | E106: =+_xlfn.XLOOKUP(radicados[[#This Row],[MUNICIPIO]],MUNICIPIOS!A:A,MUNICIPIOS!E:E,0,0,1) -> Urabá | F106: Vigía del Fuerte | G106: 91 | H106: MEJORAMIENTO DE LA RED VIAL DEL CASCO URBANO MEDIANTE LA CONSTRUCCIÓN DE 1.0 Km DE VIAS PEATONALES EN CONCRETO REFORZADO EN EL MUNICIPIO DE VIGIA DEL FUERTE EN EL DEPARTAMENTO DE ANTIOQUIA | I106: Proyecto nuevo | J106: 3060251962
A107: =ROW() - ROW(radicados[[#Headers],[ID_RADICADOS]]) -> 106 | B107: 2024010430044 | C107: 45548 | D107: =+TODAY()-radicados[[#This Row],[FECHA]] -> 448 | E107: =+_xlfn.XLOOKUP(radicados[[#This Row],[MUNICIPIO]],MUNICIPIOS!A:A,MUNICIPIOS!E:E,0,0,1) -> Bajo Cauca | F107: Cáceres | G107: 92 | H107: CONSTRUCCIÓN DE 2.4 KM DE PLACA HUELLA EN LA VÍA VEREDA LA EMBOSCADA Y VEREDA LA REVERZA EN EL MUNICIPIO DE CACERES ANTIOQUIA | I107: Proyecto nuevo | J107: 5048456575
A108: =ROW() - ROW(radicados[[#Headers],[ID_RADICADOS]]) -> 107 | B108: 2024010442066 | C108: 45554 | D108: =+TODAY()-radicados[[#This Row],[FECHA]] -> 442 | E108: =+_xlfn.XLOOKUP(radicados[[#This Row],[MUNICIPIO]],MUNICIPIOS!A:A,MUNICIPIOS!E:E,0,0,1) -> Urabá | F108: Arboletes | G108: 93 | H108: CONSTRUCCION DE PAVIMENTO EN CONCRETO RIGIDO EN LA ZONA URBANA DEL MUNICIPIO DE ARBOLETES ANTIOQUIA. | I108: Proyecto nuevo | J108: 10681457198
A109: =ROW() - ROW(radicados[[#Headers],[ID_RADICADOS]]) -> 108 | B109: 2024010446070 | C109: 45562 | D109: =+TODAY()-radicados[[#This Row],[FECHA]] -> 434 | E109: =+_xlfn.XLOOKUP(radicados[[#This Row],[MUNICIPIO]],MUNICIPIOS!A:A,MUNICIPIOS!E:E,0,0,1) -> Norte | F109: Briceño | G109: 94 | H109: ESTUDIOS Y DISEÑOS PARA LA CONSTRUCCION DE 1.7 KILOMETROS DE PLACA HUELLA EN LA VEREDA MORAVIA, ZONA RURAL DEL MUNICIPIO DE BRICEÑO-ANTIOQUIA | I109: Proyecto nuevo | J109: 2753990112
A110: =ROW() - ROW(radicados[[#Headers],[ID_RADICADOS]]) -> 109 | B110: 2024010449385 | C110: 45565 | D110: =+TODAY()-radicados[[#This Row],[FECHA]] -> 431 | E110: =+_xlfn.XLOOKUP(radicados[[#This Row],[MUNICIPIO]],MUNICIPIOS!A:A,MUNICIPIOS!E:E,0,0,1) -> Valle de Aburrá | F110: Girardota | G110: 114 | H110: MEJORAMIENTO DE VÍAS TERCIARIAS EN EL MUNICIPIO DE GIRARDOTA ANTIOQUIA SECTOR PORTACHUELO, HOLANDA BAJA Y ALTA. | I110: Proyecto nuevo | J110: 17008905677
A111: =ROW() - ROW(radicados[[#Headers],[ID_RADICADOS]]) -> 110 | B111: 2024010427693 | C111: 45332 | D111: =+TODAY()-radicados[[#This Row],[FECHA]] -> 664 | E111: =+_xlfn.XLOOKUP(radicados[[#This Row],[MUNICIPIO]],MUNICIPIOS!A:A,MUNICIPIOS!E:E,0,0,1) -> Valle de Aburrá | F111: Girardota | G111: 95 | H111: Mejoramiento y recuperación de las condiciones de movilidad entre el municipio de Girardota, valle de aburra y la "YE" que comunica con guarne, oriente antioqueño, y con el municipio de san Vicente de Ferrer. | I111: Proyecto nuevo | J111: 18011055743
A112: =ROW() - ROW(radicados[[#Headers],[ID_RADICADOS]]) -> 111 | B112: 2024010423384 | C112: 45554 | D112: =+TODAY()-radicados[[#This Row],[FECHA]] -> 442 | E112: =+_xlfn.XLOOKUP(radicados[[#This Row],[MUNICIPIO]],MUNICIPIOS!A:A,MUNICIPIOS!E:E,0,0,1) -> Urabá | F112: Arboletes | G112: 96 | H112: CONSTRUCCION DE PLACA HUELLA EN LAS VIA DE ACCESO AL CORREGIMIENTO DE NARANJITAS MUNICIPIO DE ARBOLETES ANTIOQUIA | I112: Proyecto nuevo | J112: 4441184458
... A123: =ROW() - ROW(radicados[[#Headers],[ID_RADICADOS]]) -> 122 | B123: 2024010463584 | C123: 45301 | D123: =+TODAY()-radicados[[#This Row],[FECHA]] -> 695 | E123: =+_xlfn.XLOOKUP(radicados[[#This Row],[MUNICIPIO]],MUNICIPIOS!A:A,MUNICIPIOS!E:E,0,0,1) -> Bajo Cauca | F123: Cáceres | G123: 105 | H123: Construcción de pavimento rígido y optimización de redes de acueducto y alcantarillado en los barrios: La Magdalena, El Carmen, y Costa de Oro en el municipio de Cáceres, departamento de Antioquia. | I123: Proyecto nuevo | J123: 3.2015094e+09
A124: =ROW() - ROW(radicados[[#Headers],[ID_RADICADOS]]) -> 123 | B124: 2024010467704 | C124: 45545 | D124: =+TODAY()-radicados[[#This Row],[FECHA]] -> 451 | E124: =+_xlfn.XLOOKUP(radicados[[#This Row],[MUNICIPIO]],MUNICIPIOS!A:A,MUNICIPIOS!E:E,0,0,1) -> Suroeste | F124: Tarso | G124: 85 | H124: SOLICITUD DE PAVIMENTACIÓN DE LA VÍA PEÑALISA – LA BODEGA, LA BODEGA – TARSO, LA BODEGA – PUEBLORRICO | I124: Proyecto nuevo
A125: =ROW() - ROW(radicados[[#Headers],[ID_RADICADOS]]) -> 124 | B125: 2024010464392 | C125: 45606 | D125: =+TODAY()-radicados[[#This Row],[FECHA]] -> 390 | E125: =+_xlfn.XLOOKUP(radicados[[#This Row],[MUNICIPIO]],MUNICIPIOS!A:A,MUNICIPIOS!E:E,0,0,1) -> Occidente | F125: Liborina | G125: 106 | H125: Mejoramiento de vías terciarias y construcción de obras para la reducción del riesgo en zona rural del municipio de Liborina. | I125: Proyecto nuevo | J125: 3000000000
A126: =ROW() - ROW(radicados[[#Headers],[ID_RADICADOS]]) -> 125 | B126: 2024010477292 | C126: 45545 | D126: =+TODAY()-radicados[[#This Row],[FECHA]] -> 451 | E126: =+_xlfn.XLOOKUP(radicados[[#This Row],[MUNICIPIO]],MUNICIPIOS!A:A,MUNICIPIOS!E:E,0,0,1) -> Suroeste | F126: Andes | G126: 107 | H126: MEJORAMIENTO DE LA MALLA VIAL EN EL TRAMO ECOPARQUE REGIONAL MARIO ARAMBURO RESTREPO CORREGIMIENTO DE SAN JOS | I126: Proyecto nuevo | J126: 27306608479
A127: =ROW() - ROW(radicados[[#Headers],[ID_RADICADOS]]) -> 126 | B127: 2024010477263 | C127: 45586 | D127: =+TODAY()-radicados[[#This Row],[FECHA]] -> 410 | E127: =+_xlfn.XLOOKUP(radicados[[#This Row],[MUNICIPIO]],MUNICIPIOS!A:A,MUNICIPIOS!E:E,0,0,1) -> Suroeste | F127: Andes | G127: 107 | H127: MEJORAMIENTO DE LA MALLA VIAL EN EL TRAMO ECOPARQUE REGIONAL MARIO ARAMBURO RESTREPO CORREGIMIENTO DE SAN JOS | I127: Proyecto nuevo | J127: 27306608479
A128: =ROW() - ROW(radicados[[#Headers],[ID_RADICADOS]]) -> 127 | B128: 2024010464862 | C128: 45575 | D128: =+TODAY()-radicados[[#This Row],[FECHA]] -> 421 | E128: =+_xlfn.XLOOKUP(radicados[[#This Row],[MUNICIPIO]],MUNICIPIOS!A:A,MUNICIPIOS!E:E,0,0,1) -> Urabá | F128: Carepa | G128: 108 | H128: CONSTRUCCIÓN DE PAVIMENTO RÍGIDO Y URBANISMO PARA MEJORAR LA MOVILIDAD EN EL MUNICIPIO DE CAREPA, ANTIOQUIA | I128: Proyecto nuevo | J128: 7789949678
A129: =ROW() - ROW(radicados[[#Headers],[ID_RADICADOS]]) -> 128 | B129: 2024010467655 | C129: 45607 | D129: =+TODAY()-radicados[[#This Row],[FECHA]] -> 389 | E129: =+_xlfn.XLOOKUP(radicados[[#This Row],[MUNICIPIO]],MUNICIPIOS!A:A,MUNICIPIOS!E:E,0,0,1) -> Suroeste | F129: Urrao | G129: 109 | H129: CONSTRUCCIÓN DE PAVIMENTO RÍGIDO DE VÍAS URBANAS DISPERSAS EN EL MUNICIPIO DE URRAO, ANTIOQUIA | I129: Proyecto nuevo | J129: 4999509465
A130: =ROW() - ROW(radicados[[#Headers],[ID_RADICADOS]]) -> 129 | B130: 2024010500511 | C130: 45596 | D130: =+TODAY()-radicados[[#This Row],[FECHA]] -> 400 | E130: =+_xlfn.XLOOKUP(radicados[[#This Row],[MUNICIPIO]],MUNICIPIOS!A:A,MUNICIPIOS!E:E,0,0,1) -> Bajo Cauca | F130: Caucasia | G130: 110 | H130: CONSTRUCCIÓN DE PLACA HUELLA EN LA VÍA QUE CONDUCE DESDE LA VEREDA CAMPO ALEGRE A LA VEREDA SANTA ROSITA, ZONA RURAL DEL MUNICIPIO DE CAUCASIA" | I130: Proyecto nuevo | J130: 1956684978
A131: =ROW() - ROW(radicados[[#Headers],[ID_RADICADOS]]) -> 130 | B131: 2024010499529 | C131: 45596 | D131: =+TODAY()-radicados[[#This Row],[FECHA]] -> 400 | E131: =+_xlfn.XLOOKUP(radicados[[#This Row],[MUNICIPIO]],MUNICIPIOS!A:A,MUNICIPIOS!E:E,0,0,1) -> Oriente | F131: Guarne | G131: 111 | H131: "ESTUDIOS Y DISEÑOS PARA ELMEJORAMIENTO Y REHABILITACIÓN DE LA VÍA YOLOMBAL CIRCUNVALAR GUARNE,PARA LA UNIÓN DEL VALLE DE ABURRÁ Y EL VALLE DE SAN NICOLÁSI | I131: Proyecto nuevo | J131: 400000000
A132: =ROW() - ROW(radicados[[#Headers],[ID_RADICADOS]]) -> 131 | B132: 2024010490524 | C132: 45590 | D132: =+TODAY()-radicados[[#This Row],[FECHA]] -> 406 | E132: =+_xlfn.XLOOKUP(radicados[[#This Row],[MUNICIPIO]],MUNICIPIOS!A:A,MUNICIPIOS!E:E,0,0,1) -> Urabá | F132: Turbo | G132: 112 | H132: "CONSTRUCCIÓN DE PAVIMENTO DELA VÍA DE ACCESO AL HOSPITAL DON BOSCO DEL CORREGIMIENTO DECURRULAO DEL DISTRITO DE TURBO, ANTIOQUIA” | I132: Proyecto nuevo | J132: 2775714198
A133: =ROW() - ROW(radicados[[#Headers],[ID_RADICADOS]]) -> 132 | B133: 2024010502109 | C133: 45302 | D133: =+TODAY()-radicados[[#This Row],[FECHA]] -> 694 | E133: =+_xlfn.XLOOKUP(radicados[[#This Row],[MUNICIPIO]],MUNICIPIOS!A:A,MUNICIPIOS!E:E,0,0,1) -> Suroeste | F133: Ciudad Bolívar | G133: 113 | H133: PAVIMENTACIÓN VÍA DE ACCESO DEL CORREGIMIENTO ALFONSO LOPEZ, MUNICIPIO DE CIUDAD BOLIVAR - ANTIOQUIA | I133: Proyecto nuevo | J133: 3.9324539e+10
A134: =ROW() - ROW(radicados[[#Headers],[ID_RADICADOS]]) -> 133 | B134: 2024010513281 | C134: 45515 | D134: =+TODAY()-radicados[[#This Row],[FECHA]] -> 481 | E134: =+_xlfn.XLOOKUP(radicados[[#This Row],[MUNICIPIO]],MUNICIPIOS!A:A,MUNICIPIOS!E:E,0,0,1) -> Valle de Aburrá | F134: Girardota | G134: 114 | H134: REHABILITACION DE VIA HOLANDA PARTE ALTA Y HOLANDA PARTE BAJA DEL MUNICIPIO DE GIRARDOTA | I134: Proyecto nuevo | J134: 1.7008906e+10
A135: =ROW() - ROW(radicados[[#Headers],[ID_RADICADOS]]) -> 134 | B135: 2024010513286 | C135: 45515 | D135: =+TODAY()-radicados[[#This Row],[FECHA]] -> 481 | E135: =+_xlfn.XLOOKUP(radicados[[#This Row],[MUNICIPIO]],MUNICIPIOS!A:A,MUNICIPIOS!E:E,0,0,1) -> Valle de Aburrá | F135: Girardota | G135: 114 | H135: REHABILITACION DE VIA HOLANDA PARTE ALTA Y HOLANDA PARTE BAJA DEL MUNICIPIO DE GIRARDOTA | I135: Proyecto nuevo | J135: 1.7008906e+10
A136: =ROW() - ROW(radicados[[#Headers],[ID_RADICADOS]]) -> 135 | B136: 2024010520677 | C136: 45610 | D136: =+TODAY()-radicados[[#This Row],[FECHA]] -> 386 | E136: =+_xlfn.XLOOKUP(radicados[[#This Row],[MUNICIPIO]],MUNICIPIOS!A:A,MUNICIPIOS!E:E,0,0,1) -> Suroeste | F136: Ciudad Bolívar | G136: 115 | H136: REHABILITACIÓN CON PAVIMENTO TIPO PLACA HUELLA DE LA VÍA TERCIARIA MANZANILLO EN EL MUNICIPIO DE CIUDAD BOLÍVAR, ANTIOQUIA | I136: Proyecto nuevo | J136: 2177618498
... A144: =ROW() - ROW(radicados[[#Headers],[ID_RADICADOS]]) -> 143 | B144: 2024010518399 | C144: 45596 | D144: =+TODAY()-radicados[[#This Row],[FECHA]] -> 400 | E144: =+_xlfn.XLOOKUP(radicados[[#This Row],[MUNICIPIO]],MUNICIPIOS!A:A,MUNICIPIOS!E:E,0,0,1) -> Oriente | F144: El Peñol | G144: 121 | H144: CONSTRUCCIÓN DE PAVIMENTO EN PLACA HUELLA PARA LA VÍA A LA VEREDA: 1. LA MESETA ($ 2.385.209.672) 2. SANTA ANA ($ 1.121.164.516) 3. EL CARMELO ($ 1.700.051.625) | I144: Proyecto nuevo | J144: 5206425813
A145: =ROW() - ROW(radicados[[#Headers],[ID_RADICADOS]]) -> 144 | B145: 2024010523151 | C145: 45609 | D145: =+TODAY()-radicados[[#This Row],[FECHA]] -> 387 | E145: =+_xlfn.XLOOKUP(radicados[[#This Row],[MUNICIPIO]],MUNICIPIOS!A:A,MUNICIPIOS!E:E,0,0,1) -> Oriente | F145: San Carlos | G145: 122 | H145: PAVIMENTACION Y URBANISMO EN CONCRETO RIGIDO ZONA URBANA DEL MUNICIPIO DE SAN CARLOS, DEPARTAMENTO DE ANTIOQUIA | I145: Proyecto nuevo | J145: 2371629272 | K145: Ajuste al radicado anterior
A146: =ROW() - ROW(radicados[[#Headers],[ID_RADICADOS]]) -> 145 | B146: 2024010524340 | C146: 45611 | D146: =+TODAY()-radicados[[#This Row],[FECHA]] -> 385 | E146: =+_xlfn.XLOOKUP(radicados[[#This Row],[MUNICIPIO]],MUNICIPIOS!A:A,MUNICIPIOS!E:E,0,0,1) -> Oriente | F146: Sonsón | G146: 123 | H146: MEJORAMIENTO DE LA VÍA DEPARTAMENTAL SONSÓN AGUADAS, MUNICIPIO DE SONSÓN ANTIOQUIA. | I146: Proyecto nuevo | J146: 10000000000
A147: =ROW() - ROW(radicados[[#Headers],[ID_RADICADOS]]) -> 146 | B147: 2024010528792 | C147: 45611 | D147: =+TODAY()-radicados[[#This Row],[FECHA]] -> 385 | E147: =+_xlfn.XLOOKUP(radicados[[#This Row],[MUNICIPIO]],MUNICIPIOS!A:A,MUNICIPIOS!E:E,0,0,1) -> Oriente | F147: La Ceja | G147: 124 | H147: Construcción de placa huellas en zonas rurales. | I147: Proyecto nuevo | J147: 9902922492
A148: =ROW() - ROW(radicados[[#Headers],[ID_RADICADOS]]) -> 147 | B148: 2024010535795 | C148: 45615 | D148: =+TODAY()-radicados[[#This Row],[FECHA]] -> 381 | E148: =+_xlfn.XLOOKUP(radicados[[#This Row],[MUNICIPIO]],MUNICIPIOS!A:A,MUNICIPIOS!E:E,0,0,1) -> Oriente | F148: El Peñol | G148: 125 | H148: MEJORAMIENTO DE VÍAS URBANAS EN EL BARRIO CONQUISTADORES DEL MUNICIPIO DE EL PEÑOL | I148: Proyecto nuevo | J148: 4155687169
A149: =ROW() - ROW(radicados[[#Headers],[ID_RADICADOS]]) -> 148 | B149: 2024010538367 | C149: 45618 | D149: =+TODAY()-radicados[[#This Row],[FECHA]] -> 378 | E149: =+_xlfn.XLOOKUP(radicados[[#This Row],[MUNICIPIO]],MUNICIPIOS!A:A,MUNICIPIOS!E:E,0,0,1) -> Suroeste | F149: Montebello | G149: 126 | H149: SOLICITUD DE ESTUDIOS Y EJECUCIÓN DE PROYECTO PLACA HUELLA RURAL. | I149: Petición
A150: =ROW() - ROW(radicados[[#Headers],[ID_RADICADOS]]) -> 149 | B150: 2024010544598 | C150: 45622 | D150: =+TODAY()-radicados[[#This Row],[FECHA]] -> 374 | E150: =+_xlfn.XLOOKUP(radicados[[#This Row],[MUNICIPIO]],MUNICIPIOS!A:A,MUNICIPIOS!E:E,0,0,1) -> Nordeste | F150: Cisneros | G150: 127 | H150: CONSTRUCCION DE 1.5 KILMETROS DE PAVIMENTO URBANO DEL MUNICIPIO DE CISNEROS | I150: Proyecto nuevo | J150: 7365388005
A151: =ROW() - ROW(radicados[[#Headers],[ID_RADICADOS]]) -> 150 | B151: 2024010552957 | C151: 45624 | D151: =+TODAY()-radicados[[#This Row],[FECHA]] -> 372 | E151: =+_xlfn.XLOOKUP(radicados[[#This Row],[MUNICIPIO]],MUNICIPIOS!A:A,MUNICIPIOS!E:E,0,0,1) -> Norte | F151: Donmatías | G151: 128 | H151: Pavimentacin de 1,950 km de la via Iborra en la zona rural del municipio de Donmatas, del Departamento de Antioqui | I151: Proyecto nuevo | J151: 5716669019
A152: =ROW() - ROW(radicados[[#Headers],[ID_RADICADOS]]) -> 151 | B152: 2024010556193 | C152: 45363 | D152: =+TODAY()-radicados[[#This Row],[FECHA]] -> 633 | E152: =+_xlfn.XLOOKUP(radicados[[#This Row],[MUNICIPIO]],MUNICIPIOS!A:A,MUNICIPIOS!E:E,0,0,1) -> Suroeste | F152: Betania | G152: 159 | H152: PAVIMENTACIN MEDIANTE EL SISTEMA CONSTRUCTIVO DE PLACA HUELLA, DE LA VÍA BETANIA PEDRAL ARRIBA SECTOR SAN LUIS EN ZONA RURAL DEL MUNICIPIO DE BETANIA ANTIOQUIA. | I152: Proyecto nuevo | J152: 2299954496
A153: =ROW() - ROW(radicados[[#Headers],[ID_RADICADOS]]) -> 152 | B153: 2024010559100 | C153: 45424 | D153: =+TODAY()-radicados[[#This Row],[FECHA]] -> 572 | E153: =+_xlfn.XLOOKUP(radicados[[#This Row],[MUNICIPIO]],MUNICIPIOS!A:A,MUNICIPIOS!E:E,0,0,1) -> Oriente | F153: El Santuario | G153: 129 | H153: CONSTRUCCIÓN DE PLACA HUELLA EN VIAS TERCIARIAS DEL MUNICIPIO DE EL SANTUARIO-ANTIOQUIA | I153: Proyecto nuevo | J153: 2482841960
A154: =ROW() - ROW(radicados[[#Headers],[ID_RADICADOS]]) -> 153 | B154: 2024010559910 | C154: 45424 | D154: =+TODAY()-radicados[[#This Row],[FECHA]] -> 572 | E154: =+_xlfn.XLOOKUP(radicados[[#This Row],[MUNICIPIO]],MUNICIPIOS!A:A,MUNICIPIOS!E:E,0,0,1) -> Bajo Cauca | F154: Caucasia | G154: 130 | H154: CONSTRUCCIÓN DE PAVIMENTO RIGIDO EN VIAS DEL BARRIO BUENOS AIRES ZONA URBANA DEL MUNICIPIO DE CAUCASIA ANTIOQUIA | I154: Proyecto nuevo | J154: 1614250889
A155: =ROW() - ROW(radicados[[#Headers],[ID_RADICADOS]]) -> 154 | B155: 2024010562218 | C155: 45455 | D155: =+TODAY()-radicados[[#This Row],[FECHA]] -> 541 | E155: =+_xlfn.XLOOKUP(radicados[[#This Row],[MUNICIPIO]],MUNICIPIOS!A:A,MUNICIPIOS!E:E,0,0,1) -> Valle de Aburrá | F155: Sabaneta | G155: 131 | H155: Proyecto intercambio vial de la calle 77 sur entre la carrera 45 y carrera 46 y sus lazos de conexión. | I155: Proyecto nuevo | J155: 16755097970
A156: =ROW() - ROW(radicados[[#Headers],[ID_RADICADOS]]) -> 155 | B156: 2024010569332 | C156: 45455 | D156: =+TODAY()-radicados[[#This Row],[FECHA]] -> 541 | E156: =+_xlfn.XLOOKUP(radicados[[#This Row],[MUNICIPIO]],MUNICIPIOS!A:A,MUNICIPIOS!E:E,0,0,1) -> Magdalena Medio | F156: Puerto Triunfo | G156: 132 | H156: PAVIMENTACIN DE VÍS uRBANAS EN EL MUNICIPIO DE PUERTO TRIUNFO - ANTIOQUIA | I156: Proyecto nuevo | J156: 5766878117
A157: =ROW() - ROW(radicados[[#Headers],[ID_RADICADOS]]) -> 156 | B157: 2024010572157 | C157: 45608 | D157: =+TODAY()-radicados[[#This Row],[FECHA]] -> 388 | E157: =+_xlfn.XLOOKUP(radicados[[#This Row],[MUNICIPIO]],MUNICIPIOS!A:A,MUNICIPIOS!E:E,0,0,1) -> Nordeste | F157: San Roque | G157: 133 | H157: MEJORAMIENTO Y REPOSICIN DE PAVIMENTO RGIDO EN VIAS URBANAS DE LA CABECERA MUNICIPAL, Y LOS CORREGIMIENTOS DE SAN JOSE DEL NUS Y PROVIDENCIA DEL MUNICIPIO DE SAN ROQUE, DEPARTAMENTO DE ANTIOQUIA | I157: Proyecto nuevo | J157: 1955624022
A158: =ROW() - ROW(radicados[[#Headers],[ID_RADICADOS]]) -> 157 | B158: 2024010575640 | C158: 45638 | D158: =+TODAY()-radicados[[#This Row],[FECHA]] -> 358 | E158: =+_xlfn.XLOOKUP(radicados[[#This Row],[MUNICIPIO]],MUNICIPIOS!A:A,MUNICIPIOS!E:E,0,0,1) -> Oriente | F158: El Santuario | G158: 134 | H158: ESTUDIOS Y DISENOS PARA LA TERCERA ETAPA DE LA VIA INTERMEDIA | I158: Petición | J158: 9804796414
A159: =ROW() - ROW(radicados[[#Headers],[ID_RADICADOS]]) -> 158 | B159: 2024010435914 | C159: 45639 | D159: =+TODAY()-radicados[[#This Row],[FECHA]] -> 357 | E159: =+_xlfn.XLOOKUP(radicados[[#This Row],[MUNICIPIO]],MUNICIPIOS!A:A,MUNICIPIOS!E:E,0,0,1) -> Norte | F159: Donmatías | G159: 135 | H159: PAVIMENTACION VÍA FATIMA EN EL MUNICIPIO DE DONMATIAS | I159: Proyecto nuevo | J159: 2405517156
A160: =ROW() - ROW(radicados[[#Headers],[ID_RADICADOS]]) -> 159 | B160: 2024010435573 | C160: 45559 | D160: =+TODAY()-radicados[[#This Row],[FECHA]] -> 437 | E160: =+_xlfn.XLOOKUP(radicados[[#This Row],[MUNICIPIO]],MUNICIPIOS!A:A,MUNICIPIOS!E:E,0,0,1) -> Occidente | F160: Frontino | G160: 136 | H160: PAVIMENTACION VÍA FRONTINO NUTIBARA MUNICIPIO DE FRONTINO | I160: Petición | J160: 18933645714
A161: =ROW() - ROW(radicados[[#Headers],[ID_RADICADOS]]) -> 160 | B161: 2024010432919 | C161: 45559 | D161: =+TODAY()-radicados[[#This Row],[FECHA]] -> 437 | E161: =+_xlfn.XLOOKUP(radicados[[#This Row],[MUNICIPIO]],MUNICIPIOS!A:A,MUNICIPIOS!E:E,0,0,1) -> Urabá | F161: Murindó | G161: 137 | H161: CONSTRUCCIÓN DE PUENTES PEATONALES EN CONCRETO EN LA CABECERA MUNICIPAL DE MURINDÓ - ANTIOQUIA | I161: Proyecto nuevo
A162: =ROW() - ROW(radicados[[#Headers],[ID_RADICADOS]]) -> 161 | B162: 2024010575497 | C162: 45558 | D162: =+TODAY()-radicados[[#This Row],[FECHA]] -> 438 | E162: =+_xlfn.XLOOKUP(radicados[[#This Row],[MUNICIPIO]],MUNICIPIOS!A:A,MUNICIPIOS!E:E,0,0,1) -> Occidente | F162: Uramita | G162: 138 | H162: PAVIMENTACIÓN Y ADECUACIÓN DE VÍA EN EL BARRIO EL SOCORRO Y LA COPA EN LA ZONA URBANA DEL MUNICIPIO DE URAMITA, ANTIOQUIA | I162: Proyecto nuevo | J162: 1958822896
A163: =ROW() - ROW(radicados[[#Headers],[ID_RADICADOS]]) -> 162 | B163: 2024020058554 | C163: 45639 | D163: =+TODAY()-radicados[[#This Row],[FECHA]] -> 357 | E163: =+_xlfn.XLOOKUP(radicados[[#This Row],[MUNICIPIO]],MUNICIPIOS!A:A,MUNICIPIOS!E:E,0,0,1) -> Suroeste | F163: Amagá | G163: 35 | H163: plaza de mercado del municipio de amagá | I163: Petición | J163: 1.4991251e+09
A164: =ROW() - ROW(radicados[[#Headers],[ID_RADICADOS]]) -> 163 | B164: 2024010569315 | C164: 45552 | D164: =+TODAY()-radicados[[#This Row],[FECHA]] -> 444 | E164: =+_xlfn.XLOOKUP(radicados[[#This Row],[MUNICIPIO]],MUNICIPIOS!A:A,MUNICIPIOS!E:E,0,0,1) -> Magdalena Medio | F164: Puerto Triunfo | G164: 140 | H164: Construcción parque recreativo obrero en la zona urbana de la cabecera municipal | I164: Petición | J164: 0
A165: =ROW() - ROW(radicados[[#Headers],[ID_RADICADOS]]) -> 164 | B165: 2024010572114 | C165: 45394 | D165: =+TODAY()-radicados[[#This Row],[FECHA]] -> 602 | E165: =+_xlfn.XLOOKUP(radicados[[#This Row],[MUNICIPIO]],MUNICIPIOS!A:A,MUNICIPIOS!E:E,0,0,1) -> Oriente | F165: Marinilla | G165: 141 | H165: cicloruta municipio de marinilla | I165: Petición | J165: 1.5180146e+10
A166: =ROW() - ROW(radicados[[#Headers],[ID_RADICADOS]]) -> 165 | B166: 2024010596746 | C166: 45577 | D166: =+TODAY()-radicados[[#This Row],[FECHA]] -> 419 | E166: =+_xlfn.XLOOKUP(radicados[[#This Row],[MUNICIPIO]],MUNICIPIOS!A:A,MUNICIPIOS!E:E,0,0,1) -> Occidente | F166: Liborina | G166: 142 | H166: Construcción de placa huella en las vias terciearias del municipio de Liborina | I166: Proyecto nuevo
A167: =ROW() - ROW(radicados[[#Headers],[ID_RADICADOS]]) -> 166 | B167: 2024010596745 | C167: 45608 | D167: =+TODAY()-radicados[[#This Row],[FECHA]] -> 388 | E167: =+_xlfn.XLOOKUP(radicados[[#This Row],[MUNICIPIO]],MUNICIPIOS!A:A,MUNICIPIOS!E:E,0,0,1) -> Occidente | F167: Liborina | G167: 142 | H167: Construcción de placa huella en las vias terciearias del municipio de Liborina | I167: Proyecto nuevo
A168: =ROW() - ROW(radicados[[#Headers],[ID_RADICADOS]]) -> 167 | B168: 2024010584314 | C168: 45656 | D168: =+TODAY()-radicados[[#This Row],[FECHA]] -> 340 | E168: =+_xlfn.XLOOKUP(radicados[[#This Row],[MUNICIPIO]],MUNICIPIOS!A:A,MUNICIPIOS!E:E,0,0,1) -> Suroeste | F168: Betania | G168: 173 | H168: “CONSTRUCCIÓN DEL PUENTE VEHICULAR EL RETEN SOBRE EL RIO PEDRAL, ZONA RURAL DEL MUNICIPIO DE BETANIA - ANTIOQUIA.” | I168: Proyecto nuevo | J168: 1985764409
A169: =ROW() - ROW(radicados[[#Headers],[ID_RADICADOS]]) -> 168 | B169: 2025010011836 | C169: 45644 | D169: =+TODAY()-radicados[[#This Row],[FECHA]] -> 352 | E169: =+_xlfn.XLOOKUP(radicados[[#This Row],[MUNICIPIO]],MUNICIPIOS!A:A,MUNICIPIOS!E:E,0,0,1) -> Norte | F169: Yarumal | G169: 144 | H169: SOLICITUD SOLICITUD DE APOYO PARA LA COFINANCIACION EN LA EJECUCION DEL PROYECTO PAVIMENTACION EN CONCRETO RIGIDO -TIPO PLACA HUELLA- EN LA ZONA URBANA CORREGIMIENTO CEDRO Y PUEBLITO DEL MUNICIPIO DE YARUMAL | I169: Petición | J169: 5541310263
A170: =ROW() - ROW(radicados[[#Headers],[ID_RADICADOS]]) -> 169 | B170: 2024010518216 | C170: 45670 | D170: =+TODAY()-radicados[[#This Row],[FECHA]] -> 326 | E170: =+_xlfn.XLOOKUP(radicados[[#This Row],[MUNICIPIO]],MUNICIPIOS!A:A,MUNICIPIOS!E:E,0,0,1) -> Oriente | F170: El Retiro | G170: 145 | H170: PARQUE LINEAL - BOSQUES URBANOS DEL MUNICIPIO DE EL RETIRO | I170: Proyecto nuevo | J170: 21621443440
A171: =ROW() - ROW(radicados[[#Headers],[ID_RADICADOS]]) -> 170 | B171: 2025010002774 | C171: 45394 | D171: =+TODAY()-radicados[[#This Row],[FECHA]] -> 602 | E171: =+_xlfn.XLOOKUP(radicados[[#This Row],[MUNICIPIO]],MUNICIPIOS!A:A,MUNICIPIOS!E:E,0,0,1) -> Oriente | F171: San Luis | G171: 146 | H171: PROYECTO DE PAVIMENTACIÓN DE LA VÍA SAN LUIS - CHOCÓ | I171: Proyecto nuevo | J171: 78158511470
A172: =ROW() - ROW(radicados[[#Headers],[ID_RADICADOS]]) -> 171 | B172: 2025010013911 | C172: 45609 | D172: =+TODAY()-radicados[[#This Row],[FECHA]] -> 387 | E172: =+_xlfn.XLOOKUP(radicados[[#This Row],[MUNICIPIO]],MUNICIPIOS!A:A,MUNICIPIOS!E:E,0,0,1) -> Occidente | F172: Olaya | G172: 147 | H172: Construccion de pavimento flexible en la vía que conduce al corregimiento Llanadas del Municipio de Olaya. | I172: Proyecto nuevo | J172: 4297876107
A173: =ROW() - ROW(radicados[[#Headers],[ID_RADICADOS]]) -> 172 | B173: 2024010353894 | C173: 45510 | D173: =+TODAY()-radicados[[#This Row],[FECHA]] -> 486 | E173: =+_xlfn.XLOOKUP(radicados[[#This Row],[MUNICIPIO]],MUNICIPIOS!A:A,MUNICIPIOS!E:E,0,0,1) -> Magdalena Medio | F173: Puerto Nare | G173: 61 | H173: Mejoramiento de la red vial urbana del municipio de Puerto Nare | I173: Proyecto nuevo | J173: 1653399856
...

Sheet 2.BDN
A1: ID_NECESIDAD | B1: NECESIDAD | C1: FECHA RECEPCION NECESIDAD | D1: MUNICIPIO | E1: SUBREGION | F1: LONGITUD | G1: LATITUD | H1: PDET | I1: ZOMAC | J1: RADICADOS ASOCIADOS | K1: FASE PROYECTO | L1: VALOR NECESIDAD SIF | M1: TIPOLOGIA | N1: ORDEN VIAL | O1: ASOCIACION AL PD | P1: OBSERVACION | Q1: PRIORIZADO | R1: POSIBLE FUENTE FINANCIACION | S1: PROGRAMA | T1: CATEGORÍA | U1: INGRESOS EJECUTADOS 2024 PROYECTADOS 2025 | V1: GASTOS EJECUTADOS 2024 PROYECTADOS 2025 | W1: AHORRO OPERACIONAL | X1: DEUDA IDEA Incluye por desembolsar | Y1: DEUDAS CON OTROS BANCOS Incluye por desembolsar | Z1: SALDO TOTAL DEUDA PROYECTADA | AA1: INDICADOR DE CAPACIDAD LEY 358 DE 1997 | AB1: CAPACIDAD MAXIMA DE ENDEUDAMIENTO AL 100% | AC1: CAPACIDAD MAXIMA DE ENDEUDAMIENTO AL 80% | AD1: CAPACIDAD MAXIMA DE ENDEUDAMIENTO AL 60% | AE1: Deuda del IDEA sobre el total | AF1: INDICADOR LEY 617 | AG1: LÍMITE 617 | AH1: SEMÁFORO | AI1: APORTE GOB | AJ1: SOBRANTE FALTANTE
A2: 1 | B2: CONSTRUCCIÓN DE PARQUES DEL RIO ETAPA 1 EN EL MUNICIPIO DE VEGACHÍ ANTIOQUIA” | C2: =+_xlfn.XLOOKUP(PROYECTOS[[#This Row],[ID_NECESIDAD]],'1.RADICADOS'!G:G,'1.RADICADOS'!C:C,0,0,1)*1 -> 45327 | D2: Vegachí | E2: =+_xlfn.XLOOKUP(PROYECTOS[[#This Row],[MUNICIPIO]],MUNICIPIOS!A:A,MUNICIPIOS!E:E,0,0,1) -> Nordeste | F2: =+_xlfn.XLOOKUP(PROYECTOS[[#This Row],[MUNICIPIO]],MUNICIPIOS!A:A,MUNICIPIOS!F:F,0,0,1) -> -74.798714 | G2: =+_xlfn.XLOOKUP(PROYECTOS[[#This Row],[MUNICIPIO]],MUNICIPIOS!A:A,MUNICIPIOS!G:G,0,0,1) -> 6.773525 | H2: =+_xlfn.XLOOKUP(PROYECTOS[[#This Row],[MUNICIPIO]],MUNICIPIOS!A:A,MUNICIPIOS!B:B,0,0,1) -> 0 | I2: =+_xlfn.XLOOKUP(PROYECTOS[[#This Row],[MUNICIPIO]],MUNICIPIOS!A:A,MUNICIPIOS!C:C,0,0,1) -> 1 | J2: {=_xlfn.TEXTJOIN(" ", TRUE, IF(radicados[ID PROYECTOS]=A2, radicados[RADICADO], ""))} -> 2024010048235 | K2: 1 | M2: Parque | N2: N/A | O2: Espacio público adecuado | T2: =+_xlfn.XLOOKUP(PROYECTOS[[#This Row],[MUNICIPIO]],'4.CAP_ENDMNT'!B:B,'4.CAP_ENDMNT'!C:C,0,0,1) -> 6 | U2: =+_xlfn.XLOOKUP(PROYECTOS[[#This Row],[MUNICIPIO]],'4.CAP_ENDMNT'!B:B,'4.CAP_ENDMNT'!D:D,0,0,1) -> 1.4438256e+10 | V2: =+_xlfn.XLOOKUP(PROYECTOS[[#This Row],[MUNICIPIO]],'4.CAP_ENDMNT'!B:B,'4.CAP_ENDMNT'!E:E,0,0,1) -> 4.6682009e+09 | W2: =+_xlfn.XLOOKUP(PROYECTOS[[#This Row],[MUNICIPIO]],'4.CAP_ENDMNT'!B:B,'4.CAP_ENDMNT'!F:F,0,0,1) -> 9.770055e+09 | X2: =+_xlfn.XLOOKUP(PROYECTOS[[#This Row],[MUNICIPIO]],'4.CAP_ENDMNT'!B:B,'4.CAP_ENDMNT'!G:G,0,0,1) -> 2534414723 | Y2: =+_xlfn.XLOOKUP(PROYECTOS[[#This Row],[MUNICIPIO]],'4.CAP_ENDMNT'!B:B,'4.CAP_ENDMNT'!H:H,0,0,1) -> 0 | Z2: =+_xlfn.XLOOKUP(PROYECTOS[[#This Row],[MUNICIPIO]],'4.CAP_ENDMNT'!B:B,'4.CAP_ENDMNT'!I:I,0,0,1) -> 2534414723 | AA2: =+_xlfn.XLOOKUP(PROYECTOS[[#This Row],[MUNICIPIO]],'4.CAP_ENDMNT'!B:B,'4.CAP_ENDMNT'!J:J,0,0,1) -> 0.17553469 | AB2: =+_xlfn.XLOOKUP(PROYECTOS[[#This Row],[MUNICIPIO]],'4.CAP_ENDMNT'!B:B,'4.CAP_ENDMNT'!K:K,0,0,1) -> 1.1903841e+10 | AC2: =+_xlfn.XLOOKUP(PROYECTOS[[#This Row],[MUNICIPIO]],'4.CAP_ENDMNT'!B:B,'4.CAP_ENDMNT'!L:L,0,0,1) -> 9.523073e+09 | AD2: =+_xlfn.XLOOKUP(PROYECTOS[[#This Row],[MUNICIPIO]],'4.CAP_ENDMNT'!B:B,'4.CAP_ENDMNT'!M:M,0,0,1) -> 7.1423047e+09 | AE2: =+_xlfn.XLOOKUP(PROYECTOS[[#This Row],[MUNICIPIO]],'4.CAP_ENDMNT'!B:B,'4.CAP_ENDMNT'!N:N,0,0,1) -> 1 | AF2: =+_xlfn.XLOOKUP(PROYECTOS[[#This Row],[MUNICIPIO]],'4.CAP_ENDMNT'!B:B,'4.CAP_ENDMNT'!O:O,0,0,1) -> 0.51487078 | AG2: =+_xlfn.XLOOKUP(PROYECTOS[[#This Row],[MUNICIPIO]],'4.CAP_ENDMNT'!B:B,'4.CAP_ENDMNT'!P:P,0,0,1) -> 0.8 | AH2: =+_xlfn.XLOOKUP(PROYECTOS[[#This Row],[MUNICIPIO]],'4.CAP_ENDMNT'!B:B,'4.CAP_ENDMNT'!Q:Q,0,0,1) -> Cumple | AI2: =+_xlfn.XLOOKUP(PROYECTOS[[#This Row],[MUNICIPIO]],'4.CAP_ENDMNT'!B:B,'4.CAP_ENDMNT'!V:V,0,0,1) -> 1.4284609e+09 | AJ2: =+_xlfn.XLOOKUP(PROYECTOS[[#This Row],[MUNICIPIO]],'4.CAP_ENDMNT'!B:B,'4.CAP_ENDMNT'!Y:Y,0,0,1) -> 1.1007549e+09
A3: 3 | B3: Intercambio vial sector 3 | C3: =+_xlfn.XLOOKUP(PROYECTOS[[#This Row],[ID_NECESIDAD]],'1.RADICADOS'!G:G,'1.RADICADOS'!C:C,0,0,1)*1 -> 45629 | D3: Barbosa | E3: =+_xlfn.XLOOKUP(PROYECTOS[[#This Row],[MUNICIPIO]],MUNICIPIOS!A:A,MUNICIPIOS!E:E,0,0,1) -> Valle de Aburrá | F3: =+_xlfn.XLOOKUP(PROYECTOS[[#This Row],[MUNICIPIO]],MUNICIPIOS!A:A,MUNICIPIOS!F:F,0,0,1) -> -75.331627 | G3: =+_xlfn.XLOOKUP(PROYECTOS[[#This Row],[MUNICIPIO]],MUNICIPIOS!A:A,MUNICIPIOS!G:G,0,0,1) -> 6,439195 | H3: =+_xlfn.XLOOKUP(PROYECTOS[[#This Row],[MUNICIPIO]],MUNICIPIOS!A:A,MUNICIPIOS!B:B,0,0,1) -> 0 | I3: =+_xlfn.XLOOKUP(PROYECTOS[[#This Row],[MUNICIPIO]],MUNICIPIOS!A:A,MUNICIPIOS!C:C,0,0,1) -> 0 | J3: {=_xlfn.TEXTJOIN(" ", TRUE, IF(radicados[ID PROYECTOS]=A3, radicados[RADICADO], ""))} -> 2024010111694 | K3: 3 | L3: 54654511129 | M3: Intercambio Vial | N3: Urbana | O3: Vía urbana mejorada | T3: =+_xlfn.XLOOKUP(PROYECTOS[[#This Row],[MUNICIPIO]],'4.CAP_ENDMNT'!B:B,'4.CAP_ENDMNT'!C:C,0,0,1) -> 4 | U3: =+_xlfn.XLOOKUP(PROYECTOS[[#This Row],[MUNICIPIO]],'4.CAP_ENDMNT'!B:B,'4.CAP_ENDMNT'!D:D,0,0,1) -> 5.6592203e+10 | V3: =+_xlfn.XLOOKUP(PROYECTOS[[#This Row],[MUNICIPIO]],'4.CAP_ENDMNT'!B:B,'4.CAP_ENDMNT'!E:E,0,0,1) -> 2.4375973e+10 | W3: =+_xlfn.XLOOKUP(PROYECTOS[[#This Row],[MUNICIPIO]],'4.CAP_ENDMNT'!B:B,'4.CAP_ENDMNT'!F:F,0,0,1) -> 3.2216231e+10 | X3: =+_xlfn.XLOOKUP(PROYECTOS[[#This Row],[MUNICIPIO]],'4.CAP_ENDMNT'!B:B,'4.CAP_ENDMNT'!G:G,0,0,1) -> 0 | Y3: =+_xlfn.XLOOKUP(PROYECTOS[[#This Row],[MUNICIPIO]],'4.CAP_ENDMNT'!B:B,'4.CAP_ENDMNT'!H:H,0,0,1) -> 1.5044963e+10 | Z3: =+_xlfn.XLOOKUP(PROYECTOS[[#This Row],[MUNICIPIO]],'4.CAP_ENDMNT'!B:B,'4.CAP_ENDMNT'!I:I,0,0,1) -> 1.5044963e+10 | AA3: =+_xlfn.XLOOKUP(PROYECTOS[[#This Row],[MUNICIPIO]],'4.CAP_ENDMNT'!B:B,'4.CAP_ENDMNT'!J:J,0,0,1) -> 0.26584869 | AB3: =+_xlfn.XLOOKUP(PROYECTOS[[#This Row],[MUNICIPIO]],'4.CAP_ENDMNT'!B:B,'4.CAP_ENDMNT'!K:K,0,0,1) -> 4.154724e+10 | AC3: =+_xlfn.XLOOKUP(PROYECTOS[[#This Row],[MUNICIPIO]],'4.CAP_ENDMNT'!B:B,'4.CAP_ENDMNT'!L:L,0,0,1) -> 3.3237792e+10 | AD3: =+_xlfn.XLOOKUP(PROYECTOS[[#This Row],[MUNICIPIO]],'4.CAP_ENDMNT'!B:B,'4.CAP_ENDMNT'!M:M,0,0,1) -> 2.4928344e+10 | AE3: =+_xlfn.XLOOKUP(PROYECTOS[[#This Row],[MUNICIPIO]],'4.CAP_ENDMNT'!B:B,'4.CAP_ENDMNT'!N:N,0,0,1) -> 0 | AF3: =+_xlfn.XLOOKUP(PROYECTOS[[#This Row],[MUNICIPIO]],'4.CAP_ENDMNT'!B:B,'4.CAP_ENDMNT'!O:O,0,0,1) -> 0.60385208 | AG3: =+_xlfn.XLOOKUP(PROYECTOS[[#This Row],[MUNICIPIO]],'4.CAP_ENDMNT'!B:B,'4.CAP_ENDMNT'!P:P,0,0,1) -> 0.8 | AH3: =+_xlfn.XLOOKUP(PROYECTOS[[#This Row],[MUNICIPIO]],'4.CAP_ENDMNT'!B:B,'4.CAP_ENDMNT'!Q:Q,0,0,1) -> Cumple | AI3: =+_xlfn.XLOOKUP(PROYECTOS[[#This Row],[MUNICIPIO]],'4.CAP_ENDMNT'!B:B,'4.CAP_ENDMNT'!V:V,0,0,1) -> 4.9856688e+09 | AJ3: =+_xlfn.XLOOKUP(PROYECTOS[[#This Row],[MUNICIPIO]],'4.CAP_ENDMNT'!B:B,'4.CAP_ENDMNT'!Y:Y,0,0,1) -> -3.1357431e+10
A4: 4 | B4: Construcción del Puente Biblioteca en el municipio de Rionegro - ADICION A PROYECTO EN EJECUCION | C4: =+_xlfn.XLOOKUP(PROYECTOS[[#This Row],[ID_NECESIDAD]],'1.RADICADOS'!G:G,'1.RADICADOS'!C:C,0,0,1)*1 -> 45476 | D4: Rionegro | E4: =+_xlfn.XLOOKUP(PROYECTOS[[#This Row],[MUNICIPIO]],MUNICIPIOS!A:A,MUNICIPIOS!E:E,0,0,1) -> Oriente | F4: =+_xlfn.XLOOKUP(PROYECTOS[[#This Row],[MUNICIPIO]],MUNICIPIOS!A:A,MUNICIPIOS!F:F,0,0,1) -> -75.377316 | G4: =+_xlfn.XLOOKUP(PROYECTOS[[#This Row],[MUNICIPIO]],MUNICIPIOS!A:A,MUNICIPIOS!G:G,0,0,1) -> 6,147148 | H4: =+_xlfn.XLOOKUP(PROYECTOS[[#This Row],[MUNICIPIO]],MUNICIPIOS!A:A,MUNICIPIOS!B:B,0,0,1) -> 0 | I4: =+_xlfn.XLOOKUP(PROYECTOS[[#This Row],[MUNICIPIO]],MUNICIPIOS!A:A,MUNICIPIOS!C:C,0,0,1) -> 0 | J4: {=_xlfn.TEXTJOIN(" ", TRUE, IF(radicados[ID PROYECTOS]=A4, radicados[RADICADO], ""))} -> 2024010105045 | K4: 3 | L4: 8594513471 | M4: Edificio Institucional | N4: N/A | O4: Equipamientos construidos | P4: Peticion por recursos para obra adicional | T4: =+_xlfn.XLOOKUP(PROYECTOS[[#This Row],[MUNICIPIO]],'4.CAP_ENDMNT'!B:B,'4.CAP_ENDMNT'!C:C,0,0,1) -> 1 | U4: =+_xlfn.XLOOKUP(PROYECTOS[[#This Row],[MUNICIPIO]],'4.CAP_ENDMNT'!B:B,'4.CAP_ENDMNT'!D:D,0,0,1) -> 5.0123644e+11 | V4: =+_xlfn.XLOOKUP(PROYECTOS[[#This Row],[MUNICIPIO]],'4.CAP_ENDMNT'!B:B,'4.CAP_ENDMNT'!E:E,0,0,1) -> 1.1250202e+11 | W4: =+_xlfn.XLOOKUP(PROYECTOS[[#This Row],[MUNICIPIO]],'4.CAP_ENDMNT'!B:B,'4.CAP_ENDMNT'!F:F,0,0,1) -> 3.8873442e+11 | X4: =+_xlfn.XLOOKUP(PROYECTOS[[#This Row],[MUNICIPIO]],'4.CAP_ENDMNT'!B:B,'4.CAP_ENDMNT'!G:G,0,0,1) -> 85394840514 | Y4: =+_xlfn.XLOOKUP(PROYECTOS[[#This Row],[MUNICIPIO]],'4.CAP_ENDMNT'!B:B,'4.CAP_ENDMNT'!H:H,0,0,1) -> 1.1410989e+11 | Z4: =+_xlfn.XLOOKUP(PROYECTOS[[#This Row],[MUNICIPIO]],'4.CAP_ENDMNT'!B:B,'4.CAP_ENDMNT'!I:I,0,0,1) -> 1.9950473e+11 | AA4: =+_xlfn.XLOOKUP(PROYECTOS[[#This Row],[MUNICIPIO]],'4.CAP_ENDMNT'!B:B,'4.CAP_ENDMNT'!J:J,0,0,1) -> 0.39802519 | AB4: =+_xlfn.XLOOKUP(PROYECTOS[[#This Row],[MUNICIPIO]],'4.CAP_ENDMNT'!B:B,'4.CAP_ENDMNT'!K:K,0,0,1) -> 3.0173171e+11 | AC4: =+_xlfn.XLOOKUP(PROYECTOS[[#This Row],[MUNICIPIO]],'4.CAP_ENDMNT'!B:B,'4.CAP_ENDMNT'!L:L,0,0,1) -> 2.4138537e+11 | AD4: =+_xlfn.XLOOKUP(PROYECTOS[[#This Row],[MUNICIPIO]],'4.CAP_ENDMNT'!B:B,'4.CAP_ENDMNT'!M:M,0,0,1) -> 1.8103903e+11 | AE4: =+_xlfn.XLOOKUP(PROYECTOS[[#This Row],[MUNICIPIO]],'4.CAP_ENDMNT'!B:B,'4.CAP_ENDMNT'!N:N,0,0,1) -> 0.42803417 | AF4: =+_xlfn.XLOOKUP(PROYECTOS[[#This Row],[MUNICIPIO]],'4.CAP_ENDMNT'!B:B,'4.CAP_ENDMNT'!O:O,0,0,1) -> 0.23207277 | AG4: =+_xlfn.XLOOKUP(PROYECTOS[[#This Row],[MUNICIPIO]],'4.CAP_ENDMNT'!B:B,'4.CAP_ENDMNT'!P:P,0,0,1) -> 0.65 | AH4: =+_xlfn.XLOOKUP(PROYECTOS[[#This Row],[MUNICIPIO]],'4.CAP_ENDMNT'!B:B,'4.CAP_ENDMNT'!Q:Q,0,0,1) -> Cumple | AI4: =+_xlfn.XLOOKUP(PROYECTOS[[#This Row],[MUNICIPIO]],'4.CAP_ENDMNT'!B:B,'4.CAP_ENDMNT'!V:V,0,0,1) -> 3.6207806e+10 | AJ4: =+_xlfn.XLOOKUP(PROYECTOS[[#This Row],[MUNICIPIO]],'4.CAP_ENDMNT'!B:B,'4.CAP_ENDMNT'!Y:Y,0,0,1) -> 1.9947085e+11
A5: 5 | B5: Pavimentación de la vía Santa Bárbara - Fredonia (ruta 25) Fredonia Código 25AN02 en el Plan de Desarrollo Departamental 2024 - 2027 | C5: =+_xlfn.XLOOKUP(PROYECTOS[[#This Row],[ID_NECESIDAD]],'1.RADICADOS'!G:G,'1.RADICADOS'!C:C,0,0,1)*1 -> 45338 | D5: Santa Bárbara | E5: =+_xlfn.XLOOKUP(PROYECTOS[[#This Row],[MUNICIPIO]],MUNICIPIOS!A:A,MUNICIPIOS!E:E,0,0,1) -> Suroeste | F5: =+_xlfn.XLOOKUP(PROYECTOS[[#This Row],[MUNICIPIO]],MUNICIPIOS!A:A,MUNICIPIOS!F:F,0,0,1) -> -75.567351 | G5: =+_xlfn.XLOOKUP(PROYECTOS[[#This Row],[MUNICIPIO]],MUNICIPIOS!A:A,MUNICIPIOS!G:G,0,0,1) -> 5,875527 | H5: =+_xlfn.XLOOKUP(PROYECTOS[[#This Row],[MUNICIPIO]],MUNICIPIOS!A:A,MUNICIPIOS!B:B,0,0,1) -> 0 | I5: =+_xlfn.XLOOKUP(PROYECTOS[[#This Row],[MUNICIPIO]],MUNICIPIOS!A:A,MUNICIPIOS!C:C,0,0,1) -> 0 | J5: {=_xlfn.TEXTJOIN(" ", TRUE, IF(radicados[ID PROYECTOS]=A5, radicados[RADICADO], ""))} -> 2024010070587 | K5: 1 | M5: Pavimento Flexible | N5: Segundo Orden | O5: Vías secundarias mejoradas | P5: Solicitud para incluir en PD 2024 pavimentacion de via secundaria Santa Barbara - Fredonia | T5: =+_xlfn.XLOOKUP(PROYECTOS[[#This Row],[MUNICIPIO]],'4.CAP_ENDMNT'!B:B,'4.CAP_ENDMNT'!C:C,0,0,1) -> 6 | U5: =+_xlfn.XLOOKUP(PROYECTOS[[#This Row],[MUNICIPIO]],'4.CAP_ENDMNT'!B:B,'4.CAP_ENDMNT'!D:D,0,0,1) -> 1.2109127e+10 | V5: =+_xlfn.XLOOKUP(PROYECTOS[[#This Row],[MUNICIPIO]],'4.CAP_ENDMNT'!B:B,'4.CAP_ENDMNT'!E:E,0,0,1) -> 6.4850763e+09 | W5: =+_xlfn.XLOOKUP(PROYECTOS[[#This Row],[MUNICIPIO]],'4.CAP_ENDMNT'!B:B,'4.CAP_ENDMNT'!F:F,0,0,1) -> 5.624051e+09 | X5: =+_xlfn.XLOOKUP(PROYECTOS[[#This Row],[MUNICIPIO]],'4.CAP_ENDMNT'!B:B,'4.CAP_ENDMNT'!G:G,0,0,1) -> 3662325591 | Y5: =+_xlfn.XLOOKUP(PROYECTOS[[#This Row],[MUNICIPIO]],'4.CAP_ENDMNT'!B:B,'4.CAP_ENDMNT'!H:H,0,0,1) -> 0 | Z5: =+_xlfn.XLOOKUP(PROYECTOS[[#This Row],[MUNICIPIO]],'4.CAP_ENDMNT'!B:B,'4.CAP_ENDMNT'!I:I,0,0,1) -> 3662325591 | AA5: =+_xlfn.XLOOKUP(PROYECTOS[[#This Row],[MUNICIPIO]],'4.CAP_ENDMNT'!B:B,'4.CAP_ENDMNT'!J:J,0,0,1) -> 0.3024434 | AB5: =+_xlfn.XLOOKUP(PROYECTOS[[#This Row],[MUNICIPIO]],'4.CAP_ENDMNT'!B:B,'4.CAP_ENDMNT'!K:K,0,0,1) -> 8.4468017e+09 | AC5: =+_xlfn.XLOOKUP(PROYECTOS[[#This Row],[MUNICIPIO]],'4.CAP_ENDMNT'!B:B,'4.CAP_ENDMNT'!L:L,0,0,1) -> 6.7574414e+09 | AD5: =+_xlfn.XLOOKUP(PROYECTOS[[#This Row],[MUNICIPIO]],'4.CAP_ENDMNT'!B:B,'4.CAP_ENDMNT'!M:M,0,0,1) -> 5.068081e+09 | AE5: =+_xlfn.XLOOKUP(PROYECTOS[[#This Row],[MUNICIPIO]],'4.CAP_ENDMNT'!B:B,'4.CAP_ENDMNT'!N:N,0,0,1) -> 1 | AF5: =+_xlfn.XLOOKUP(PROYECTOS[[#This Row],[MUNICIPIO]],'4.CAP_ENDMNT'!B:B,'4.CAP_ENDMNT'!O:O,0,0,1) -> 0.55253262 | AG5: =+_xlfn.XLOOKUP(PROYECTOS[[#This Row],[MUNICIPIO]],'4.CAP_ENDMNT'!B:B,'4.CAP_ENDMNT'!P:P,0,0,1) -> 0.8 | AH5: =+_xlfn.XLOOKUP(PROYECTOS[[#This Row],[MUNICIPIO]],'4.CAP_ENDMNT'!B:B,'4.CAP_ENDMNT'!Q:Q,0,0,1) -> Cumple | AI5: =+_xlfn.XLOOKUP(PROYECTOS[[#This Row],[MUNICIPIO]],'4.CAP_ENDMNT'!B:B,'4.CAP_ENDMNT'!V:V,0,0,1) -> 1.0136162e+09 | AJ5: =+_xlfn.XLOOKUP(PROYECTOS[[#This Row],[MUNICIPIO]],'4.CAP_ENDMNT'!B:B,'4.CAP_ENDMNT'!Y:Y,0,0,1) -> 5.2816972e+09
A6: 6 | B6: Placa huella Abejorral - Purima | C6: =+_xlfn.XLOOKUP(PROYECTOS[[#This Row],[ID_NECESIDAD]],'1.RADICADOS'!G:G,'1.RADICADOS'!C:C,0,0,1)*1 -> 45341 | D6: Abejorral | E6: =+_xlfn.XLOOKUP(PROYECTOS[[#This Row],[MUNICIPIO]],MUNICIPIOS!A:A,MUNICIPIOS!E:E,0,0,1) -> Oriente | F6: =+_xlfn.XLOOKUP(PROYECTOS[[#This Row],[MUNICIPIO]],MUNICIPIOS!A:A,MUNICIPIOS!F:F,0,0,1) -> -75.428739 | G6: =+_xlfn.XLOOKUP(PROYECTOS[[#This Row],[MUNICIPIO]],MUNICIPIOS!A:A,MUNICIPIOS!G:G,0,0,1) -> 5.789315 | H6: =+_xlfn.XLOOKUP(PROYECTOS[[#This Row],[MUNICIPIO]],MUNICIPIOS!A:A,MUNICIPIOS!B:B,0,0,1) -> 0 | I6: =+_xlfn.XLOOKUP(PROYECTOS[[#This Row],[MUNICIPIO]],MUNICIPIOS!A:A,MUNICIPIOS!C:C,0,0,1) -> 1 | J6: {=_xlfn.TEXTJOIN(" ", TRUE, IF(radicados[ID PROYECTOS]=A6, radicados[RADICADO], ""))} -> 2024010071479 | K6: 1 | M6: Placa huella | N6: Tercer Orden | O6: Vías terciarias mejoradas | P6: No tiene E&D. GOB 50% MUNIC 30% COM 20% | Q6: 1 | R6: SGR Regionales 60% | S6: Placa huellas 2025-2 | T6: =+_xlfn.XLOOKUP(PROYECTOS[[#This Row],[MUNICIPIO]],'4.CAP_ENDMNT'!B:B,'4.CAP_ENDMNT'!C:C,0,0,1) -> 6 | U6: =+_xlfn.XLOOKUP(PROYECTOS[[#This Row],[MUNICIPIO]],'4.CAP_ENDMNT'!B:B,'4.CAP_ENDMNT'!D:D,0,0,1) -> 1.5030771e+10 | V6: =+_xlfn.XLOOKUP(PROYECTOS[[#This Row],[MUNICIPIO]],'4.CAP_ENDMNT'!B:B,'4.CAP_ENDMNT'!E:E,0,0,1) -> 4.4096727e+09 | W6: =+_xlfn.XLOOKUP(PROYECTOS[[#This Row],[MUNICIPIO]],'4.CAP_ENDMNT'!B:B,'4.CAP_ENDMNT'!F:F,0,0,1) -> 1.0621098e+10 | X6: =+_xlfn.XLOOKUP(PROYECTOS[[#This Row],[MUNICIPIO]],'4.CAP_ENDMNT'!B:B,'4.CAP_ENDMNT'!G:G,0,0,1) -> 1969764886 | Y6: =+_xlfn.XLOOKUP(PROYECTOS[[#This Row],[MUNICIPIO]],'4.CAP_ENDMNT'!B:B,'4.CAP_ENDMNT'!H:H,0,0,1) -> 0 | Z6: =+_xlfn.XLOOKUP(PROYECTOS[[#This Row],[MUNICIPIO]],'4.CAP_ENDMNT'!B:B,'4.CAP_ENDMNT'!I:I,0,0,1) -> 1969764886 | AA6: =+_xlfn.XLOOKUP(PROYECTOS[[#This Row],[MUNICIPIO]],'4.CAP_ENDMNT'!B:B,'4.CAP_ENDMNT'!J:J,0,0,1) -> 0.13104883 | AB6: =+_xlfn.XLOOKUP(PROYECTOS[[#This Row],[MUNICIPIO]],'4.CAP_ENDMNT'!B:B,'4.CAP_ENDMNT'!K:K,0,0,1) -> 1.3061006e+10 | AC6: =+_xlfn.XLOOKUP(PROYECTOS[[#This Row],[MUNICIPIO]],'4.CAP_ENDMNT'!B:B,'4.CAP_ENDMNT'!L:L,0,0,1) -> 1.0448805e+10 | AD6: =+_xlfn.XLOOKUP(PROYECTOS[[#This Row],[MUNICIPIO]],'4.CAP_ENDMNT'!B:B,'4.CAP_ENDMNT'!M:M,0,0,1) -> 7.8366036e+09 | AE6: =+_xlfn.XLOOKUP(PROYECTOS[[#This Row],[MUNICIPIO]],'4.CAP_ENDMNT'!B:B,'4.CAP_ENDMNT'!N:N,0,0,1) -> 1 | AF6: =+_xlfn.XLOOKUP(PROYECTOS[[#This Row],[MUNICIPIO]],'4.CAP_ENDMNT'!B:B,'4.CAP_ENDMNT'!O:O,0,0,1) -> 0.39507659 | AG6: =+_xlfn.XLOOKUP(PROYECTOS[[#This Row],[MUNICIPIO]],'4.CAP_ENDMNT'!B:B,'4.CAP_ENDMNT'!P:P,0,0,1) -> 0.8 | AH6: =+_xlfn.XLOOKUP(PROYECTOS[[#This Row],[MUNICIPIO]],'4.CAP_ENDMNT'!B:B,'4.CAP_ENDMNT'!Q:Q,0,0,1) -> Cumple | AI6: =+_xlfn.XLOOKUP(PROYECTOS[[#This Row],[MUNICIPIO]],'4.CAP_ENDMNT'!B:B,'4.CAP_ENDMNT'!V:V,0,0,1) -> 1.5673207e+09 | AJ6: =+_xlfn.XLOOKUP(PROYECTOS[[#This Row],[MUNICIPIO]],'4.CAP_ENDMNT'!B:B,'4.CAP_ENDMNT'!Y:Y,0,0,1) -> 4.2011717e+09
A7: 7 | B7: Pavimentación de 11km de la vía Riogrande - Bellavista (05237VT073) | C7: =+_xlfn.XLOOKUP(PROYECTOS[[#This Row],[ID_NECESIDAD]],'1.RADICADOS'!G:G,'1.RADICADOS'!C:C,0,0,1)*1 -> 45308 | D7: Donmatías | E7: =+_xlfn.XLOOKUP(PROYECTOS[[#This Row],[MUNICIPIO]],MUNICIPIOS!A:A,MUNICIPIOS!E:E,0,0,1) -> Norte | F7: =+_xlfn.XLOOKUP(PROYECTOS[[#This Row],[MUNICIPIO]],MUNICIPIOS!A:A,MUNICIPIOS!F:F,0,0,1) -> -75.39263 | G7: =+_xlfn.XLOOKUP(PROYECTOS[[#This Row],[MUNICIPIO]],MUNICIPIOS!A:A,MUNICIPIOS!G:G,0,0,1) -> 6,485603 | H7: =+_xlfn.XLOOKUP(PROYECTOS[[#This Row],[MUNICIPIO]],MUNICIPIOS!A:A,MUNICIPIOS!B:B,0,0,1) -> 0 | I7: =+_xlfn.XLOOKUP(PROYECTOS[[#This Row],[MUNICIPIO]],MUNICIPIOS!A:A,MUNICIPIOS!C:C,0,0,1) -> 0 | J7: {=_xlfn.TEXTJOIN(" ", TRUE, IF(radicados[ID PROYECTOS]=A7, radicados[RADICADO], ""))} -> 2024010019030 | K7: 1 | M7: Pavimento Flexible | N7: Tercer Orden | O7: Vías terciarias mejoradas | T7: =+_xlfn.XLOOKUP(PROYECTOS[[#This Row],[MUNICIPIO]],'4.CAP_ENDMNT'!B:B,'4.CAP_ENDMNT'!C:C,0,0,1) -> 6 | U7: =+_xlfn.XLOOKUP(PROYECTOS[[#This Row],[MUNICIPIO]],'4.CAP_ENDMNT'!B:B,'4.CAP_ENDMNT'!D:D,0,0,1) -> 2.4529039e+10 | V7: =+_xlfn.XLOOKUP(PROYECTOS[[#This Row],[MUNICIPIO]],'4.CAP_ENDMNT'!B:B,'4.CAP_ENDMNT'!E:E,0,0,1) -> 8.9730124e+09 | W7: =+_xlfn.XLOOKUP(PROYECTOS[[#This Row],[MUNICIPIO]],'4.CAP_ENDMNT'!B:B,'4.CAP_ENDMNT'!F:F,0,0,1) -> 1.5556027e+10 | X7: =+_xlfn.XLOOKUP(PROYECTOS[[#This Row],[MUNICIPIO]],'4.CAP_ENDMNT'!B:B,'4.CAP_ENDMNT'!G:G,0,0,1) -> 7973050390 | Y7: =+_xlfn.XLOOKUP(PROYECTOS[[#This Row],[MUNICIPIO]],'4.CAP_ENDMNT'!B:B,'4.CAP_ENDMNT'!H:H,0,0,1) -> 1625381984 | Z7: =+_xlfn.XLOOKUP(PROYECTOS[[#This Row],[MUNICIPIO]],'4.CAP_ENDMNT'!B:B,'4.CAP_ENDMNT'!I:I,0,0,1) -> 9598432374 | AA7: =+_xlfn.XLOOKUP(PROYECTOS[[#This Row],[MUNICIPIO]],'4.CAP_ENDMNT'!B:B,'4.CAP_ENDMNT'!J:J,0,0,1) -> 0.39130894 | AB7: =+_xlfn.XLOOKUP(PROYECTOS[[#This Row],[MUNICIPIO]],'4.CAP_ENDMNT'!B:B,'4.CAP_ENDMNT'!K:K,0,0,1) -> 1.4930607e+10 | AC7: =+_xlfn.XLOOKUP(PROYECTOS[[#This Row],[MUNICIPIO]],'4.CAP_ENDMNT'!B:B,'4.CAP_ENDMNT'!L:L,0,0,1) -> 1.1944486e+10 | AD7: =+_xlfn.XLOOKUP(PROYECTOS[[#This Row],[MUNICIPIO]],'4.CAP_ENDMNT'!B:B,'4.CAP_ENDMNT'!M:M,0,0,1) -> 8.9583642e+09 | AE7: =+_xlfn.XLOOKUP(PROYECTOS[[#This Row],[MUNICIPIO]],'4.CAP_ENDMNT'!B:B,'4.CAP_ENDMNT'!N:N,0,0,1) -> 0.83066172 | AF7: =+_xlfn.XLOOKUP(PROYECTOS[[#This Row],[MUNICIPIO]],'4.CAP_ENDMNT'!B:B,'4.CAP_ENDMNT'!O:O,0,0,1) -> 0.53024344 | AG7: =+_xlfn.XLOOKUP(PROYECTOS[[#This Row],[MUNICIPIO]],'4.CAP_ENDMNT'!B:B,'4.CAP_ENDMNT'!P:P,0,0,1) -> 0.8 | AH7: =+_xlfn.XLOOKUP(PROYECTOS[[#This Row],[MUNICIPIO]],'4.CAP_ENDMNT'!B:B,'4.CAP_ENDMNT'!Q:Q,0,0,1) -> Cumple | AI7: =+_xlfn.XLOOKUP(PROYECTOS[[#This Row],[MUNICIPIO]],'4.CAP_ENDMNT'!B:B,'4.CAP_ENDMNT'!V:V,0,0,1) -> 1.7916728e+09 | AJ7: =+_xlfn.XLOOKUP(PROYECTOS[[#This Row],[MUNICIPIO]],'4.CAP_ENDMNT'!B:B,'4.CAP_ENDMNT'!Y:Y,0,0,1) -> -8.1641356e+09
A8: 8 | B8: Solicitud de apoyo y acompañamiento integral a la Gestión territorial - Remitido por el ministerio de ambiente | C8: =+_xlfn.XLOOKUP(PROYECTOS[[#This Row],[ID_NECESIDAD]],'1.RADICADOS'!G:G,'1.RADICADOS'!C:C,0,0,1)*1 -> 45308 | D8: Carepa | E8: =+_xlfn.XLOOKUP(PROYECTOS[[#This Row],[MUNICIPIO]],MUNICIPIOS!A:A,MUNICIPIOS!E:E,0,0,1) -> Urabá | F8: =+_xlfn.XLOOKUP(PROYECTOS[[#This Row],[MUNICIPIO]],MUNICIPIOS!A:A,MUNICIPIOS!F:F,0,0,1) -> -76.652652 | G8: =+_xlfn.XLOOKUP(PROYECTOS[[#This Row],[MUNICIPIO]],MUNICIPIOS!A:A,MUNICIPIOS!G:G,0,0,1) -> 7,755148 | H8: =+_xlfn.XLOOKUP(PROYECTOS[[#This Row],[MUNICIPIO]],MUNICIPIOS!A:A,MUNICIPIOS!B:B,0,0,1) -> 1 | I8: =+_xlfn.XLOOKUP(PROYECTOS[[#This Row],[MUNICIPIO]],MUNICIPIOS!A:A,MUNICIPIOS!C:C,0,0,1) -> 1 | J8: {=_xlfn.TEXTJOIN(" ", TRUE, IF(radicados[ID PROYECTOS]=A8, radicados[RADICADO], ""))} -> 2024010020020 | K8: N/A | M8: Otros | N8: N/A | O8: Otros | T8: =+_xlfn.XLOOKUP(PROYECTOS[[#This Row],[MUNICIPIO]],'4.CAP_ENDMNT'!B:B,'4.CAP_ENDMNT'!C:C,0,0,1) -> 6 | U8: =+_xlfn.XLOOKUP(PROYECTOS[[#This Row],[MUNICIPIO]],'4.CAP_ENDMNT'!B:B,'4.CAP_ENDMNT'!D:D,0,0,1) -> 3.1551502e+10 | V8: =+_xlfn.XLOOKUP(PROYECTOS[[#This Row],[MUNICIPIO]],'4.CAP_ENDMNT'!B:B,'4.CAP_ENDMNT'!E:E,0,0,1) -> 1.2896902e+10 | W8: =+_xlfn.XLOOKUP(PROYECTOS[[#This Row],[MUNICIPIO]],'4.CAP_ENDMNT'!B:B,'4.CAP_ENDMNT'!F:F,0,0,1) -> 1.86546e+10 | X8: =+_xlfn.XLOOKUP(PROYECTOS[[#This Row],[MUNICIPIO]],'4.CAP_ENDMNT'!B:B,'4.CAP_ENDMNT'!G:G,0,0,1) -> 4320802475 | Y8: =+_xlfn.XLOOKUP(PROYECTOS[[#This Row],[MUNICIPIO]],'4.CAP_ENDMNT'!B:B,'4.CAP_ENDMNT'!H:H,0,0,1) -> 2.1185629e+09 | Z8: =+_xlfn.XLOOKUP(PROYECTOS[[#This Row],[MUNICIPIO]],'4.CAP_ENDMNT'!B:B,'4.CAP_ENDMNT'!I:I,0,0,1) -> 6.4393654e+09 | AA8: =+_xlfn.XLOOKUP(PROYECTOS[[#This Row],[MUNICIPIO]],'4.CAP_ENDMNT'!B:B,'4.CAP_ENDMNT'!J:J,0,0,1) -> 0.20409062 | AB8: =+_xlfn.XLOOKUP(PROYECTOS[[#This Row],[MUNICIPIO]],'4.CAP_ENDMNT'!B:B,'4.CAP_ENDMNT'!K:K,0,0,1) -> 2.5112136e+10 | AC8: =+_xlfn.XLOOKUP(PROYECTOS[[#This Row],[MUNICIPIO]],'4.CAP_ENDMNT'!B:B,'4.CAP_ENDMNT'!L:L,0,0,1) -> 2.0089709e+10 | AD8: =+_xlfn.XLOOKUP(PROYECTOS[[#This Row],[MUNICIPIO]],'4.CAP_ENDMNT'!B:B,'4.CAP_ENDMNT'!M:M,0,0,1) -> 1.5067282e+10 | AE8: =+_xlfn.XLOOKUP(PROYECTOS[[#This Row],[MUNICIPIO]],'4.CAP_ENDMNT'!B:B,'4.CAP_ENDMNT'!N:N,0,0,1) -> 0.67099818 | AF8: =+_xlfn.XLOOKUP(PROYECTOS[[#This Row],[MUNICIPIO]],'4.CAP_ENDMNT'!B:B,'4.CAP_ENDMNT'!O:O,0,0,1) -> 0.60103296 | AG8: =+_xlfn.XLOOKUP(PROYECTOS[[#This Row],[MUNICIPIO]],'4.CAP_ENDMNT'!B:B,'4.CAP_ENDMNT'!P:P,0,0,1) -> 0.8 | AH8: =+_xlfn.XLOOKUP(PROYECTOS[[#This Row],[MUNICIPIO]],'4.CAP_ENDMNT'!B:B,'4.CAP_ENDMNT'!Q:Q,0,0,1) -> Cumple | AI8: =+_xlfn.XLOOKUP(PROYECTOS[[#This Row],[MUNICIPIO]],'4.CAP_ENDMNT'!B:B,'4.CAP_ENDMNT'!V:V,0,0,1) -> 3.0134564e+09 | AJ8: =+_xlfn.XLOOKUP(PROYECTOS[[#This Row],[MUNICIPIO]],'4.CAP_ENDMNT'!B:B,'4.CAP_ENDMNT'!Y:Y,0,0,1) -> 1.0290789e+10
A9: 9 | B9: Pavimentación de la vía que conduce al corregimiento portachuelo en Amalfí desde el municipio de Vegachí (05858VT61) "Alejandría - Cascajo" | C9: =+_xlfn.XLOOKUP(PROYECTOS[[#This Row],[ID_NECESIDAD]],'1.RADICADOS'!G:G,'1.RADICADOS'!C:C,0,0,1)*1 -> 45414 | D9: Vegachí | E9: =+_xlfn.XLOOKUP(PROYECTOS[[#This Row],[MUNICIPIO]],MUNICIPIOS!A:A,MUNICIPIOS!E:E,0,0,1) -> Nordeste | F9: =+_xlfn.XLOOKUP(PROYECTOS[[#This Row],[MUNICIPIO]],MUNICIPIOS!A:A,MUNICIPIOS!F:F,0,0,1) -> -74.798714 | G9: =+_xlfn.XLOOKUP(PROYECTOS[[#This Row],[MUNICIPIO]],MUNICIPIOS!A:A,MUNICIPIOS!G:G,0,0,1) -> 6.773525 | H9: =+_xlfn.XLOOKUP(PROYECTOS[[#This Row],[MUNICIPIO]],MUNICIPIOS!A:A,MUNICIPIOS!B:B,0,0,1) -> 0 | I9: =+_xlfn.XLOOKUP(PROYECTOS[[#This Row],[MUNICIPIO]],MUNICIPIOS!A:A,MUNICIPIOS!C:C,0,0,1) -> 1 | J9: {=_xlfn.TEXTJOIN(" ", TRUE, IF(radicados[ID PROYECTOS]=A9, radicados[RADICADO], ""))} -> 2024010048752 | K9: 1 | M9: Pavimento Flexible | N9: Tercer Orden | O9: Vías terciarias mejoradas | T9: =+_xlfn.XLOOKUP(PROYECTOS[[#This Row],[MUNICIPIO]],'4.CAP_ENDMNT'!B:B,'4.CAP_ENDMNT'!C:C,0,0,1) -> 6 | U9: =+_xlfn.XLOOKUP(PROYECTOS[[#This Row],[MUNICIPIO]],'4.CAP_ENDMNT'!B:B,'4.CAP_ENDMNT'!D:D,0,0,1) -> 1.4438256e+10 | V9: =+_xlfn.XLOOKUP(PROYECTOS[[#This Row],[MUNICIPIO]],'4.CAP_ENDMNT'!B:B,'4.CAP_ENDMNT'!E:E,0,0,1) -> 4.6682009e+09 | W9: =+_xlfn.XLOOKUP(PROYECTOS[[#This Row],[MUNICIPIO]],'4.CAP_ENDMNT'!B:B,'4.CAP_ENDMNT'!F:F,0,0,1) -> 9.770055e+09 | X9: =+_xlfn.XLOOKUP(PROYECTOS[[#This Row],[MUNICIPIO]],'4.CAP_ENDMNT'!B:B,'4.CAP_ENDMNT'!G:G,0,0,1) -> 2534414723 | Y9: =+_xlfn.XLOOKUP(PROYECTOS[[#This Row],[MUNICIPIO]],'4.CAP_ENDMNT'!B:B,'4.CAP_ENDMNT'!H:H,0,0,1) -> 0 | Z9: =+_xlfn.XLOOKUP(PROYECTOS[[#This Row],[MUNICIPIO]],'4.CAP_ENDMNT'!B:B,'4.CAP_ENDMNT'!I:I,0,0,1) -> 2534414723 | AA9: =+_xlfn.XLOOKUP(PROYECTOS[[#This Row],[MUNICIPIO]],'4.CAP_ENDMNT'!B:B,'4.CAP_ENDMNT'!J:J,0,0,1) -> 0.17553469 | AB9: =+_xlfn.XLOOKUP(PROYECTOS[[#This Row],[MUNICIPIO]],'4.CAP_ENDMNT'!B:B,'4.CAP_ENDMNT'!K:K,0,0,1) -> 1.1903841e+10 | AC9: =+_xlfn.XLOOKUP(PROYECTOS[[#This Row],[MUNICIPIO]],'4.CAP_ENDMNT'!B:B,'4.CAP_ENDMNT'!L:L,0,0,1) -> 9.523073e+09 | AD9: =+_xlfn.XLOOKUP(PROYECTOS[[#This Row],[MUNICIPIO]],'4.CAP_ENDMNT'!B:B,'4.CAP_ENDMNT'!M:M,0,0,1) -> 7.1423047e+09 | AE9: =+_xlfn.XLOOKUP(PROYECTOS[[#This Row],[MUNICIPIO]],'4.CAP_ENDMNT'!B:B,'4.CAP_ENDMNT'!N:N,0,0,1) -> 1 | AF9: =+_xlfn.XLOOKUP(PROYECTOS[[#This Row],[MUNICIPIO]],'4.CAP_ENDMNT'!B:B,'4.CAP_ENDMNT'!O:O,0,0,1) -> 0.51487078 | AG9: =+_xlfn.XLOOKUP(PROYECTOS[[#This Row],[MUNICIPIO]],'4.CAP_ENDMNT'!B:B,'4.CAP_ENDMNT'!P:P,0,0,1) -> 0.8 | AH9: =+_xlfn.XLOOKUP(PROYECTOS[[#This Row],[MUNICIPIO]],'4.CAP_ENDMNT'!B:B,'4.CAP_ENDMNT'!Q:Q,0,0,1) -> Cumple | AI9: =+_xlfn.XLOOKUP(PROYECTOS[[#This Row],[MUNICIPIO]],'4.CAP_ENDMNT'!B:B,'4.CAP_ENDMNT'!V:V,0,0,1) -> 1.4284609e+09 | AJ9: =+_xlfn.XLOOKUP(PROYECTOS[[#This Row],[MUNICIPIO]],'4.CAP_ENDMNT'!B:B,'4.CAP_ENDMNT'!Y:Y,0,0,1) -> 1.1007549e+09
A10: 10 | B10: Propuesta proyectos en desarrollo Bajo Cauca Antioqueño. Finca la Mariela - Caucasía Antioquia | C10: =+_xlfn.XLOOKUP(PROYECTOS[[#This Row],[ID_NECESIDAD]],'1.RADICADOS'!G:G,'1.RADICADOS'!C:C,0,0,1)*1 -> 45293 | D10: Caucasia | E10: =+_xlfn.XLOOKUP(PROYECTOS[[#This Row],[MUNICIPIO]],MUNICIPIOS!A:A,MUNICIPIOS!E:E,0,0,1) -> Bajo Cauca | F10: =+_xlfn.XLOOKUP(PROYECTOS[[#This Row],[MUNICIPIO]],MUNICIPIOS!A:A,MUNICIPIOS!F:F,0,0,1) -> -75.197996 | G10: =+_xlfn.XLOOKUP(PROYECTOS[[#This Row],[MUNICIPIO]],MUNICIPIOS!A:A,MUNICIPIOS!G:G,0,0,1) -> 7,977278 | H10: =+_xlfn.XLOOKUP(PROYECTOS[[#This Row],[MUNICIPIO]],MUNICIPIOS!A:A,MUNICIPIOS!B:B,0,0,1) -> 1 | I10: =+_xlfn.XLOOKUP(PROYECTOS[[#This Row],[MUNICIPIO]],MUNICIPIOS!A:A,MUNICIPIOS!C:C,0,0,1) -> 1 | J10: {=_xlfn.TEXTJOIN(" ", TRUE, IF(radicados[ID PROYECTOS]=A10, radicados[RADICADO], ""))} -> 2024010043395 | K10: 2 | M10: Parque | N10: N/A | O10: Espacio público adecuado | P10: Son tres proyectos para los cuales CEDRA busca apoyo | T10: =+_xlfn.XLOOKUP(PROYECTOS[[#This Row],[MUNICIPIO]],'4.CAP_ENDMNT'!B:B,'4.CAP_ENDMNT'!C:C,0,0,1) -> 5 | U10: =+_xlfn.XLOOKUP(PROYECTOS[[#This Row],[MUNICIPIO]],'4.CAP_ENDMNT'!B:B,'4.CAP_ENDMNT'!D:D,0,0,1) -> 5.5415011e+10 | V10: =+_xlfn.XLOOKUP(PROYECTOS[[#This Row],[MUNICIPIO]],'4.CAP_ENDMNT'!B:B,'4.CAP_ENDMNT'!E:E,0,0,1) -> 2.4252117e+10 | W10: =+_xlfn.XLOOKUP(PROYECTOS[[#This Row],[MUNICIPIO]],'4.CAP_ENDMNT'!B:B,'4.CAP_ENDMNT'!F:F,0,0,1) -> 3.1162894e+10 | X10: =+_xlfn.XLOOKUP(PROYECTOS[[#This Row],[MUNICIPIO]],'4.CAP_ENDMNT'!B:B,'4.CAP_ENDMNT'!G:G,0,0,1) -> 8970758412 | Y10: =+_xlfn.XLOOKUP(PROYECTOS[[#This Row],[MUNICIPIO]],'4.CAP_ENDMNT'!B:B,'4.CAP_ENDMNT'!H:H,0,0,1) -> 3.5721739e+09 | Z10: =+_xlfn.XLOOKUP(PROYECTOS[[#This Row],[MUNICIPIO]],'4.CAP_ENDMNT'!B:B,'4.CAP_ENDMNT'!I:I,0,0,1) -> 1.2542932e+10 | AA10: =+_xlfn.XLOOKUP(PROYECTOS[[#This Row],[MUNICIPIO]],'4.CAP_ENDMNT'!B:B,'4.CAP_ENDMNT'!J:J,0,0,1) -> 0.22634539 | AB10: =+_xlfn.XLOOKUP(PROYECTOS[[#This Row],[MUNICIPIO]],'4.CAP_ENDMNT'!B:B,'4.CAP_ENDMNT'!K:K,0,0,1) -> 4.2872079e+10 | AC10: =+_xlfn.XLOOKUP(PROYECTOS[[#This Row],[MUNICIPIO]],'4.CAP_ENDMNT'!B:B,'4.CAP_ENDMNT'!L:L,0,0,1) -> 3.4297663e+10 | AD10: =+_xlfn.XLOOKUP(PROYECTOS[[#This Row],[MUNICIPIO]],'4.CAP_ENDMNT'!B:B,'4.CAP_ENDMNT'!M:M,0,0,1) -> 2.5723247e+10 | AE10: =+_xlfn.XLOOKUP(PROYECTOS[[#This Row],[MUNICIPIO]],'4.CAP_ENDMNT'!B:B,'4.CAP_ENDMNT'!N:N,0,0,1) -> 0.71520425 | AF10: =+_xlfn.XLOOKUP(PROYECTOS[[#This Row],[MUNICIPIO]],'4.CAP_ENDMNT'!B:B,'4.CAP_ENDMNT'!O:O,0,0,1) -> 0.67052011 | AG10: =+_xlfn.XLOOKUP(PROYECTOS[[#This Row],[MUNICIPIO]],'4.CAP_ENDMNT'!B:B,'4.CAP_ENDMNT'!P:P,0,0,1) -> 0.8 | AH10: =+_xlfn.XLOOKUP(PROYECTOS[[#This Row],[MUNICIPIO]],'4.CAP_ENDMNT'!B:B,'4.CAP_ENDMNT'!Q:Q,0,0,1) -> Cumple | AI10: =+_xlfn.XLOOKUP(PROYECTOS[[#This Row],[MUNICIPIO]],'4.CAP_ENDMNT'!B:B,'4.CAP_ENDMNT'!V:V,0,0,1) -> 5.1446495e+09 | AJ10: =+_xlfn.XLOOKUP(PROYECTOS[[#This Row],[MUNICIPIO]],'4.CAP_ENDMNT'!B:B,'4.CAP_ENDMNT'!Y:Y,0,0,1) -> 3.549127e+09
A11: 11 | B11: Recuperación pavimentación y mantenimiento a la malla vial que comunica al municipio de Armenia con el municipio de Titiribí | C11: =+_xlfn.XLOOKUP(PROYECTOS[[#This Row],[ID_NECESIDAD]],'1.RADICADOS'!G:G,'1.RADICADOS'!C:C,0,0,1)*1 -> 45338 | D11: Armenia | E11: =+_xlfn.XLOOKUP(PROYECTOS[[#This Row],[MUNICIPIO]],MUNICIPIOS!A:A,MUNICIPIOS!E:E,0,0,1) -> Occidente | F11: =+_xlfn.XLOOKUP(PROYECTOS[[#This Row],[MUNICIPIO]],MUNICIPIOS!A:A,MUNICIPIOS!F:F,0,0,1) -> -75.786647 | G11: =+_xlfn.XLOOKUP(PROYECTOS[[#This Row],[MUNICIPIO]],MUNICIPIOS!A:A,MUNICIPIOS!G:G,0,0,1) -> 6,155667 | H11: =+_xlfn.XLOOKUP(PROYECTOS[[#This Row],[MUNICIPIO]],MUNICIPIOS!A:A,MUNICIPIOS!B:B,0,0,1) -> 0 | I11: =+_xlfn.XLOOKUP(PROYECTOS[[#This Row],[MUNICIPIO]],MUNICIPIOS!A:A,MUNICIPIOS!C:C,0,0,1) -> 0 | J11: {=_xlfn.TEXTJOIN(" ", TRUE, IF(radicados[ID PROYECTOS]=A11, radicados[RADICADO], ""))} -> 2024010068835 | K11: 1 | M11: Pavimento Flexible | N11: Tercer Orden | O11: Vías terciarias mejoradas | T11: =+_xlfn.XLOOKUP(PROYECTOS[[#This Row],[MUNICIPIO]],'4.CAP_ENDMNT'!B:B,'4.CAP_ENDMNT'!C:C,0,0,1) -> 6 | U11: =+_xlfn.XLOOKUP(PROYECTOS[[#This Row],[MUNICIPIO]],'4.CAP_ENDMNT'!B:B,'4.CAP_ENDMNT'!D:D,0,0,1) -> 4.6679398e+09 | V11: =+_xlfn.XLOOKUP(PROYECTOS[[#This Row],[MUNICIPIO]],'4.CAP_ENDMNT'!B:B,'4.CAP_ENDMNT'!E:E,0,0,1) -> 2.0296029e+09 | W11: =+_xlfn.XLOOKUP(PROYECTOS[[#This Row],[MUNICIPIO]],'4.CAP_ENDMNT'!B:B,'4.CAP_ENDMNT'!F:F,0,0,1) -> 2.6383368e+09 | X11: =+_xlfn.XLOOKUP(PROYECTOS[[#This Row],[MUNICIPIO]],'4.CAP_ENDMNT'!B:B,'4.CAP_ENDMNT'!G:G,0,0,1) -> 355713183 | Y11: =+_xlfn.XLOOKUP(PROYECTOS[[#This Row],[MUNICIPIO]],'4.CAP_ENDMNT'!B:B,'4.CAP_ENDMNT'!H:H,0,0,1) -> 0 | Z11: =+_xlfn.XLOOKUP(PROYECTOS[[#This Row],[MUNICIPIO]],'4.CAP_ENDMNT'!B:B,'4.CAP_ENDMNT'!I:I,0,0,1) -> 355713183 | AA11: =+_xlfn.XLOOKUP(PROYECTOS[[#This Row],[MUNICIPIO]],'4.CAP_ENDMNT'!B:B,'4.CAP_ENDMNT'!J:J,0,0,1) -> 0.076203464 | AB11: =+_xlfn.XLOOKUP(PROYECTOS[[#This Row],[MUNICIPIO]],'4.CAP_ENDMNT'!B:B,'4.CAP_ENDMNT'!K:K,0,0,1) -> 4.3122266e+09 | AC11: =+_xlfn.XLOOKUP(PROYECTOS[[#This Row],[MUNICIPIO]],'4.CAP_ENDMNT'!B:B,'4.CAP_ENDMNT'!L:L,0,0,1) -> 3.4497813e+09 | AD11: =+_xlfn.XLOOKUP(PROYECTOS[[#This Row],[MUNICIPIO]],'4.CAP_ENDMNT'!B:B,'4.CAP_ENDMNT'!M:M,0,0,1) -> 2.587336e+09 | AE11: =+_xlfn.XLOOKUP(PROYECTOS[[#This Row],[MUNICIPIO]],'4.CAP_ENDMNT'!B:B,'4.CAP_ENDMNT'!N:N,0,0,1) -> 1 | AF11: =+_xlfn.XLOOKUP(PROYECTOS[[#This Row],[MUNICIPIO]],'4.CAP_ENDMNT'!B:B,'4.CAP_ENDMNT'!O:O,0,0,1) -> 0.65637282 | AG11: =+_xlfn.XLOOKUP(PROYECTOS[[#This Row],[MUNICIPIO]],'4.CAP_ENDMNT'!B:B,'4.CAP_ENDMNT'!P:P,0,0,1) -> 0.8 | AH11: =+_xlfn.XLOOKUP(PROYECTOS[[#This Row],[MUNICIPIO]],'4.CAP_ENDMNT'!B:B,'4.CAP_ENDMNT'!Q:Q,0,0,1) -> Cumple | AI11: =+_xlfn.XLOOKUP(PROYECTOS[[#This Row],[MUNICIPIO]],'4.CAP_ENDMNT'!B:B,'4.CAP_ENDMNT'!V:V,0,0,1) -> 5.1746719e+08 | AJ11: =+_xlfn.XLOOKUP(PROYECTOS[[#This Row],[MUNICIPIO]],'4.CAP_ENDMNT'!B:B,'4.CAP_ENDMNT'!Y:Y,0,0,1) -> 3.1048031e+09
A12: 13 | B12: Vía entre corregimiento de San Pablo y vereda Naranjal (Codigo 05856VT104) | C12: 45292 | D12: Támesis | E12: =+_xlfn.XLOOKUP(PROYECTOS[[#This Row],[MUNICIPIO]],MUNICIPIOS!A:A,MUNICIPIOS!E:E,0,0,1) -> Suroeste | F12: =+_xlfn.XLOOKUP(PROYECTOS[[#This Row],[MUNICIPIO]],MUNICIPIOS!A:A,MUNICIPIOS!F:F,0,0,1) -> -75.714429 | G12: =+_xlfn.XLOOKUP(PROYECTOS[[#This Row],[MUNICIPIO]],MUNICIPIOS!A:A,MUNICIPIOS!G:G,0,0,1) -> 5.664645 | H12: =+_xlfn.XLOOKUP(PROYECTOS[[#This Row],[MUNICIPIO]],MUNICIPIOS!A:A,MUNICIPIOS!B:B,0,0,1) -> 0 | I12: =+_xlfn.XLOOKUP(PROYECTOS[[#This Row],[MUNICIPIO]],MUNICIPIOS!A:A,MUNICIPIOS!C:C,0,0,1) -> 0 | J12: {=_xlfn.TEXTJOIN(" ", TRUE, IF(radicados[ID PROYECTOS]=A12, radicados[RADICADO], ""))} | K12: 1 | M12: Placa huella | N12: Tercer Orden | O12: Vías terciarias mejoradas | P12: Via 2.5km que comunica corregimientos de San Pablo y la vereda el Narajal. FASE 1 | T12: =+_xlfn.XLOOKUP(PROYECTOS[[#This Row],[MUNICIPIO]],'4.CAP_ENDMNT'!B:B,'4.CAP_ENDMNT'!C:C,0,0,1) -> 6 | U12: =+_xlfn.XLOOKUP(PROYECTOS[[#This Row],[MUNICIPIO]],'4.CAP_ENDMNT'!B:B,'4.CAP_ENDMNT'!D:D,0,0,1) -> 1.3939578e+10 | V12: =+_xlfn.XLOOKUP(PROYECTOS[[#This Row],[MUNICIPIO]],'4.CAP_ENDMNT'!B:B,'4.CAP_ENDMNT'!E:E,0,0,1) -> 5.4086452e+09 | W12: =+_xlfn.XLOOKUP(PROYECTOS[[#This Row],[MUNICIPIO]],'4.CAP_ENDMNT'!B:B,'4.CAP_ENDMNT'!F:F,0,0,1) -> 8.5309327e+09 | X12: =+_xlfn.XLOOKUP(PROYECTOS[[#This Row],[MUNICIPIO]],'4.CAP_ENDMNT'!B:B,'4.CAP_ENDMNT'!G:G,0,0,1) -> 2408239973 | Y12: =+_xlfn.XLOOKUP(PROYECTOS[[#This Row],[MUNICIPIO]],'4.CAP_ENDMNT'!B:B,'4.CAP_ENDMNT'!H:H,0,0,1) -> 812109375 | Z12: =+_xlfn.XLOOKUP(PROYECTOS[[#This Row],[MUNICIPIO]],'4.CAP_ENDMNT'!B:B,'4.CAP_ENDMNT'!I:I,0,0,1) -> 3220349348 | AA12: =+_xlfn.XLOOKUP(PROYECTOS[[#This Row],[MUNICIPIO]],'4.CAP_ENDMNT'!B:B,'4.CAP_ENDMNT'!J:J,0,0,1) -> 0.23102201 | AB12: =+_xlfn.XLOOKUP(PROYECTOS[[#This Row],[MUNICIPIO]],'4.CAP_ENDMNT'!B:B,'4.CAP_ENDMNT'!K:K,0,0,1) -> 1.0719229e+10 | AC12: =+_xlfn.XLOOKUP(PROYECTOS[[#This Row],[MUNICIPIO]],'4.CAP_ENDMNT'!B:B,'4.CAP_ENDMNT'!L:L,0,0,1) -> 8.5753828e+09 | AD12: =+_xlfn.XLOOKUP(PROYECTOS[[#This Row],[MUNICIPIO]],'4.CAP_ENDMNT'!B:B,'4.CAP_ENDMNT'!M:M,0,0,1) -> 6.4315371e+09 | AE12: =+_xlfn.XLOOKUP(PROYECTOS[[#This Row],[MUNICIPIO]],'4.CAP_ENDMNT'!B:B,'4.CAP_ENDMNT'!N:N,0,0,1) -> 0.74781948 | AF12: =+_xlfn.XLOOKUP(PROYECTOS[[#This Row],[MUNICIPIO]],'4.CAP_ENDMNT'!B:B,'4.CAP_ENDMNT'!O:O,0,0,1) -> 0.4814897 | AG12: =+_xlfn.XLOOKUP(PROYECTOS[[#This Row],[MUNICIPIO]],'4.CAP_ENDMNT'!B:B,'4.CAP_ENDMNT'!P:P,0,0,1) -> 0.8 | AH12: =+_xlfn.XLOOKUP(PROYECTOS[[#This Row],[MUNICIPIO]],'4.CAP_ENDMNT'!B:B,'4.CAP_ENDMNT'!Q:Q,0,0,1) -> Cumple | AI12: =+_xlfn.XLOOKUP(PROYECTOS[[#This Row],[MUNICIPIO]],'4.CAP_ENDMNT'!B:B,'4.CAP_ENDMNT'!V:V,0,0,1) -> 1.2863074e+09 | AJ12: =+_xlfn.XLOOKUP(PROYECTOS[[#This Row],[MUNICIPIO]],'4.CAP_ENDMNT'!B:B,'4.CAP_ENDMNT'!Y:Y,0,0,1) -> -1.0772172e+10
A13: 14 | B13: Solicitud de Pavimentación vía Peñalisa - La Bodega - Tarso La Bodega - Pueblorico con codigo 25BAN03-1 | C13: =+_xlfn.XLOOKUP(PROYECTOS[[#This Row],[ID_NECESIDAD]],'1.RADICADOS'!G:G,'1.RADICADOS'!C:C,0,0,1)*1 -> 45348 | D13: Tarso | E13: =+_xlfn.XLOOKUP(PROYECTOS[[#This Row],[MUNICIPIO]],MUNICIPIOS!A:A,MUNICIPIOS!E:E,0,0,1) -> Suroeste | F13: =+_xlfn.XLOOKUP(PROYECTOS[[#This Row],[MUNICIPIO]],MUNICIPIOS!A:A,MUNICIPIOS!F:F,0,0,1) -> -75.822956 | G13: =+_xlfn.XLOOKUP(PROYECTOS[[#This Row],[MUNICIPIO]],MUNICIPIOS!A:A,MUNICIPIOS!G:G,0,0,1) -> 5.864542 | H13: =+_xlfn.XLOOKUP(PROYECTOS[[#This Row],[MUNICIPIO]],MUNICIPIOS!A:A,MUNICIPIOS!B:B,0,0,1) -> 0 | I13: =+_xlfn.XLOOKUP(PROYECTOS[[#This Row],[MUNICIPIO]],MUNICIPIOS!A:A,MUNICIPIOS!C:C,0,0,1) -> 0 | J13: {=_xlfn.TEXTJOIN(" ", TRUE, IF(radicados[ID PROYECTOS]=A13, radicados[RADICADO], ""))} -> 2024010084216 | K13: 2 | M13: Pavimento Flexible | N13: Segundo Orden | O13: Vías secundarias mejoradas | P13: Peticion se ha hecho en multiples ocasiones. Reclaman un intervencion que nunca se hizo y piden apoyo | T13: =+_xlfn.XLOOKUP(PROYECTOS[[#This Row],[MUNICIPIO]],'4.CAP_ENDMNT'!B:B,'4.CAP_ENDMNT'!C:C,0,0,1) -> 6 | U13: =+_xlfn.XLOOKUP(PROYECTOS[[#This Row],[MUNICIPIO]],'4.CAP_ENDMNT'!B:B,'4.CAP_ENDMNT'!D:D,0,0,1) -> 9.2972046e+09 | V13: =+_xlfn.XLOOKUP(PROYECTOS[[#This Row],[MUNICIPIO]],'4.CAP_ENDMNT'!B:B,'4.CAP_ENDMNT'!E:E,0,0,1) -> 4.6509009e+09 | W13: =+_xlfn.XLOOKUP(PROYECTOS[[#This Row],[MUNICIPIO]],'4.CAP_ENDMNT'!B:B,'4.CAP_ENDMNT'!F:F,0,0,1) -> 4.6463037e+09 | X13: =+_xlfn.XLOOKUP(PROYECTOS[[#This Row],[MUNICIPIO]],'4.CAP_ENDMNT'!B:B,'4.CAP_ENDMNT'!G:G,0,0,1) -> 1308996768 | Y13: =+_xlfn.XLOOKUP(PROYECTOS[[#This Row],[MUNICIPIO]],'4.CAP_ENDMNT'!B:B,'4.CAP_ENDMNT'!H:H,0,0,1) -> 0 | Z13: =+_xlfn.XLOOKUP(PROYECTOS[[#This Row],[MUNICIPIO]],'4.CAP_ENDMNT'!B:B,'4.CAP_ENDMNT'!I:I,0,0,1) -> 1308996768 | AA13: =+_xlfn.XLOOKUP(PROYECTOS[[#This Row],[MUNICIPIO]],'4.CAP_ENDMNT'!B:B,'4.CAP_ENDMNT'!J:J,0,0,1) -> 0.14079466 | AB13: =+_xlfn.XLOOKUP(PROYECTOS[[#This Row],[MUNICIPIO]],'4.CAP_ENDMNT'!B:B,'4.CAP_ENDMNT'!K:K,0,0,1) -> 7.9882078e+09 | AC13: =+_xlfn.XLOOKUP(PROYECTOS[[#This Row],[MUNICIPIO]],'4.CAP_ENDMNT'!B:B,'4.CAP_ENDMNT'!L:L,0,0,1) -> 6.3905663e+09 | AD13: =+_xlfn.XLOOKUP(PROYECTOS[[#This Row],[MUNICIPIO]],'4.CAP_ENDMNT'!B:B,'4.CAP_ENDMNT'!M:M,0,0,1) -> 4.7929247e+09 | AE13: =+_xlfn.XLOOKUP(PROYECTOS[[#This Row],[MUNICIPIO]],'4.CAP_ENDMNT'!B:B,'4.CAP_ENDMNT'!N:N,0,0,1) -> 1 | AF13: =+_xlfn.XLOOKUP(PROYECTOS[[#This Row],[MUNICIPIO]],'4.CAP_ENDMNT'!B:B,'4.CAP_ENDMNT'!O:O,0,0,1) -> 0.67267671 | AG13: =+_xlfn.XLOOKUP(PROYECTOS[[#This Row],[MUNICIPIO]],'4.CAP_ENDMNT'!B:B,'4.CAP_ENDMNT'!P:P,0,0,1) -> 0.8 | AH13: =+_xlfn.XLOOKUP(PROYECTOS[[#This Row],[MUNICIPIO]],'4.CAP_ENDMNT'!B:B,'4.CAP_ENDMNT'!Q:Q,0,0,1) -> Cumple | AI13: =+_xlfn.XLOOKUP(PROYECTOS[[#This Row],[MUNICIPIO]],'4.CAP_ENDMNT'!B:B,'4.CAP_ENDMNT'!V:V,0,0,1) -> 9.5858494e+08 | AJ13: =+_xlfn.XLOOKUP(PROYECTOS[[#This Row],[MUNICIPIO]],'4.CAP_ENDMNT'!B:B,'4.CAP_ENDMNT'!Y:Y,0,0,1) -> -1.2177885e+09
A14: 15 | B14: Mejoramiento de la red vial urbana Municipio de San josé de la Montaña | C14: =+_xlfn.XLOOKUP(PROYECTOS[[#This Row],[ID_NECESIDAD]],'1.RADICADOS'!G:G,'1.RADICADOS'!C:C,0,0,1)*1 -> 45322 | D14: San José de la Montaña | E14: =+_xlfn.XLOOKUP(PROYECTOS[[#This Row],[MUNICIPIO]],MUNICIPIOS!A:A,MUNICIPIOS!E:E,0,0,1) -> Norte | F14: =+_xlfn.XLOOKUP(PROYECTOS[[#This Row],[MUNICIPIO]],MUNICIPIOS!A:A,MUNICIPIOS!F:F,0,0,1) -> -75.683352 | G14: =+_xlfn.XLOOKUP(PROYECTOS[[#This Row],[MUNICIPIO]],MUNICIPIOS!A:A,MUNICIPIOS!G:G,0,0,1) -> 6,85009 | H14: =+_xlfn.XLOOKUP(PROYECTOS[[#This Row],[MUNICIPIO]],MUNICIPIOS!A:A,MUNICIPIOS!B:B,0,0,1) -> 0 | I14: =+_xlfn.XLOOKUP(PROYECTOS[[#This Row],[MUNICIPIO]],MUNICIPIOS!A:A,MUNICIPIOS!C:C,0,0,1) -> 0 | J14: {=_xlfn.TEXTJOIN(" ", TRUE, IF(radicados[ID PROYECTOS]=A14, radicados[RADICADO], ""))} -> 2024010041849 | K14: 1 | M14: Pavimento Flexible | N14: Urbana | O14: Vía urbana mejorada | T14: =+_xlfn.XLOOKUP(PROYECTOS[[#This Row],[MUNICIPIO]],'4.CAP_ENDMNT'!B:B,'4.CAP_ENDMNT'!C:C,0,0,1) -> 6 | U14: =+_xlfn.XLOOKUP(PROYECTOS[[#This Row],[MUNICIPIO]],'4.CAP_ENDMNT'!B:B,'4.CAP_ENDMNT'!D:D,0,0,1) -> 5.4378026e+09 | V14: =+_xlfn.XLOOKUP(PROYECTOS[[#This Row],[MUNICIPIO]],'4.CAP_ENDMNT'!B:B,'4.CAP_ENDMNT'!E:E,0,0,1) -> 2.1952578e+09 | W14: =+_xlfn.XLOOKUP(PROYECTOS[[#This Row],[MUNICIPIO]],'4.CAP_ENDMNT'!B:B,'4.CAP_ENDMNT'!F:F,0,0,1) -> 3.2425447e+09 | X14: =+_xlfn.XLOOKUP(PROYECTOS[[#This Row],[MUNICIPIO]],'4.CAP_ENDMNT'!B:B,'4.CAP_ENDMNT'!G:G,0,0,1) -> 1389038990 | Y14: =+_xlfn.XLOOKUP(PROYECTOS[[#This Row],[MUNICIPIO]],'4.CAP_ENDMNT'!B:B,'4.CAP_ENDMNT'!H:H,0,0,1) -> 0 | Z14: =+_xlfn.XLOOKUP(PROYECTOS[[#This Row],[MUNICIPIO]],'4.CAP_ENDMNT'!B:B,'4.CAP_ENDMNT'!I:I,0,0,1) -> 1389038990 | AA14: =+_xlfn.XLOOKUP(PROYECTOS[[#This Row],[MUNICIPIO]],'4.CAP_ENDMNT'!B:B,'4.CAP_ENDMNT'!J:J,0,0,1) -> 0.25544123 | AB14: =+_xlfn.XLOOKUP(PROYECTOS[[#This Row],[MUNICIPIO]],'4.CAP_ENDMNT'!B:B,'4.CAP_ENDMNT'!K:K,0,0,1) -> 4.0487636e+09 | AC14: =+_xlfn.XLOOKUP(PROYECTOS[[#This Row],[MUNICIPIO]],'4.CAP_ENDMNT'!B:B,'4.CAP_ENDMNT'!L:L,0,0,1) -> 3.2390109e+09 | AD14: =+_xlfn.XLOOKUP(PROYECTOS[[#This Row],[MUNICIPIO]],'4.CAP_ENDMNT'!B:B,'4.CAP_ENDMNT'!M:M,0,0,1) -> 2.4292581e+09 | AE14: =+_xlfn.XLOOKUP(PROYECTOS[[#This Row],[MUNICIPIO]],'4.CAP_ENDMNT'!B:B,'4.CAP_ENDMNT'!N:N,0,0,1) -> 1 | AF14: =+_xlfn.XLOOKUP(PROYECTOS[[#This Row],[MUNICIPIO]],'4.CAP_ENDMNT'!B:B,'4.CAP_ENDMNT'!O:O,0,0,1) -> 0.7423058 | AG14: =+_xlfn.XLOOKUP(PROYECTOS[[#This Row],[MUNICIPIO]],'4.CAP_ENDMNT'!B:B,'4.CAP_ENDMNT'!P:P,0,0,1) -> 0.8 | AH14: =+_xlfn.XLOOKUP(PROYECTOS[[#This Row],[MUNICIPIO]],'4.CAP_ENDMNT'!B:B,'4.CAP_ENDMNT'!Q:Q,0,0,1) -> Cumple | AI14: =+_xlfn.XLOOKUP(PROYECTOS[[#This Row],[MUNICIPIO]],'4.CAP_ENDMNT'!B:B,'4.CAP_ENDMNT'!V:V,0,0,1) -> 4.8585163e+08 | AJ14: =+_xlfn.XLOOKUP(PROYECTOS[[#This Row],[MUNICIPIO]],'4.CAP_ENDMNT'!B:B,'4.CAP_ENDMNT'!Y:Y,0,0,1) -> -1.4155937e+10
A15: 16 | B15: Mejoramiento de vías rurales en los municipios de Belmira y San José de la Montaña Antioquia | C15: =+_xlfn.XLOOKUP(PROYECTOS[[#This Row],[ID_NECESIDAD]],'1.RADICADOS'!G:G,'1.RADICADOS'!C:C,0,0,1)*1 -> 45475 | D15: San José de la Montaña | E15: =+_xlfn.XLOOKUP(PROYECTOS[[#This Row],[MUNICIPIO]],MUNICIPIOS!A:A,MUNICIPIOS!E:E,0,0,1) -> Norte | F15: =+_xlfn.XLOOKUP(PROYECTOS[[#This Row],[MUNICIPIO]],MUNICIPIOS!A:A,MUNICIPIOS!F:F,0,0,1) -> -75.683352 | G15: =+_xlfn.XLOOKUP(PROYECTOS[[#This Row],[MUNICIPIO]],MUNICIPIOS!A:A,MUNICIPIOS!G:G,0,0,1) -> 6,85009 | H15: =+_xlfn.XLOOKUP(PROYECTOS[[#This Row],[MUNICIPIO]],MUNICIPIOS!A:A,MUNICIPIOS!B:B,0,0,1) -> 0 | I15: =+_xlfn.XLOOKUP(PROYECTOS[[#This Row],[MUNICIPIO]],MUNICIPIOS!A:A,MUNICIPIOS!C:C,0,0,1) -> 0 | J15: {=_xlfn.TEXTJOIN(" ", TRUE, IF(radicados[ID PROYECTOS]=A15, radicados[RADICADO], ""))} -> 2024010054228 | K15: 3 | L15: 3142000000 | M15: Pavimento Flexible | N15: Tercer Orden | O15: Vías terciarias mejoradas | T15: =+_xlfn.XLOOKUP(PROYECTOS[[#This Row],[MUNICIPIO]],'4.CAP_ENDMNT'!B:B,'4.CAP_ENDMNT'!C:C,0,0,1) -> 6 | U15: =+_xlfn.XLOOKUP(PROYECTOS[[#This Row],[MUNICIPIO]],'4.CAP_ENDMNT'!B:B,'4.CAP_ENDMNT'!D:D,0,0,1) -> 5.4378026e+09 | V15: =+_xlfn.XLOOKUP(PROYECTOS[[#This Row],[MUNICIPIO]],'4.CAP_ENDMNT'!B:B,'4.CAP_ENDMNT'!E:E,0,0,1) -> 2.1952578e+09 | W15: =+_xlfn.XLOOKUP(PROYECTOS[[#This Row],[MUNICIPIO]],'4.CAP_ENDMNT'!B:B,'4.CAP_ENDMNT'!F:F,0,0,1) -> 3.2425447e+09 | X15: =+_xlfn.XLOOKUP(PROYECTOS[[#This Row],[MUNICIPIO]],'4.CAP_ENDMNT'!B:B,'4.CAP_ENDMNT'!G:G,0,0,1) -> 1389038990 | Y15: =+_xlfn.XLOOKUP(PROYECTOS[[#This Row],[MUNICIPIO]],'4.CAP_ENDMNT'!B:B,'4.CAP_ENDMNT'!H:H,0,0,1) -> 0 | Z15: =+_xlfn.XLOOKUP(PROYECTOS[[#This Row],[MUNICIPIO]],'4.CAP_ENDMNT'!B:B,'4.CAP_ENDMNT'!I:I,0,0,1) -> 1389038990 | AA15: =+_xlfn.XLOOKUP(PROYECTOS[[#This Row],[MUNICIPIO]],'4.CAP_ENDMNT'!B:B,'4.CAP_ENDMNT'!J:J,0,0,1) -> 0.25544123 | AB15: =+_xlfn.XLOOKUP(PROYECTOS[[#This Row],[MUNICIPIO]],'4.CAP_ENDMNT'!B:B,'4.CAP_ENDMNT'!K:K,0,0,1) -> 4.0487636e+09 | AC15: =+_xlfn.XLOOKUP(PROYECTOS[[#This Row],[MUNICIPIO]],'4.CAP_ENDMNT'!B:B,'4.CAP_ENDMNT'!L:L,0,0,1) -> 3.2390109e+09 | AD15: =+_xlfn.XLOOKUP(PROYECTOS[[#This Row],[MUNICIPIO]],'4.CAP_ENDMNT'!B:B,'4.CAP_ENDMNT'!M:M,0,0,1) -> 2.4292581e+09 | AE15: =+_xlfn.XLOOKUP(PROYECTOS[[#This Row],[MUNICIPIO]],'4.CAP_ENDMNT'!B:B,'4.CAP_ENDMNT'!N:N,0,0,1) -> 1 | AF15: =+_xlfn.XLOOKUP(PROYECTOS[[#This Row],[MUNICIPIO]],'4.CAP_ENDMNT'!B:B,'4.CAP_ENDMNT'!O:O,0,0,1) -> 0.7423058 | AG15: =+_xlfn.XLOOKUP(PROYECTOS[[#This Row],[MUNICIPIO]],'4.CAP_ENDMNT'!B:B,'4.CAP_ENDMNT'!P:P,0,0,1) -> 0.8 | AH15: =+_xlfn.XLOOKUP(PROYECTOS[[#This Row],[MUNICIPIO]],'4.CAP_ENDMNT'!B:B,'4.CAP_ENDMNT'!Q:Q,0,0,1) -> Cumple | AI15: =+_xlfn.XLOOKUP(PROYECTOS[[#This Row],[MUNICIPIO]],'4.CAP_ENDMNT'!B:B,'4.CAP_ENDMNT'!V:V,0,0,1) -> 4.8585163e+08 | AJ15: =+_xlfn.XLOOKUP(PROYECTOS[[#This Row],[MUNICIPIO]],'4.CAP_ENDMNT'!B:B,'4.CAP_ENDMNT'!Y:Y,0,0,1) -> -1.4155937e+10
A16: 17 | B16: Solicitud pavimentación vía corregimiento Marsella | C16: =+_xlfn.XLOOKUP(PROYECTOS[[#This Row],[ID_NECESIDAD]],'1.RADICADOS'!G:G,'1.RADICADOS'!C:C,0,0,1)*1 -> 45306 | D16: Fredonia | E16: =+_xlfn.XLOOKUP(PROYECTOS[[#This Row],[MUNICIPIO]],MUNICIPIOS!A:A,MUNICIPIOS!E:E,0,0,1) -> Suroeste | F16: =+_xlfn.XLOOKUP(PROYECTOS[[#This Row],[MUNICIPIO]],MUNICIPIOS!A:A,MUNICIPIOS!F:F,0,0,1) -> -75.675072 | G16: =+_xlfn.XLOOKUP(PROYECTOS[[#This Row],[MUNICIPIO]],MUNICIPIOS!A:A,MUNICIPIOS!G:G,0,0,1) -> 5,928039 | H16: =+_xlfn.XLOOKUP(PROYECTOS[[#This Row],[MUNICIPIO]],MUNICIPIOS!A:A,MUNICIPIOS!B:B,0,0,1) -> 0 | I16: =+_xlfn.XLOOKUP(PROYECTOS[[#This Row],[MUNICIPIO]],MUNICIPIOS!A:A,MUNICIPIOS!C:C,0,0,1) -> 0 | J16: {=_xlfn.TEXTJOIN(" ", TRUE, IF(radicados[ID PROYECTOS]=A16, radicados[RADICADO], ""))} -> 2024010013378 | K16: 1 | M16: Pavimento Flexible | N16: Segundo Orden | O16: Vías secundarias mejoradas | P16: Peticion para pavimentar via de segundo orden | T16: =+_xlfn.XLOOKUP(PROYECTOS[[#This Row],[MUNICIPIO]],'4.CAP_ENDMNT'!B:B,'4.CAP_ENDMNT'!C:C,0,0,1) -> 6 | U16: =+_xlfn.XLOOKUP(PROYECTOS[[#This Row],[MUNICIPIO]],'4.CAP_ENDMNT'!B:B,'4.CAP_ENDMNT'!D:D,0,0,1) -> 1.7515986e+10 | V16: =+_xlfn.XLOOKUP(PROYECTOS[[#This Row],[MUNICIPIO]],'4.CAP_ENDMNT'!B:B,'4.CAP_ENDMNT'!E:E,0,0,1) -> 8.3467649e+09 | W16: =+_xlfn.XLOOKUP(PROYECTOS[[#This Row],[MUNICIPIO]],'4.CAP_ENDMNT'!B:B,'4.CAP_ENDMNT'!F:F,0,0,1) -> 9.1692212e+09 | X16: =+_xlfn.XLOOKUP(PROYECTOS[[#This Row],[MUNICIPIO]],'4.CAP_ENDMNT'!B:B,'4.CAP_ENDMNT'!G:G,0,0,1) -> 0 | Y16: =+_xlfn.XLOOKUP(PROYECTOS[[#This Row],[MUNICIPIO]],'4.CAP_ENDMNT'!B:B,'4.CAP_ENDMNT'!H:H,0,0,1) -> 6328650461 | Z16: =+_xlfn.XLOOKUP(PROYECTOS[[#This Row],[MUNICIPIO]],'4.CAP_ENDMNT'!B:B,'4.CAP_ENDMNT'!I:I,0,0,1) -> 6328650461 | AA16: =+_xlfn.XLOOKUP(PROYECTOS[[#This Row],[MUNICIPIO]],'4.CAP_ENDMNT'!B:B,'4.CAP_ENDMNT'!J:J,0,0,1) -> 0.36130712 | AB16: =+_xlfn.XLOOKUP(PROYECTOS[[#This Row],[MUNICIPIO]],'4.CAP_ENDMNT'!B:B,'4.CAP_ENDMNT'!K:K,0,0,1) -> 1.1187336e+10 | AC16: =+_xlfn.XLOOKUP(PROYECTOS[[#This Row],[MUNICIPIO]],'4.CAP_ENDMNT'!B:B,'4.CAP_ENDMNT'!L:L,0,0,1) -> 8.9498685e+09 | AD16: =+_xlfn.XLOOKUP(PROYECTOS[[#This Row],[MUNICIPIO]],'4.CAP_ENDMNT'!B:B,'4.CAP_ENDMNT'!M:M,0,0,1) -> 6.7124014e+09 | AE16: =+_xlfn.XLOOKUP(PROYECTOS[[#This Row],[MUNICIPIO]],'4.CAP_ENDMNT'!B:B,'4.CAP_ENDMNT'!N:N,0,0,1) -> 0 | AF16: =+_xlfn.XLOOKUP(PROYECTOS[[#This Row],[MUNICIPIO]],'4.CAP_ENDMNT'!B:B,'4.CAP_ENDMNT'!O:O,0,0,1) -> 0.67376313 | AG16: =+_xlfn.XLOOKUP(PROYECTOS[[#This Row],[MUNICIPIO]],'4.CAP_ENDMNT'!B:B,'4.CAP_ENDMNT'!P:P,0,0,1) -> 0.8 | AH16: =+_xlfn.XLOOKUP(PROYECTOS[[#This Row],[MUNICIPIO]],'4.CAP_ENDMNT'!B:B,'4.CAP_ENDMNT'!Q:Q,0,0,1) -> Cumple | AI16: =+_xlfn.XLOOKUP(PROYECTOS[[#This Row],[MUNICIPIO]],'4.CAP_ENDMNT'!B:B,'4.CAP_ENDMNT'!V:V,0,0,1) -> 1.3424803e+09 | AJ16: =+_xlfn.XLOOKUP(PROYECTOS[[#This Row],[MUNICIPIO]],'4.CAP_ENDMNT'!B:B,'4.CAP_ENDMNT'!Y:Y,0,0,1) -> 3.2809622e+09
A17: 18 | B17: Construcción de pavimento rígido en vías del casco urbano del municipio de San Pedro de Urabá Antiquia | C17: =+_xlfn.XLOOKUP(PROYECTOS[[#This Row],[ID_NECESIDAD]],'1.RADICADOS'!G:G,'1.RADICADOS'!C:C,0,0,1)*1 -> 45406 | D17: San Pedro de Urabá | E17: =+_xlfn.XLOOKUP(PROYECTOS[[#This Row],[MUNICIPIO]],MUNICIPIOS!A:A,MUNICIPIOS!E:E,0,0,1) -> Urabá | F17: =+_xlfn.XLOOKUP(PROYECTOS[[#This Row],[MUNICIPIO]],MUNICIPIOS!A:A,MUNICIPIOS!F:F,0,0,1) -> -76.380567 | G17: =+_xlfn.XLOOKUP(PROYECTOS[[#This Row],[MUNICIPIO]],MUNICIPIOS!A:A,MUNICIPIOS!G:G,0,0,1) -> 8,276884 | H17: =+_xlfn.XLOOKUP(PROYECTOS[[#This Row],[MUNICIPIO]],MUNICIPIOS!A:A,MUNICIPIOS!B:B,0,0,1) -> 1 | I17: =+_xlfn.XLOOKUP(PROYECTOS[[#This Row],[MUNICIPIO]],MUNICIPIOS!A:A,MUNICIPIOS!C:C,0,0,1) -> 1 | J17: {=_xlfn.TEXTJOIN(" ", TRUE, IF(radicados[ID PROYECTOS]=A17, radicados[RADICADO], ""))} -> 2024010179553 | K17: 3 | M17: Pavimento Rígido | N17: Urbana | O17: Vía urbana mejorada | T17: =+_xlfn.XLOOKUP(PROYECTOS[[#This Row],[MUNICIPIO]],'4.CAP_ENDMNT'!B:B,'4.CAP_ENDMNT'!C:C,0,0,1) -> 6 | U17: =+_xlfn.XLOOKUP(PROYECTOS[[#This Row],[MUNICIPIO]],'4.CAP_ENDMNT'!B:B,'4.CAP_ENDMNT'!D:D,0,0,1) -> 1.9508373e+10 | V17: =+_xlfn.XLOOKUP(PROYECTOS[[#This Row],[MUNICIPIO]],'4.CAP_ENDMNT'!B:B,'4.CAP_ENDMNT'!E:E,0,0,1) -> 5.3898343e+09 | W17: =+_xlfn.XLOOKUP(PROYECTOS[[#This Row],[MUNICIPIO]],'4.CAP_ENDMNT'!B:B,'4.CAP_ENDMNT'!F:F,0,0,1) -> 1.4118538e+10 | X17: =+_xlfn.XLOOKUP(PROYECTOS[[#This Row],[MUNICIPIO]],'4.CAP_ENDMNT'!B:B,'4.CAP_ENDMNT'!G:G,0,0,1) -> 2594281047 | Y17: =+_xlfn.XLOOKUP(PROYECTOS[[#This Row],[MUNICIPIO]],'4.CAP_ENDMNT'!B:B,'4.CAP_ENDMNT'!H:H,0,0,1) -> 1833333333 | Z17: =+_xlfn.XLOOKUP(PROYECTOS[[#This Row],[MUNICIPIO]],'4.CAP_ENDMNT'!B:B,'4.CAP_ENDMNT'!I:I,0,0,1) -> 4427614380 | AA17: =+_xlfn.XLOOKUP(PROYECTOS[[#This Row],[MUNICIPIO]],'4.CAP_ENDMNT'!B:B,'4.CAP_ENDMNT'!J:J,0,0,1) -> 0.2269597 | AB17: =+_xlfn.XLOOKUP(PROYECTOS[[#This Row],[MUNICIPIO]],'4.CAP_ENDMNT'!B:B,'4.CAP_ENDMNT'!K:K,0,0,1) -> 1.5080758e+10 | AC17: =+_xlfn.XLOOKUP(PROYECTOS[[#This Row],[MUNICIPIO]],'4.CAP_ENDMNT'!B:B,'4.CAP_ENDMNT'!L:L,0,0,1) -> 1.2064607e+10 | AD17: =+_xlfn.XLOOKUP(PROYECTOS[[#This Row],[MUNICIPIO]],'4.CAP_ENDMNT'!B:B,'4.CAP_ENDMNT'!M:M,0,0,1) -> 9.048455e+09 | AE17: =+_xlfn.XLOOKUP(PROYECTOS[[#This Row],[MUNICIPIO]],'4.CAP_ENDMNT'!B:B,'4.CAP_ENDMNT'!N:N,0,0,1) -> 0.58593202 | AF17: =+_xlfn.XLOOKUP(PROYECTOS[[#This Row],[MUNICIPIO]],'4.CAP_ENDMNT'!B:B,'4.CAP_ENDMNT'!O:O,0,0,1) -> 0.58851113 | AG17: =+_xlfn.XLOOKUP(PROYECTOS[[#This Row],[MUNICIPIO]],'4.CAP_ENDMNT'!B:B,'4.CAP_ENDMNT'!P:P,0,0,1) -> 0.8 | AH17: =+_xlfn.XLOOKUP(PROYECTOS[[#This Row],[MUNICIPIO]],'4.CAP_ENDMNT'!B:B,'4.CAP_ENDMNT'!Q:Q,0,0,1) -> Cumple | AI17: =+_xlfn.XLOOKUP(PROYECTOS[[#This Row],[MUNICIPIO]],'4.CAP_ENDMNT'!B:B,'4.CAP_ENDMNT'!V:V,0,0,1) -> 1.809691e+09 | AJ17: =+_xlfn.XLOOKUP(PROYECTOS[[#This Row],[MUNICIPIO]],'4.CAP_ENDMNT'!B:B,'4.CAP_ENDMNT'!Y:Y,0,0,1) -> -1.2348844e+10
A18: 19 | B18: Construcción de placa huella en la vía acceso al corregimiento de Belén Municipio de San Juan de Urabá Antioquia | C18: =+_xlfn.XLOOKUP(PROYECTOS[[#This Row],[ID_NECESIDAD]],'1.RADICADOS'!G:G,'1.RADICADOS'!C:C,0,0,1)*1 -> 45405 | D18: San Juan de Urabá | E18: =+_xlfn.XLOOKUP(PROYECTOS[[#This Row],[MUNICIPIO]],MUNICIPIOS!A:A,MUNICIPIOS!E:E,0,0,1) -> Urabá | F18: =+_xlfn.XLOOKUP(PROYECTOS[[#This Row],[MUNICIPIO]],MUNICIPIOS!A:A,MUNICIPIOS!F:F,0,0,1) -> -76.52857 | G18: =+_xlfn.XLOOKUP(PROYECTOS[[#This Row],[MUNICIPIO]],MUNICIPIOS!A:A,MUNICIPIOS!G:G,0,0,1) -> 8,758964 | H18: =+_xlfn.XLOOKUP(PROYECTOS[[#This Row],[MUNICIPIO]],MUNICIPIOS!A:A,MUNICIPIOS!B:B,0,0,1) -> 0 | I18: =+_xlfn.XLOOKUP(PROYECTOS[[#This Row],[MUNICIPIO]],MUNICIPIOS!A:A,MUNICIPIOS!C:C,0,0,1) -> 0 | J18: {=_xlfn.TEXTJOIN(" ", TRUE, IF(radicados[ID PROYECTOS]=A18, radicados[RADICADO], ""))} -> 2024010178436 | K18: 3 | L18: 2139964660 | M18: Placa huella | N18: Tercer Orden | O18: Vías terciarias mejoradas | Q18: 1 | R18: SGR Regionales 60% | S18: Placa huellas 2025-1 | T18: =+_xlfn.XLOOKUP(PROYECTOS[[#This Row],[MUNICIPIO]],'4.CAP_ENDMNT'!B:B,'4.CAP_ENDMNT'!C:C,0,0,1) -> 6 | U18: =+_xlfn.XLOOKUP(PROYECTOS[[#This Row],[MUNICIPIO]],'4.CAP_ENDMNT'!B:B,'4.CAP_ENDMNT'!D:D,0,0,1) -> 2.15584e+10 | V18: =+_xlfn.XLOOKUP(PROYECTOS[[#This Row],[MUNICIPIO]],'4.CAP_ENDMNT'!B:B,'4.CAP_ENDMNT'!E:E,0,0,1) -> 4.0285529e+09 | W18: =+_xlfn.XLOOKUP(PROYECTOS[[#This Row],[MUNICIPIO]],'4.CAP_ENDMNT'!B:B,'4.CAP_ENDMNT'!F:F,0,0,1) -> 1.7529848e+10 | X18: =+_xlfn.XLOOKUP(PROYECTOS[[#This Row],[MUNICIPIO]],'4.CAP_ENDMNT'!B:B,'4.CAP_ENDMNT'!G:G,0,0,1) -> 573337825 | Y18: =+_xlfn.XLOOKUP(PROYECTOS[[#This Row],[MUNICIPIO]],'4.CAP_ENDMNT'!B:B,'4.CAP_ENDMNT'!H:H,0,0,1) -> 3454671378 | Z18: =+_xlfn.XLOOKUP(PROYECTOS[[#This Row],[MUNICIPIO]],'4.CAP_ENDMNT'!B:B,'4.CAP_ENDMNT'!I:I,0,0,1) -> 4028009203 | AA18: =+_xlfn.XLOOKUP(PROYECTOS[[#This Row],[MUNICIPIO]],'4.CAP_ENDMNT'!B:B,'4.CAP_ENDMNT'!J:J,0,0,1) -> 0.18684175 | AB18: =+_xlfn.XLOOKUP(PROYECTOS[[#This Row],[MUNICIPIO]],'4.CAP_ENDMNT'!B:B,'4.CAP_ENDMNT'!K:K,0,0,1) -> 1.7530391e+10 | AC18: =+_xlfn.XLOOKUP(PROYECTOS[[#This Row],[MUNICIPIO]],'4.CAP_ENDMNT'!B:B,'4.CAP_ENDMNT'!L:L,0,0,1) -> 1.4024313e+10 | AD18: =+_xlfn.XLOOKUP(PROYECTOS[[#This Row],[MUNICIPIO]],'4.CAP_ENDMNT'!B:B,'4.CAP_ENDMNT'!M:M,0,0,1) -> 1.0518235e+10 | AE18: =+_xlfn.XLOOKUP(PROYECTOS[[#This Row],[MUNICIPIO]],'4.CAP_ENDMNT'!B:B,'4.CAP_ENDMNT'!N:N,0,0,1) -> 0.14233776 | AF18: =+_xlfn.XLOOKUP(PROYECTOS[[#This Row],[MUNICIPIO]],'4.CAP_ENDMNT'!B:B,'4.CAP_ENDMNT'!O:O,0,0,1) -> 0.45202185 | AG18: =+_xlfn.XLOOKUP(PROYECTOS[[#This Row],[MUNICIPIO]],'4.CAP_ENDMNT'!B:B,'4.CAP_ENDMNT'!P:P,0,0,1) -> 0.8 | AH18: =+_xlfn.XLOOKUP(PROYECTOS[[#This Row],[MUNICIPIO]],'4.CAP_ENDMNT'!B:B,'4.CAP_ENDMNT'!Q:Q,0,0,1) -> Cumple | AI18: =+_xlfn.XLOOKUP(PROYECTOS[[#This Row],[MUNICIPIO]],'4.CAP_ENDMNT'!B:B,'4.CAP_ENDMNT'!V:V,0,0,1) -> 2.103647e+09 | AJ18: =+_xlfn.XLOOKUP(PROYECTOS[[#This Row],[MUNICIPIO]],'4.CAP_ENDMNT'!B:B,'4.CAP_ENDMNT'!Y:Y,0,0,1) -> 5.4542225e+09
A19: 20 | B19: Mejoramiento vías urbanas municipio de Yolombó | C19: =+_xlfn.XLOOKUP(PROYECTOS[[#This Row],[ID_NECESIDAD]],'1.RADICADOS'!G:G,'1.RADICADOS'!C:C,0,0,1)*1 -> 45405 | D19: Yolombó | E19: =+_xlfn.XLOOKUP(PROYECTOS[[#This Row],[MUNICIPIO]],MUNICIPIOS!A:A,MUNICIPIOS!E:E,0,0,1) -> Nordeste | F19: =+_xlfn.XLOOKUP(PROYECTOS[[#This Row],[MUNICIPIO]],MUNICIPIOS!A:A,MUNICIPIOS!F:F,0,0,1) -> -75.013385 | G19: =+_xlfn.XLOOKUP(PROYECTOS[[#This Row],[MUNICIPIO]],MUNICIPIOS!A:A,MUNICIPIOS!G:G,0,0,1) -> 6.594511 | H19: =+_xlfn.XLOOKUP(PROYECTOS[[#This Row],[MUNICIPIO]],MUNICIPIOS!A:A,MUNICIPIOS!B:B,0,0,1) -> 0 | I19: =+_xlfn.XLOOKUP(PROYECTOS[[#This Row],[MUNICIPIO]],MUNICIPIOS!A:A,MUNICIPIOS!C:C,0,0,1) -> 1 | J19: {=_xlfn.TEXTJOIN(" ", TRUE, IF(radicados[ID PROYECTOS]=A19, radicados[RADICADO], ""))} -> 2024010178733 | K19: 1 | M19: Pavimento Flexible | N19: Urbana | O19: Vía urbana mejorada | P19: Ya se aportaron recursos | T19: =+_xlfn.XLOOKUP(PROYECTOS[[#This Row],[MUNICIPIO]],'4.CAP_ENDMNT'!B:B,'4.CAP_ENDMNT'!C:C,0,0,1) -> 6 | U19: =+_xlfn.XLOOKUP(PROYECTOS[[#This Row],[MUNICIPIO]],'4.CAP_ENDMNT'!B:B,'4.CAP_ENDMNT'!D:D,0,0,1) -> 1.8632663e+10 | V19: =+_xlfn.XLOOKUP(PROYECTOS[[#This Row],[MUNICIPIO]],'4.CAP_ENDMNT'!B:B,'4.CAP_ENDMNT'!E:E,0,0,1) -> 4.3322935e+09 | W19: =+_xlfn.XLOOKUP(PROYECTOS[[#This Row],[MUNICIPIO]],'4.CAP_ENDMNT'!B:B,'4.CAP_ENDMNT'!F:F,0,0,1) -> 1.430037e+10 | X19: =+_xlfn.XLOOKUP(PROYECTOS[[#This Row],[MUNICIPIO]],'4.CAP_ENDMNT'!B:B,'4.CAP_ENDMNT'!G:G,0,0,1) -> 3970281006 | Y19: =+_xlfn.XLOOKUP(PROYECTOS[[#This Row],[MUNICIPIO]],'4.CAP_ENDMNT'!B:B,'4.CAP_ENDMNT'!H:H,0,0,1) -> 1500000000 | Z19: =+_xlfn.XLOOKUP(PROYECTOS[[#This Row],[MUNICIPIO]],'4.CAP_ENDMNT'!B:B,'4.CAP_ENDMNT'!I:I,0,0,1) -> 5470281006 | AA19: =+_xlfn.XLOOKUP(PROYECTOS[[#This Row],[MUNICIPIO]],'4.CAP_ENDMNT'!B:B,'4.CAP_ENDMNT'!J:J,0,0,1) -> 0.29358557 | AB19: =+_xlfn.XLOOKUP(PROYECTOS[[#This Row],[MUNICIPIO]],'4.CAP_ENDMNT'!B:B,'4.CAP_ENDMNT'!K:K,0,0,1) -> 1.3162382e+10 | AC19: =+_xlfn.XLOOKUP(PROYECTOS[[#This Row],[MUNICIPIO]],'4.CAP_ENDMNT'!B:B,'4.CAP_ENDMNT'!L:L,0,0,1) -> 1.0529906e+10 | AD19: =+_xlfn.XLOOKUP(PROYECTOS[[#This Row],[MUNICIPIO]],'4.CAP_ENDMNT'!B:B,'4.CAP_ENDMNT'!M:M,0,0,1) -> 7.8974293e+09 | AE19: =+_xlfn.XLOOKUP(PROYECTOS[[#This Row],[MUNICIPIO]],'4.CAP_ENDMNT'!B:B,'4.CAP_ENDMNT'!N:N,0,0,1) -> 0.72579105 | AF19: =+_xlfn.XLOOKUP(PROYECTOS[[#This Row],[MUNICIPIO]],'4.CAP_ENDMNT'!B:B,'4.CAP_ENDMNT'!O:O,0,0,1) -> 0.44683078 | AG19: =+_xlfn.XLOOKUP(PROYECTOS[[#This Row],[MUNICIPIO]],'4.CAP_ENDMNT'!B:B,'4.CAP_ENDMNT'!P:P,0,0,1) -> 0.8 | AH19: =+_xlfn.XLOOKUP(PROYECTOS[[#This Row],[MUNICIPIO]],'4.CAP_ENDMNT'!B:B,'4.CAP_ENDMNT'!Q:Q,0,0,1) -> Cumple | AI19: =+_xlfn.XLOOKUP(PROYECTOS[[#This Row],[MUNICIPIO]],'4.CAP_ENDMNT'!B:B,'4.CAP_ENDMNT'!V:V,0,0,1) -> 1.5794859e+09 | AJ19: =+_xlfn.XLOOKUP(PROYECTOS[[#This Row],[MUNICIPIO]],'4.CAP_ENDMNT'!B:B,'4.CAP_ENDMNT'!Y:Y,0,0,1) -> 2.1111588e+09
A20: 21 | B20: Construcción del ámbito patrimonio del proyecto Paisajes del Agua en el Municipio de Rionegro -ADICION A PROYECTO EN EJECUCION | C20: =+_xlfn.XLOOKUP(PROYECTOS[[#This Row],[ID_NECESIDAD]],'1.RADICADOS'!G:G,'1.RADICADOS'!C:C,0,0,1)*1 -> 45398 | D20: Rionegro | E20: =+_xlfn.XLOOKUP(PROYECTOS[[#This Row],[MUNICIPIO]],MUNICIPIOS!A:A,MUNICIPIOS!E:E,0,0,1) -> Oriente | F20: =+_xlfn.XLOOKUP(PROYECTOS[[#This Row],[MUNICIPIO]],MUNICIPIOS!A:A,MUNICIPIOS!F:F,0,0,1) -> -75.377316 | G20: =+_xlfn.XLOOKUP(PROYECTOS[[#This Row],[MUNICIPIO]],MUNICIPIOS!A:A,MUNICIPIOS!G:G,0,0,1) -> 6,147148 | H20: =+_xlfn.XLOOKUP(PROYECTOS[[#This Row],[MUNICIPIO]],MUNICIPIOS!A:A,MUNICIPIOS!B:B,0,0,1) -> 0 | I20: =+_xlfn.XLOOKUP(PROYECTOS[[#This Row],[MUNICIPIO]],MUNICIPIOS!A:A,MUNICIPIOS!C:C,0,0,1) -> 0 | J20: {=_xlfn.TEXTJOIN(" ", TRUE, IF(radicados[ID PROYECTOS]=A20, radicados[RADICADO], ""))} -> 2024020016404 | K20: 3 | L20: 1578945342 | M20: Parque | N20: N/A | O20: Espacio público adecuado | P20: Peticion por recursos para obra adicional | T20: =+_xlfn.XLOOKUP(PROYECTOS[[#This Row],[MUNICIPIO]],'4.CAP_ENDMNT'!B:B,'4.CAP_ENDMNT'!C:C,0,0,1) -> 1 | U20: =+_xlfn.XLOOKUP(PROYECTOS[[#This Row],[MUNICIPIO]],'4.CAP_ENDMNT'!B:B,'4.CAP_ENDMNT'!D:D,0,0,1) -> 5.0123644e+11 | V20: =+_xlfn.XLOOKUP(PROYECTOS[[#This Row],[MUNICIPIO]],'4.CAP_ENDMNT'!B:B,'4.CAP_ENDMNT'!E:E,0,0,1) -> 1.1250202e+11 | W20: =+_xlfn.XLOOKUP(PROYECTOS[[#This Row],[MUNICIPIO]],'4.CAP_ENDMNT'!B:B,'4.CAP_ENDMNT'!F:F,0,0,1) -> 3.8873442e+11 | X20: =+_xlfn.XLOOKUP(PROYECTOS[[#This Row],[MUNICIPIO]],'4.CAP_ENDMNT'!B:B,'4.CAP_ENDMNT'!G:G,0,0,1) -> 85394840514 | Y20: =+_xlfn.XLOOKUP(PROYECTOS[[#This Row],[MUNICIPIO]],'4.CAP_ENDMNT'!B:B,'4.CAP_ENDMNT'!H:H,0,0,1) -> 1.1410989e+11 | Z20: =+_xlfn.XLOOKUP(PROYECTOS[[#This Row],[MUNICIPIO]],'4.CAP_ENDMNT'!B:B,'4.CAP_ENDMNT'!I:I,0,0,1) -> 1.9950473e+11 | AA20: =+_xlfn.XLOOKUP(PROYECTOS[[#This Row],[MUNICIPIO]],'4.CAP_ENDMNT'!B:B,'4.CAP_ENDMNT'!J:J,0,0,1) -> 0.39802519 | AB20: =+_xlfn.XLOOKUP(PROYECTOS[[#This Row],[MUNICIPIO]],'4.CAP_ENDMNT'!B:B,'4.CAP_ENDMNT'!K:K,0,0,1) -> 3.0173171e+11 | AC20: =+_xlfn.XLOOKUP(PROYECTOS[[#This Row],[MUNICIPIO]],'4.CAP_ENDMNT'!B:B,'4.CAP_ENDMNT'!L:L,0,0,1) -> 2.4138537e+11 | AD20: =+_xlfn.XLOOKUP(PROYECTOS[[#This Row],[MUNICIPIO]],'4.CAP_ENDMNT'!B:B,'4.CAP_ENDMNT'!M:M,0,0,1) -> 1.8103903e+11 | AE20: =+_xlfn.XLOOKUP(PROYECTOS[[#This Row],[MUNICIPIO]],'4.CAP_ENDMNT'!B:B,'4.CAP_ENDMNT'!N:N,0,0,1) -> 0.42803417 | AF20: =+_xlfn.XLOOKUP(PROYECTOS[[#This Row],[MUNICIPIO]],'4.CAP_ENDMNT'!B:B,'4.CAP_ENDMNT'!O:O,0,0,1) -> 0.23207277 | AG20: =+_xlfn.XLOOKUP(PROYECTOS[[#This Row],[MUNICIPIO]],'4.CAP_ENDMNT'!B:B,'4.CAP_ENDMNT'!P:P,0,0,1) -> 0.65 | AH20: =+_xlfn.XLOOKUP(PROYECTOS[[#This Row],[MUNICIPIO]],'4.CAP_ENDMNT'!B:B,'4.CAP_ENDMNT'!Q:Q,0,0,1) -> Cumple | AI20: =+_xlfn.XLOOKUP(PROYECTOS[[#This Row],[MUNICIPIO]],'4.CAP_ENDMNT'!B:B,'4.CAP_ENDMNT'!V:V,0,0,1) -> 3.6207806e+10 | AJ20: =+_xlfn.XLOOKUP(PROYECTOS[[#This Row],[MUNICIPIO]],'4.CAP_ENDMNT'!B:B,'4.CAP_ENDMNT'!Y:Y,0,0,1) -> 1.9947085e+11
A21: 22 | B21: Estudios y diseños para plaza de feria ganadera en el municipio de Alejandría - Antioquia | C21: =+_xlfn.XLOOKUP(PROYECTOS[[#This Row],[ID_NECESIDAD]],'1.RADICADOS'!G:G,'1.RADICADOS'!C:C,0,0,1)*1 -> 45400 | D21: Alejandría | E21: =+_xlfn.XLOOKUP(PROYECTOS[[#This Row],[MUNICIPIO]],MUNICIPIOS!A:A,MUNICIPIOS!E:E,0,0,1) -> Oriente | F21: =+_xlfn.XLOOKUP(PROYECTOS[[#This Row],[MUNICIPIO]],MUNICIPIOS!A:A,MUNICIPIOS!F:F,0,0,1) -> -75.141346 | G21: =+_xlfn.XLOOKUP(PROYECTOS[[#This Row],[MUNICIPIO]],MUNICIPIOS!A:A,MUNICIPIOS!G:G,0,0,1) -> 6,376061 | H21: =+_xlfn.XLOOKUP(PROYECTOS[[#This Row],[MUNICIPIO]],MUNICIPIOS!A:A,MUNICIPIOS!B:B,0,0,1) -> 0 | I21: =+_xlfn.XLOOKUP(PROYECTOS[[#This Row],[MUNICIPIO]],MUNICIPIOS!A:A,MUNICIPIOS!C:C,0,0,1) -> 1 | J21: {=_xlfn.TEXTJOIN(" ", TRUE, IF(radicados[ID PROYECTOS]=A21, radicados[RADICADO], ""))} -> 2024010171235 | K21: 1 | M21: Equipamento | N21: N/A | O21: Estudios y diseños para proyectos de infraestructura realizados | P21: Se presenta perfil del proyecto | T21: =+_xlfn.XLOOKUP(PROYECTOS[[#This Row],[MUNICIPIO]],'4.CAP_ENDMNT'!B:B,'4.CAP_ENDMNT'!C:C,0,0,1) -> 6 | U21: =+_xlfn.XLOOKUP(PROYECTOS[[#This Row],[MUNICIPIO]],'4.CAP_ENDMNT'!B:B,'4.CAP_ENDMNT'!D:D,0,0,1) -> 8.3628319e+09 | V21: =+_xlfn.XLOOKUP(PROYECTOS[[#This Row],[MUNICIPIO]],'4.CAP_ENDMNT'!B:B,'4.CAP_ENDMNT'!E:E,0,0,1) -> 2.1992794e+09 | W21: =+_xlfn.XLOOKUP(PROYECTOS[[#This Row],[MUNICIPIO]],'4.CAP_ENDMNT'!B:B,'4.CAP_ENDMNT'!F:F,0,0,1) -> 6.1635525e+09 | X21: =+_xlfn.XLOOKUP(PROYECTOS[[#This Row],[MUNICIPIO]],'4.CAP_ENDMNT'!B:B,'4.CAP_ENDMNT'!G:G,0,0,1) -> 284104325 | Y21: =+_xlfn.XLOOKUP(PROYECTOS[[#This Row],[MUNICIPIO]],'4.CAP_ENDMNT'!B:B,'4.CAP_ENDMNT'!H:H,0,0,1) -> 209000000 | Z21: =+_xlfn.XLOOKUP(PROYECTOS[[#This Row],[MUNICIPIO]],'4.CAP_ENDMNT'!B:B,'4.CAP_ENDMNT'!I:I,0,0,1) -> 493104325 | AA21: =+_xlfn.XLOOKUP(PROYECTOS[[#This Row],[MUNICIPIO]],'4.CAP_ENDMNT'!B:B,'4.CAP_ENDMNT'!J:J,0,0,1) -> 0.058963797 | AB21: =+_xlfn.XLOOKUP(PROYECTOS[[#This Row],[MUNICIPIO]],'4.CAP_ENDMNT'!B:B,'4.CAP_ENDMNT'!K:K,0,0,1) -> 7.8697276e+09 | AC21: =+_xlfn.XLOOKUP(PROYECTOS[[#This Row],[MUNICIPIO]],'4.CAP_ENDMNT'!B:B,'4.CAP_ENDMNT'!L:L,0,0,1) -> 6.2957821e+09 | AD21: =+_xlfn.XLOOKUP(PROYECTOS[[#This Row],[MUNICIPIO]],'4.CAP_ENDMNT'!B:B,'4.CAP_ENDMNT'!M:M,0,0,1) -> 4.7218366e+09 | AE21: =+_xlfn.XLOOKUP(PROYECTOS[[#This Row],[MUNICIPIO]],'4.CAP_ENDMNT'!B:B,'4.CAP_ENDMNT'!N:N,0,0,1) -> 0.5761546 | AF21: =+_xlfn.XLOOKUP(PROYECTOS[[#This Row],[MUNICIPIO]],'4.CAP_ENDMNT'!B:B,'4.CAP_ENDMNT'!O:O,0,0,1) -> 0.61308929 | AG21: =+_xlfn.XLOOKUP(PROYECTOS[[#This Row],[MUNICIPIO]],'4.CAP_ENDMNT'!B:B,'4.CAP_ENDMNT'!P:P,0,0,1) -> 0.8 | AH21: =+_xlfn.XLOOKUP(PROYECTOS[[#This Row],[MUNICIPIO]],'4.CAP_ENDMNT'!B:B,'4.CAP_ENDMNT'!Q:Q,0,0,1) -> Cumple | AI21: =+_xlfn.XLOOKUP(PROYECTOS[[#This Row],[MUNICIPIO]],'4.CAP_ENDMNT'!B:B,'4.CAP_ENDMNT'!V:V,0,0,1) -> 9.4436731e+08 | AJ21: =+_xlfn.XLOOKUP(PROYECTOS[[#This Row],[MUNICIPIO]],'4.CAP_ENDMNT'!B:B,'4.CAP_ENDMNT'!Y:Y,0,0,1) -> -7.8563227e+09
A22: 23 | B22: Construcción del espacio público parques de la quebrada Donmatías Antioquia - Etapa 1 | C22: =+_xlfn.XLOOKUP(PROYECTOS[[#This Row],[ID_NECESIDAD]],'1.RADICADOS'!G:G,'1.RADICADOS'!C:C,0,0,1)*1 -> 45569 | D22: Donmatías | E22: =+_xlfn.XLOOKUP(PROYECTOS[[#This Row],[MUNICIPIO]],MUNICIPIOS!A:A,MUNICIPIOS!E:E,0,0,1) -> Norte | F22: =+_xlfn.XLOOKUP(PROYECTOS[[#This Row],[MUNICIPIO]],MUNICIPIOS!A:A,MUNICIPIOS!F:F,0,0,1) -> -75.39263 | G22: =+_xlfn.XLOOKUP(PROYECTOS[[#This Row],[MUNICIPIO]],MUNICIPIOS!A:A,MUNICIPIOS!G:G,0,0,1) -> 6,485603 | H22: =+_xlfn.XLOOKUP(PROYECTOS[[#This Row],[MUNICIPIO]],MUNICIPIOS!A:A,MUNICIPIOS!B:B,0,0,1) -> 0 | I22: =+_xlfn.XLOOKUP(PROYECTOS[[#This Row],[MUNICIPIO]],MUNICIPIOS!A:A,MUNICIPIOS!C:C,0,0,1) -> 0 | J22: {=_xlfn.TEXTJOIN(" ", TRUE, IF(radicados[ID PROYECTOS]=A22, radicados[RADICADO], ""))} -> 2024010153392 2024010238427 | K22: 1 | M22: Parque | N22: N/A | O22: Espacio público adecuado | P22: Solicitud de adicion | T22: =+_xlfn.XLOOKUP(PROYECTOS[[#This Row],[MUNICIPIO]],'4.CAP_ENDMNT'!B:B,'4.CAP_ENDMNT'!C:C,0,0,1) -> 6 | U22: =+_xlfn.XLOOKUP(PROYECTOS[[#This Row],[MUNICIPIO]],'4.CAP_ENDMNT'!B:B,'4.CAP_ENDMNT'!D:D,0,0,1) -> 2.4529039e+10 | V22: =+_xlfn.XLOOKUP(PROYECTOS[[#This Row],[MUNICIPIO]],'4.CAP_ENDMNT'!B:B,'4.CAP_ENDMNT'!E:E,0,0,1) -> 8.9730124e+09 | W22: =+_xlfn.XLOOKUP(PROYECTOS[[#This Row],[MUNICIPIO]],'4.CAP_ENDMNT'!B:B,'4.CAP_ENDMNT'!F:F,0,0,1) -> 1.5556027e+10 | X22: =+_xlfn.XLOOKUP(PROYECTOS[[#This Row],[MUNICIPIO]],'4.CAP_ENDMNT'!B:B,'4.CAP_ENDMNT'!G:G,0,0,1) -> 7973050390 | Y22: =+_xlfn.XLOOKUP(PROYECTOS[[#This Row],[MUNICIPIO]],'4.CAP_ENDMNT'!B:B,'4.CAP_ENDMNT'!H:H,0,0,1) -> 1625381984 | Z22: =+_xlfn.XLOOKUP(PROYECTOS[[#This Row],[MUNICIPIO]],'4.CAP_ENDMNT'!B:B,'4.CAP_ENDMNT'!I:I,0,0,1) -> 9598432374 | AA22: =+_xlfn.XLOOKUP(PROYECTOS[[#This Row],[MUNICIPIO]],'4.CAP_ENDMNT'!B:B,'4.CAP_ENDMNT'!J:J,0,0,1) -> 0.39130894 | AB22: =+_xlfn.XLOOKUP(PROYECTOS[[#This Row],[MUNICIPIO]],'4.CAP_ENDMNT'!B:B,'4.CAP_ENDMNT'!K:K,0,0,1) -> 1.4930607e+10 | AC22: =+_xlfn.XLOOKUP(PROYECTOS[[#This Row],[MUNICIPIO]],'4.CAP_ENDMNT'!B:B,'4.CAP_ENDMNT'!L:L,0,0,1) -> 1.1944486e+10 | AD22: =+_xlfn.XLOOKUP(PROYECTOS[[#This Row],[MUNICIPIO]],'4.CAP_ENDMNT'!B:B,'4.CAP_ENDMNT'!M:M,0,0,1) -> 8.9583642e+09 | AE22: =+_xlfn.XLOOKUP(PROYECTOS[[#This Row],[MUNICIPIO]],'4.CAP_ENDMNT'!B:B,'4.CAP_ENDMNT'!N:N,0,0,1) -> 0.83066172 | AF22: =+_xlfn.XLOOKUP(PROYECTOS[[#This Row],[MUNICIPIO]],'4.CAP_ENDMNT'!B:B,'4.CAP_ENDMNT'!O:O,0,0,1) -> 0.53024344 | AG22: =+_xlfn.XLOOKUP(PROYECTOS[[#This Row],[MUNICIPIO]],'4.CAP_ENDMNT'!B:B,'4.CAP_ENDMNT'!P:P,0,0,1) -> 0.8 | AH22: =+_xlfn.XLOOKUP(PROYECTOS[[#This Row],[MUNICIPIO]],'4.CAP_ENDMNT'!B:B,'4.CAP_ENDMNT'!Q:Q,0,0,1) -> Cumple | AI22: =+_xlfn.XLOOKUP(PROYECTOS[[#This Row],[MUNICIPIO]],'4.CAP_ENDMNT'!B:B,'4.CAP_ENDMNT'!V:V,0,0,1) -> 1.7916728e+09 | AJ22: =+_xlfn.XLOOKUP(PROYECTOS[[#This Row],[MUNICIPIO]],'4.CAP_ENDMNT'!B:B,'4.CAP_ENDMNT'!Y:Y,0,0,1) -> -8.1641356e+09
A23: 24 | B23: Construcción de la fase dos del malecón turístico del Distrito de Turbo | C23: =+_xlfn.XLOOKUP(PROYECTOS[[#This Row],[ID_NECESIDAD]],'1.RADICADOS'!G:G,'1.RADICADOS'!C:C,0,0,1)*1 -> 45509 | D23: Turbo | E23: =+_xlfn.XLOOKUP(PROYECTOS[[#This Row],[MUNICIPIO]],MUNICIPIOS!A:A,MUNICIPIOS!E:E,0,0,1) -> Urabá | F23: =+_xlfn.XLOOKUP(PROYECTOS[[#This Row],[MUNICIPIO]],MUNICIPIOS!A:A,MUNICIPIOS!F:F,0,0,1) -> -76.728858 | G23: =+_xlfn.XLOOKUP(PROYECTOS[[#This Row],[MUNICIPIO]],MUNICIPIOS!A:A,MUNICIPIOS!G:G,0,0,1) -> 8.089929 | H23: =+_xlfn.XLOOKUP(PROYECTOS[[#This Row],[MUNICIPIO]],MUNICIPIOS!A:A,MUNICIPIOS!B:B,0,0,1) -> 1 | I23: =+_xlfn.XLOOKUP(PROYECTOS[[#This Row],[MUNICIPIO]],MUNICIPIOS!A:A,MUNICIPIOS!C:C,0,0,1) -> 1 | J23: {=_xlfn.TEXTJOIN(" ", TRUE, IF(radicados[ID PROYECTOS]=A23, radicados[RADICADO], ""))} -> 2024010207402 | K23: 2 | M23: Malecón | N23: N/A | O23: Espacio público adecuado | T23: =+_xlfn.XLOOKUP(PROYECTOS[[#This Row],[MUNICIPIO]],'4.CAP_ENDMNT'!B:B,'4.CAP_ENDMNT'!C:C,0,0,1) -> 5 | U23: =+_xlfn.XLOOKUP(PROYECTOS[[#This Row],[MUNICIPIO]],'4.CAP_ENDMNT'!B:B,'4.CAP_ENDMNT'!D:D,0,0,1) -> 5.7277944e+10 | V23: =+_xlfn.XLOOKUP(PROYECTOS[[#This Row],[MUNICIPIO]],'4.CAP_ENDMNT'!B:B,'4.CAP_ENDMNT'!E:E,0,0,1) -> 3.41594e+10 | W23: =+_xlfn.XLOOKUP(PROYECTOS[[#This Row],[MUNICIPIO]],'4.CAP_ENDMNT'!B:B,'4.CAP_ENDMNT'!F:F,0,0,1) -> 2.3118544e+10 | X23: =+_xlfn.XLOOKUP(PROYECTOS[[#This Row],[MUNICIPIO]],'4.CAP_ENDMNT'!B:B,'4.CAP_ENDMNT'!G:G,0,0,1) -> 3450000000 | Y23: =+_xlfn.XLOOKUP(PROYECTOS[[#This Row],[MUNICIPIO]],'4.CAP_ENDMNT'!B:B,'4.CAP_ENDMNT'!H:H,0,0,1) -> 21452083665 | Z23: =+_xlfn.XLOOKUP(PROYECTOS[[#This Row],[MUNICIPIO]],'4.CAP_ENDMNT'!B:B,'4.CAP_ENDMNT'!I:I,0,0,1) -> 24902083665 | AA23: =+_xlfn.XLOOKUP(PROYECTOS[[#This Row],[MUNICIPIO]],'4.CAP_ENDMNT'!B:B,'4.CAP_ENDMNT'!J:J,0,0,1) -> 0.43475869 | AB23: =+_xlfn.XLOOKUP(PROYECTOS[[#This Row],[MUNICIPIO]],'4.CAP_ENDMNT'!B:B,'4.CAP_ENDMNT'!K:K,0,0,1) -> 3.237586e+10 | AC23: =+_xlfn.XLOOKUP(PROYECTOS[[#This Row],[MUNICIPIO]],'4.CAP_ENDMNT'!B:B,'4.CAP_ENDMNT'!L:L,0,0,1) -> 2.5900688e+10 | AD23: =+_xlfn.XLOOKUP(PROYECTOS[[#This Row],[MUNICIPIO]],'4.CAP_ENDMNT'!B:B,'4.CAP_ENDMNT'!M:M,0,0,1) -> 1.9425516e+10 | AE23: =+_xlfn.XLOOKUP(PROYECTOS[[#This Row],[MUNICIPIO]],'4.CAP_ENDMNT'!B:B,'4.CAP_ENDMNT'!N:N,0,0,1) -> 0.13854262 | AF23: =+_xlfn.XLOOKUP(PROYECTOS[[#This Row],[MUNICIPIO]],'4.CAP_ENDMNT'!B:B,'4.CAP_ENDMNT'!O:O,0,0,1) -> 0.87015153 | AG23: =+_xlfn.XLOOKUP(PROYECTOS[[#This Row],[MUNICIPIO]],'4.CAP_ENDMNT'!B:B,'4.CAP_ENDMNT'!P:P,0,0,1) -> 0.8 | AH23: =+_xlfn.XLOOKUP(PROYECTOS[[#This Row],[MUNICIPIO]],'4.CAP_ENDMNT'!B:B,'4.CAP_ENDMNT'!Q:Q,0,0,1) -> Incumple | AI23: =+_xlfn.XLOOKUP(PROYECTOS[[#This Row],[MUNICIPIO]],'4.CAP_ENDMNT'!B:B,'4.CAP_ENDMNT'!V:V,0,0,1) -> 3.8851032e+09 | AJ23: =+_xlfn.XLOOKUP(PROYECTOS[[#This Row],[MUNICIPIO]],'4.CAP_ENDMNT'!B:B,'4.CAP_ENDMNT'!Y:Y,0,0,1) -> -1.1405286e+11
A24: 26 | B24: Construcción de la apertura vial entre la calle 16 y la carrera 22 de la zona urbana del municipio de Alejandría | C24: =+_xlfn.XLOOKUP(PROYECTOS[[#This Row],[ID_NECESIDAD]],'1.RADICADOS'!G:G,'1.RADICADOS'!C:C,0,0,1)*1 -> 45436 | D24: Alejandría | E24: =+_xlfn.XLOOKUP(PROYECTOS[[#This Row],[MUNICIPIO]],MUNICIPIOS!A:A,MUNICIPIOS!E:E,0,0,1) -> Oriente | F24: =+_xlfn.XLOOKUP(PROYECTOS[[#This Row],[MUNICIPIO]],MUNICIPIOS!A:A,MUNICIPIOS!F:F,0,0,1) -> -75.141346 | G24: =+_xlfn.XLOOKUP(PROYECTOS[[#This Row],[MUNICIPIO]],MUNICIPIOS!A:A,MUNICIPIOS!G:G,0,0,1) -> 6,376061 | H24: =+_xlfn.XLOOKUP(PROYECTOS[[#This Row],[MUNICIPIO]],MUNICIPIOS!A:A,MUNICIPIOS!B:B,0,0,1) -> 0 | I24: =+_xlfn.XLOOKUP(PROYECTOS[[#This Row],[MUNICIPIO]],MUNICIPIOS!A:A,MUNICIPIOS!C:C,0,0,1) -> 1 | J24: {=_xlfn.TEXTJOIN(" ", TRUE, IF(radicados[ID PROYECTOS]=A24, radicados[RADICADO], ""))} -> 2024010232610 | K24: 3 | L24: 4805691053 | M24: Pavimento Flexible | N24: Urbana | O24: Vía urbana mejorada | T24: =+_xlfn.XLOOKUP(PROYECTOS[[#This Row],[MUNICIPIO]],'4.CAP_ENDMNT'!B:B,'4.CAP_ENDMNT'!C:C,0,0,1) -> 6 | U24: =+_xlfn.XLOOKUP(PROYECTOS[[#This Row],[MUNICIPIO]],'4.CAP_ENDMNT'!B:B,'4.CAP_ENDMNT'!D:D,0,0,1) -> 8.3628319e+09 | V24: =+_xlfn.XLOOKUP(PROYECTOS[[#This Row],[MUNICIPIO]],'4.CAP_ENDMNT'!B:B,'4.CAP_ENDMNT'!E:E,0,0,1) -> 2.1992794e+09 | W24: =+_xlfn.XLOOKUP(PROYECTOS[[#This Row],[MUNICIPIO]],'4.CAP_ENDMNT'!B:B,'4.CAP_ENDMNT'!F:F,0,0,1) -> 6.1635525e+09 | X24: =+_xlfn.XLOOKUP(PROYECTOS[[#This Row],[MUNICIPIO]],'4.CAP_ENDMNT'!B:B,'4.CAP_ENDMNT'!G:G,0,0,1) -> 284104325 | Y24: =+_xlfn.XLOOKUP(PROYECTOS[[#This Row],[MUNICIPIO]],'4.CAP_ENDMNT'!B:B,'4.CAP_ENDMNT'!H:H,0,0,1) -> 209000000 | Z24: =+_xlfn.XLOOKUP(PROYECTOS[[#This Row],[MUNICIPIO]],'4.CAP_ENDMNT'!B:B,'4.CAP_ENDMNT'!I:I,0,0,1) -> 493104325 | AA24: =+_xlfn.XLOOKUP(PROYECTOS[[#This Row],[MUNICIPIO]],'4.CAP_ENDMNT'!B:B,'4.CAP_ENDMNT'!J:J,0,0,1) -> 0.058963797 | AB24: =+_xlfn.XLOOKUP(PROYECTOS[[#This Row],[MUNICIPIO]],'4.CAP_ENDMNT'!B:B,'4.CAP_ENDMNT'!K:K,0,0,1) -> 7.8697276e+09 | AC24: =+_xlfn.XLOOKUP(PROYECTOS[[#This Row],[MUNICIPIO]],'4.CAP_ENDMNT'!B:B,'4.CAP_ENDMNT'!L:L,0,0,1) -> 6.2957821e+09 | AD24: =+_xlfn.XLOOKUP(PROYECTOS[[#This Row],[MUNICIPIO]],'4.CAP_ENDMNT'!B:B,'4.CAP_ENDMNT'!M:M,0,0,1) -> 4.7218366e+09 | AE24: =+_xlfn.XLOOKUP(PROYECTOS[[#This Row],[MUNICIPIO]],'4.CAP_ENDMNT'!B:B,'4.CAP_ENDMNT'!N:N,0,0,1) -> 0.5761546 | AF24: =+_xlfn.XLOOKUP(PROYECTOS[[#This Row],[MUNICIPIO]],'4.CAP_ENDMNT'!B:B,'4.CAP_ENDMNT'!O:O,0,0,1) -> 0.61308929 | AG24: =+_xlfn.XLOOKUP(PROYECTOS[[#This Row],[MUNICIPIO]],'4.CAP_ENDMNT'!B:B,'4.CAP_ENDMNT'!P:P,0,0,1) -> 0.8 | AH24: =+_xlfn.XLOOKUP(PROYECTOS[[#This Row],[MUNICIPIO]],'4.CAP_ENDMNT'!B:B,'4.CAP_ENDMNT'!Q:Q,0,0,1) -> Cumple | AI24: =+_xlfn.XLOOKUP(PROYECTOS[[#This Row],[MUNICIPIO]],'4.CAP_ENDMNT'!B:B,'4.CAP_ENDMNT'!V:V,0,0,1) -> 9.4436731e+08 | AJ24: =+_xlfn.XLOOKUP(PROYECTOS[[#This Row],[MUNICIPIO]],'4.CAP_ENDMNT'!B:B,'4.CAP_ENDMNT'!Y:Y,0,0,1) -> -7.8563227e+09
A25: 27 | B25: Malecón turístico cebecera municipal Puerto Triunfo | C25: =+_xlfn.XLOOKUP(PROYECTOS[[#This Row],[ID_NECESIDAD]],'1.RADICADOS'!G:G,'1.RADICADOS'!C:C,0,0,1)*1 -> 45436 | D25: Puerto Triunfo | E25: =+_xlfn.XLOOKUP(PROYECTOS[[#This Row],[MUNICIPIO]],MUNICIPIOS!A:A,MUNICIPIOS!E:E,0,0,1) -> Magdalena Medio | F25: =+_xlfn.XLOOKUP(PROYECTOS[[#This Row],[MUNICIPIO]],MUNICIPIOS!A:A,MUNICIPIOS!F:F,0,0,1) -> -74.64119 | G25: =+_xlfn.XLOOKUP(PROYECTOS[[#This Row],[MUNICIPIO]],MUNICIPIOS!A:A,MUNICIPIOS!G:G,0,0,1) -> 5,871318 | H25: =+_xlfn.XLOOKUP(PROYECTOS[[#This Row],[MUNICIPIO]],MUNICIPIOS!A:A,MUNICIPIOS!B:B,0,0,1) -> 0 | I25: =+_xlfn.XLOOKUP(PROYECTOS[[#This Row],[MUNICIPIO]],MUNICIPIOS!A:A,MUNICIPIOS!C:C,0,0,1) -> 0 | J25: {=_xlfn.TEXTJOIN(" ", TRUE, IF(radicados[ID PROYECTOS]=A25, radicados[RADICADO], ""))} -> 2024010233575 | K25: 1 | M25: Malecón | N25: N/A | O25: Espacio público adecuado | P25: ya se dio el recurso | T25: =+_xlfn.XLOOKUP(PROYECTOS[[#This Row],[MUNICIPIO]],'4.CAP_ENDMNT'!B:B,'4.CAP_ENDMNT'!C:C,0,0,1) -> 6 | U25: =+_xlfn.XLOOKUP(PROYECTOS[[#This Row],[MUNICIPIO]],'4.CAP_ENDMNT'!B:B,'4.CAP_ENDMNT'!D:D,0,0,1) -> 2.2896433e+10 | V25: =+_xlfn.XLOOKUP(PROYECTOS[[#This Row],[MUNICIPIO]],'4.CAP_ENDMNT'!B:B,'4.CAP_ENDMNT'!E:E,0,0,1) -> 6.5141057e+09 | W25: =+_xlfn.XLOOKUP(PROYECTOS[[#This Row],[MUNICIPIO]],'4.CAP_ENDMNT'!B:B,'4.CAP_ENDMNT'!F:F,0,0,1) -> 1.6382327e+10 | X25: =+_xlfn.XLOOKUP(PROYECTOS[[#This Row],[MUNICIPIO]],'4.CAP_ENDMNT'!B:B,'4.CAP_ENDMNT'!G:G,0,0,1) -> 15087488121 | Y25: =+_xlfn.XLOOKUP(PROYECTOS[[#This Row],[MUNICIPIO]],'4.CAP_ENDMNT'!B:B,'4.CAP_ENDMNT'!H:H,0,0,1) -> 152370595 | Z25: =+_xlfn.XLOOKUP(PROYECTOS[[#This Row],[MUNICIPIO]],'4.CAP_ENDMNT'!B:B,'4.CAP_ENDMNT'!I:I,0,0,1) -> 15239858716 | AA25: =+_xlfn.XLOOKUP(PROYECTOS[[#This Row],[MUNICIPIO]],'4.CAP_ENDMNT'!B:B,'4.CAP_ENDMNT'!J:J,0,0,1) -> 0.6655997 | AB25: =+_xlfn.XLOOKUP(PROYECTOS[[#This Row],[MUNICIPIO]],'4.CAP_ENDMNT'!B:B,'4.CAP_ENDMNT'!K:K,0,0,1) -> 7.6565739e+09 | AC25: =+_xlfn.XLOOKUP(PROYECTOS[[#This Row],[MUNICIPIO]],'4.CAP_ENDMNT'!B:B,'4.CAP_ENDMNT'!L:L,0,0,1) -> 6.1252591e+09 | AD25: =+_xlfn.XLOOKUP(PROYECTOS[[#This Row],[MUNICIPIO]],'4.CAP_ENDMNT'!B:B,'4.CAP_ENDMNT'!M:M,0,0,1) -> 4.5939443e+09 | AE25: =+_xlfn.XLOOKUP(PROYECTOS[[#This Row],[MUNICIPIO]],'4.CAP_ENDMNT'!B:B,'4.CAP_ENDMNT'!N:N,0,0,1) -> 0.99000184 | AF25: =+_xlfn.XLOOKUP(PROYECTOS[[#This Row],[MUNICIPIO]],'4.CAP_ENDMNT'!B:B,'4.CAP_ENDMNT'!O:O,0,0,1) -> 0.53987925 | AG25: =+_xlfn.XLOOKUP(PROYECTOS[[#This Row],[MUNICIPIO]],'4.CAP_ENDMNT'!B:B,'4.CAP_ENDMNT'!P:P,0,0,1) -> 0.8 | AH25: =+_xlfn.XLOOKUP(PROYECTOS[[#This Row],[MUNICIPIO]],'4.CAP_ENDMNT'!B:B,'4.CAP_ENDMNT'!Q:Q,0,0,1) -> Cumple | AI25: =+_xlfn.XLOOKUP(PROYECTOS[[#This Row],[MUNICIPIO]],'4.CAP_ENDMNT'!B:B,'4.CAP_ENDMNT'!V:V,0,0,1) -> 9.1878886e+08 | AJ25: =+_xlfn.XLOOKUP(PROYECTOS[[#This Row],[MUNICIPIO]],'4.CAP_ENDMNT'!B:B,'4.CAP_ENDMNT'!Y:Y,0,0,1) -> -5.1240425e+09
A26: 28 | B26: Pavimentación vía secundaria Barbosa - Concepción | C26: =+_xlfn.XLOOKUP(PROYECTOS[[#This Row],[ID_NECESIDAD]],'1.RADICADOS'!G:G,'1.RADICADOS'!C:C,0,0,1)*1 -> 45448 | D26: Barbosa | E26: =+_xlfn.XLOOKUP(PROYECTOS[[#This Row],[MUNICIPIO]],MUNICIPIOS!A:A,MUNICIPIOS!E:E,0,0,1) -> Valle de Aburrá | F26: =+_xlfn.XLOOKUP(PROYECTOS[[#This Row],[MUNICIPIO]],MUNICIPIOS!A:A,MUNICIPIOS!F:F,0,0,1) -> -75.331627 | G26: =+_xlfn.XLOOKUP(PROYECTOS[[#This Row],[MUNICIPIO]],MUNICIPIOS!A:A,MUNICIPIOS!G:G,0,0,1) -> 6,439195 | H26: =+_xlfn.XLOOKUP(PROYECTOS[[#This Row],[MUNICIPIO]],MUNICIPIOS!A:A,MUNICIPIOS!B:B,0,0,1) -> 0 | I26: =+_xlfn.XLOOKUP(PROYECTOS[[#This Row],[MUNICIPIO]],MUNICIPIOS!A:A,MUNICIPIOS!C:C,0,0,1) -> 0 | J26: {=_xlfn.TEXTJOIN(" ", TRUE, IF(radicados[ID PROYECTOS]=A26, radicados[RADICADO], ""))} -> 2024010201559 | K26: 2 | M26: Pavimento Flexible | N26: Segundo Orden | O26: Vías secundarias mejoradas | P26: Se ejecuto atravez de otro programa | T26: =+_xlfn.XLOOKUP(PROYECTOS[[#This Row],[MUNICIPIO]],'4.CAP_ENDMNT'!B:B,'4.CAP_ENDMNT'!C:C,0,0,1) -> 4 | U26: =+_xlfn.XLOOKUP(PROYECTOS[[#This Row],[MUNICIPIO]],'4.CAP_ENDMNT'!B:B,'4.CAP_ENDMNT'!D:D,0,0,1) -> 5.6592203e+10 | V26: =+_xlfn.XLOOKUP(PROYECTOS[[#This Row],[MUNICIPIO]],'4.CAP_ENDMNT'!B:B,'4.CAP_ENDMNT'!E:E,0,0,1) -> 2.4375973e+10 | W26: =+_xlfn.XLOOKUP(PROYECTOS[[#This Row],[MUNICIPIO]],'4.CAP_ENDMNT'!B:B,'4.CAP_ENDMNT'!F:F,0,0,1) -> 3.2216231e+10 | X26: =+_xlfn.XLOOKUP(PROYECTOS[[#This Row],[MUNICIPIO]],'4.CAP_ENDMNT'!B:B,'4.CAP_ENDMNT'!G:G,0,0,1) -> 0 | Y26: =+_xlfn.XLOOKUP(PROYECTOS[[#This Row],[MUNICIPIO]],'4.CAP_ENDMNT'!B:B,'4.CAP_ENDMNT'!H:H,0,0,1) -> 1.5044963e+10 | Z26: =+_xlfn.XLOOKUP(PROYECTOS[[#This Row],[MUNICIPIO]],'4.CAP_ENDMNT'!B:B,'4.CAP_ENDMNT'!I:I,0,0,1) -> 1.5044963e+10 | AA26: =+_xlfn.XLOOKUP(PROYECTOS[[#This Row],[MUNICIPIO]],'4.CAP_ENDMNT'!B:B,'4.CAP_ENDMNT'!J:J,0,0,1) -> 0.26584869 | AB26: =+_xlfn.XLOOKUP(PROYECTOS[[#This Row],[MUNICIPIO]],'4.CAP_ENDMNT'!B:B,'4.CAP_ENDMNT'!K:K,0,0,1) -> 4.154724e+10 | AC26: =+_xlfn.XLOOKUP(PROYECTOS[[#This Row],[MUNICIPIO]],'4.CAP_ENDMNT'!B:B,'4.CAP_ENDMNT'!L:L,0,0,1) -> 3.3237792e+10 | AD26: =+_xlfn.XLOOKUP(PROYECTOS[[#This Row],[MUNICIPIO]],'4.CAP_ENDMNT'!B:B,'4.CAP_ENDMNT'!M:M,0,0,1) -> 2.4928344e+10 | AE26: =+_xlfn.XLOOKUP(PROYECTOS[[#This Row],[MUNICIPIO]],'4.CAP_ENDMNT'!B:B,'4.CAP_ENDMNT'!N:N,0,0,1) -> 0 | AF26: =+_xlfn.XLOOKUP(PROYECTOS[[#This Row],[MUNICIPIO]],'4.CAP_ENDMNT'!B:B,'4.CAP_ENDMNT'!O:O,0,0,1) -> 0.60385208 | AG26: =+_xlfn.XLOOKUP(PROYECTOS[[#This Row],[MUNICIPIO]],'4.CAP_ENDMNT'!B:B,'4.CAP_ENDMNT'!P:P,0,0,1) -> 0.8 | AH26: =+_xlfn.XLOOKUP(PROYECTOS[[#This Row],[MUNICIPIO]],'4.CAP_ENDMNT'!B:B,'4.CAP_ENDMNT'!Q:Q,0,0,1) -> Cumple | AI26: =+_xlfn.XLOOKUP(PROYECTOS[[#This Row],[MUNICIPIO]],'4.CAP_ENDMNT'!B:B,'4.CAP_ENDMNT'!V:V,0,0,1) -> 4.9856688e+09 | AJ26: =+_xlfn.XLOOKUP(PROYECTOS[[#This Row],[MUNICIPIO]],'4.CAP_ENDMNT'!B:B,'4.CAP_ENDMNT'!Y:Y,0,0,1) -> -3.1357431e+10
A27: 29 | B27: Mejoramiento y mantenimiento mediante pavimentación en asfalto de la vía El Chaquiro (Ruta 25) - corregimiento de Aragón (Código 25AN10) Zona rural del municipio de Santa Rosa de Osos - Antioquia | C27: =+_xlfn.XLOOKUP(PROYECTOS[[#This Row],[ID_NECESIDAD]],'1.RADICADOS'!G:G,'1.RADICADOS'!C:C,0,0,1)*1 -> 45540 | D27: Santa Rosa de Osos | E27: =+_xlfn.XLOOKUP(PROYECTOS[[#This Row],[MUNICIPIO]],MUNICIPIOS!A:A,MUNICIPIOS!E:E,0,0,1) -> Norte | F27: =+_xlfn.XLOOKUP(PROYECTOS[[#This Row],[MUNICIPIO]],MUNICIPIOS!A:A,MUNICIPIOS!F:F,0,0,1) -> -75.460723 | G27: =+_xlfn.XLOOKUP(PROYECTOS[[#This Row],[MUNICIPIO]],MUNICIPIOS!A:A,MUNICIPIOS!G:G,0,0,1) -> 6,643366 | H27: =+_xlfn.XLOOKUP(PROYECTOS[[#This Row],[MUNICIPIO]],MUNICIPIOS!A:A,MUNICIPIOS!B:B,0,0,1) -> 0 | I27: =+_xlfn.XLOOKUP(PROYECTOS[[#This Row],[MUNICIPIO]],MUNICIPIOS!A:A,MUNICIPIOS!C:C,0,0,1) -> 0 | J27: {=_xlfn.TEXTJOIN(" ", TRUE, IF(radicados[ID PROYECTOS]=A27, radicados[RADICADO], ""))} -> 2024010209802 | K27: 1 | M27: Pavimento Flexible | N27: Segundo Orden | O27: Vías secundarias mejoradas | T27: =+_xlfn.XLOOKUP(PROYECTOS[[#This Row],[MUNICIPIO]],'4.CAP_ENDMNT'!B:B,'4.CAP_ENDMNT'!C:C,0,0,1) -> 5 | U27: =+_xlfn.XLOOKUP(PROYECTOS[[#This Row],[MUNICIPIO]],'4.CAP_ENDMNT'!B:B,'4.CAP_ENDMNT'!D:D,0,0,1) -> 3.791106e+10 | V27: =+_xlfn.XLOOKUP(PROYECTOS[[#This Row],[MUNICIPIO]],'4.CAP_ENDMNT'!B:B,'4.CAP_ENDMNT'!E:E,0,0,1) -> 1.2962308e+10 | W27: =+_xlfn.XLOOKUP(PROYECTOS[[#This Row],[MUNICIPIO]],'4.CAP_ENDMNT'!B:B,'4.CAP_ENDMNT'!F:F,0,0,1) -> 2.4948751e+10 | X27: =+_xlfn.XLOOKUP(PROYECTOS[[#This Row],[MUNICIPIO]],'4.CAP_ENDMNT'!B:B,'4.CAP_ENDMNT'!G:G,0,0,1) -> 8.2588586e+09 | Y27: =+_xlfn.XLOOKUP(PROYECTOS[[#This Row],[MUNICIPIO]],'4.CAP_ENDMNT'!B:B,'4.CAP_ENDMNT'!H:H,0,0,1) -> 2.6598397e+09 | Z27: =+_xlfn.XLOOKUP(PROYECTOS[[#This Row],[MUNICIPIO]],'4.CAP_ENDMNT'!B:B,'4.CAP_ENDMNT'!I:I,0,0,1) -> 10918698235 | AA27: =+_xlfn.XLOOKUP(PROYECTOS[[#This Row],[MUNICIPIO]],'4.CAP_ENDMNT'!B:B,'4.CAP_ENDMNT'!J:J,0,0,1) -> 0.28800826 | AB27: =+_xlfn.XLOOKUP(PROYECTOS[[#This Row],[MUNICIPIO]],'4.CAP_ENDMNT'!B:B,'4.CAP_ENDMNT'!K:K,0,0,1) -> 2.6992361e+10 | AC27: =+_xlfn.XLOOKUP(PROYECTOS[[#This Row],[MUNICIPIO]],'4.CAP_ENDMNT'!B:B,'4.CAP_ENDMNT'!L:L,0,0,1) -> 2.1593889e+10 | AD27: =+_xlfn.XLOOKUP(PROYECTOS[[#This Row],[MUNICIPIO]],'4.CAP_ENDMNT'!B:B,'4.CAP_ENDMNT'!M:M,0,0,1) -> 1.6195417e+10 | AE27: =+_xlfn.XLOOKUP(PROYECTOS[[#This Row],[MUNICIPIO]],'4.CAP_ENDMNT'!B:B,'4.CAP_ENDMNT'!N:N,0,0,1) -> 0.7563959 | AF27: =+_xlfn.XLOOKUP(PROYECTOS[[#This Row],[MUNICIPIO]],'4.CAP_ENDMNT'!B:B,'4.CAP_ENDMNT'!O:O,0,0,1) -> 0.52584208 | AG27: =+_xlfn.XLOOKUP(PROYECTOS[[#This Row],[MUNICIPIO]],'4.CAP_ENDMNT'!B:B,'4.CAP_ENDMNT'!P:P,0,0,1) -> 0.8 | AH27: =+_xlfn.XLOOKUP(PROYECTOS[[#This Row],[MUNICIPIO]],'4.CAP_ENDMNT'!B:B,'4.CAP_ENDMNT'!Q:Q,0,0,1) -> Cumple | AI27: =+_xlfn.XLOOKUP(PROYECTOS[[#This Row],[MUNICIPIO]],'4.CAP_ENDMNT'!B:B,'4.CAP_ENDMNT'!V:V,0,0,1) -> 3.2390834e+09 | AJ27: =+_xlfn.XLOOKUP(PROYECTOS[[#This Row],[MUNICIPIO]],'4.CAP_ENDMNT'!B:B,'4.CAP_ENDMNT'!Y:Y,0,0,1) -> 1.94345e+10
A28: 30 | B28: Construcción de vías urbanas en el municipio de Sonsón Antioquia | C28: =+_xlfn.XLOOKUP(PROYECTOS[[#This Row],[ID_NECESIDAD]],'1.RADICADOS'!G:G,'1.RADICADOS'!C:C,0,0,1)*1 -> 45432 | D28: Sonsón | E28: =+_xlfn.XLOOKUP(PROYECTOS[[#This Row],[MUNICIPIO]],MUNICIPIOS!A:A,MUNICIPIOS!E:E,0,0,1) -> Oriente | F28: =+_xlfn.XLOOKUP(PROYECTOS[[#This Row],[MUNICIPIO]],MUNICIPIOS!A:A,MUNICIPIOS!F:F,0,0,1) -> -75.309596 | G28: =+_xlfn.XLOOKUP(PROYECTOS[[#This Row],[MUNICIPIO]],MUNICIPIOS!A:A,MUNICIPIOS!G:G,0,0,1) -> 5,714851 | H28: =+_xlfn.XLOOKUP(PROYECTOS[[#This Row],[MUNICIPIO]],MUNICIPIOS!A:A,MUNICIPIOS!B:B,0,0,1) -> 0 | I28: =+_xlfn.XLOOKUP(PROYECTOS[[#This Row],[MUNICIPIO]],MUNICIPIOS!A:A,MUNICIPIOS!C:C,0,0,1) -> 1 | J28: {=_xlfn.TEXTJOIN(" ", TRUE, IF(radicados[ID PROYECTOS]=A28, radicados[RADICADO], ""))} -> 2024010224714 | K28: 3 | L28: 4281286508 | M28: Pavimento Flexible | N28: Urbana | O28: Vía urbana mejorada | T28: =+_xlfn.XLOOKUP(PROYECTOS[[#This Row],[MUNICIPIO]],'4.CAP_ENDMNT'!B:B,'4.CAP_ENDMNT'!C:C,0,0,1) -> 5 | U28: =+_xlfn.XLOOKUP(PROYECTOS[[#This Row],[MUNICIPIO]],'4.CAP_ENDMNT'!B:B,'4.CAP_ENDMNT'!D:D,0,0,1) -> 3.5695768e+10 | V28: =+_xlfn.XLOOKUP(PROYECTOS[[#This Row],[MUNICIPIO]],'4.CAP_ENDMNT'!B:B,'4.CAP_ENDMNT'!E:E,0,0,1) -> 1.3532488e+10 | W28: =+_xlfn.XLOOKUP(PROYECTOS[[#This Row],[MUNICIPIO]],'4.CAP_ENDMNT'!B:B,'4.CAP_ENDMNT'!F:F,0,0,1) -> 2.2163279e+10 | X28: =+_xlfn.XLOOKUP(PROYECTOS[[#This Row],[MUNICIPIO]],'4.CAP_ENDMNT'!B:B,'4.CAP_ENDMNT'!G:G,0,0,1) -> 1067761948 | Y28: =+_xlfn.XLOOKUP(PROYECTOS[[#This Row],[MUNICIPIO]],'4.CAP_ENDMNT'!B:B,'4.CAP_ENDMNT'!H:H,0,0,1) -> 4932032890 | Z28: =+_xlfn.XLOOKUP(PROYECTOS[[#This Row],[MUNICIPIO]],'4.CAP_ENDMNT'!B:B,'4.CAP_ENDMNT'!I:I,0,0,1) -> 5999794838 | AA28: =+_xlfn.XLOOKUP(PROYECTOS[[#This Row],[MUNICIPIO]],'4.CAP_ENDMNT'!B:B,'4.CAP_ENDMNT'!J:J,0,0,1) -> 0.16808141 | AB28: =+_xlfn.XLOOKUP(PROYECTOS[[#This Row],[MUNICIPIO]],'4.CAP_ENDMNT'!B:B,'4.CAP_ENDMNT'!K:K,0,0,1) -> 2.9695973e+10 | AC28: =+_xlfn.XLOOKUP(PROYECTOS[[#This Row],[MUNICIPIO]],'4.CAP_ENDMNT'!B:B,'4.CAP_ENDMNT'!L:L,0,0,1) -> 2.3756778e+10 | AD28: =+_xlfn.XLOOKUP(PROYECTOS[[#This Row],[MUNICIPIO]],'4.CAP_ENDMNT'!B:B,'4.CAP_ENDMNT'!M:M,0,0,1) -> 1.7817584e+10 | AE28: =+_xlfn.XLOOKUP(PROYECTOS[[#This Row],[MUNICIPIO]],'4.CAP_ENDMNT'!B:B,'4.CAP_ENDMNT'!N:N,0,0,1) -> 0.17796641 | AF28: =+_xlfn.XLOOKUP(PROYECTOS[[#This Row],[MUNICIPIO]],'4.CAP_ENDMNT'!B:B,'4.CAP_ENDMNT'!O:O,0,0,1) -> 0.40167298 | AG28: =+_xlfn.XLOOKUP(PROYECTOS[[#This Row],[MUNICIPIO]],'4.CAP_ENDMNT'!B:B,'4.CAP_ENDMNT'!P:P,0,0,1) -> 0.8 | AH28: =+_xlfn.XLOOKUP(PROYECTOS[[#This Row],[MUNICIPIO]],'4.CAP_ENDMNT'!B:B,'4.CAP_ENDMNT'!Q:Q,0,0,1) -> Cumple | AI28: =+_xlfn.XLOOKUP(PROYECTOS[[#This Row],[MUNICIPIO]],'4.CAP_ENDMNT'!B:B,'4.CAP_ENDMNT'!V:V,0,0,1) -> 3.5635167e+09 | AJ28: =+_xlfn.XLOOKUP(PROYECTOS[[#This Row],[MUNICIPIO]],'4.CAP_ENDMNT'!B:B,'4.CAP_ENDMNT'!Y:Y,0,0,1) -> -4.6557238e+10
A29: 31 | B29: Solicitud de construcción de vía en el sector Quebrada Arriba Los Lagos y Matazano (Barbosa - Donmatías) | C29: =+_xlfn.XLOOKUP(PROYECTOS[[#This Row],[ID_NECESIDAD]],'1.RADICADOS'!G:G,'1.RADICADOS'!C:C,0,0,1)*1 -> 45436 | D29: Barbosa | E29: =+_xlfn.XLOOKUP(PROYECTOS[[#This Row],[MUNICIPIO]],MUNICIPIOS!A:A,MUNICIPIOS!E:E,0,0,1) -> Valle de Aburrá | F29: =+_xlfn.XLOOKUP(PROYECTOS[[#This Row],[MUNICIPIO]],MUNICIPIOS!A:A,MUNICIPIOS!F:F,0,0,1) -> -75.331627 | G29: =+_xlfn.XLOOKUP(PROYECTOS[[#This Row],[MUNICIPIO]],MUNICIPIOS!A:A,MUNICIPIOS!G:G,0,0,1) -> 6,439195 | H29: =+_xlfn.XLOOKUP(PROYECTOS[[#This Row],[MUNICIPIO]],MUNICIPIOS!A:A,MUNICIPIOS!B:B,0,0,1) -> 0 | I29: =+_xlfn.XLOOKUP(PROYECTOS[[#This Row],[MUNICIPIO]],MUNICIPIOS!A:A,MUNICIPIOS!C:C,0,0,1) -> 0 | J29: {=_xlfn.TEXTJOIN(" ", TRUE, IF(radicados[ID PROYECTOS]=A29, radicados[RADICADO], ""))} -> 2024010233254 | K29: 1 | M29: Pavimento Flexible | N29: Segundo Orden | O29: Vías terciarias mejoradas | P29: No se encuentra mas informacion en radicado relacionado | T29: =+_xlfn.XLOOKUP(PROYECTOS[[#This Row],[MUNICIPIO]],'4.CAP_ENDMNT'!B:B,'4.CAP_ENDMNT'!C:C,0,0,1) -> 4 | U29: =+_xlfn.XLOOKUP(PROYECTOS[[#This Row],[MUNICIPIO]],'4.CAP_ENDMNT'!B:B,'4.CAP_ENDMNT'!D:D,0,0,1) -> 5.6592203e+10 | V29: =+_xlfn.XLOOKUP(PROYECTOS[[#This Row],[MUNICIPIO]],'4.CAP_ENDMNT'!B:B,'4.CAP_ENDMNT'!E:E,0,0,1) -> 2.4375973e+10 | W29: =+_xlfn.XLOOKUP(PROYECTOS[[#This Row],[MUNICIPIO]],'4.CAP_ENDMNT'!B:B,'4.CAP_ENDMNT'!F:F,0,0,1) -> 3.2216231e+10 | X29: =+_xlfn.XLOOKUP(PROYECTOS[[#This Row],[MUNICIPIO]],'4.CAP_ENDMNT'!B:B,'4.CAP_ENDMNT'!G:G,0,0,1) -> 0 | Y29: =+_xlfn.XLOOKUP(PROYECTOS[[#This Row],[MUNICIPIO]],'4.CAP_ENDMNT'!B:B,'4.CAP_ENDMNT'!H:H,0,0,1) -> 1.5044963e+10 | Z29: =+_xlfn.XLOOKUP(PROYECTOS[[#This Row],[MUNICIPIO]],'4.CAP_ENDMNT'!B:B,'4.CAP_ENDMNT'!I:I,0,0,1) -> 1.5044963e+10 | AA29: =+_xlfn.XLOOKUP(PROYECTOS[[#This Row],[MUNICIPIO]],'4.CAP_ENDMNT'!B:B,'4.CAP_ENDMNT'!J:J,0,0,1) -> 0.26584869 | AB29: =+_xlfn.XLOOKUP(PROYECTOS[[#This Row],[MUNICIPIO]],'4.CAP_ENDMNT'!B:B,'4.CAP_ENDMNT'!K:K,0,0,1) -> 4.154724e+10 | AC29: =+_xlfn.XLOOKUP(PROYECTOS[[#This Row],[MUNICIPIO]],'4.CAP_ENDMNT'!B:B,'4.CAP_ENDMNT'!L:L,0,0,1) -> 3.3237792e+10 | AD29: =+_xlfn.XLOOKUP(PROYECTOS[[#This Row],[MUNICIPIO]],'4.CAP_ENDMNT'!B:B,'4.CAP_ENDMNT'!M:M,0,0,1) -> 2.4928344e+10 | AE29: =+_xlfn.XLOOKUP(PROYECTOS[[#This Row],[MUNICIPIO]],'4.CAP_ENDMNT'!B:B,'4.CAP_ENDMNT'!N:N,0,0,1) -> 0 | AF29: =+_xlfn.XLOOKUP(PROYECTOS[[#This Row],[MUNICIPIO]],'4.CAP_ENDMNT'!B:B,'4.CAP_ENDMNT'!O:O,0,0,1) -> 0.60385208 | AG29: =+_xlfn.XLOOKUP(PROYECTOS[[#This Row],[MUNICIPIO]],'4.CAP_ENDMNT'!B:B,'4.CAP_ENDMNT'!P:P,0,0,1) -> 0.8 | AH29: =+_xlfn.XLOOKUP(PROYECTOS[[#This Row],[MUNICIPIO]],'4.CAP_ENDMNT'!B:B,'4.CAP_ENDMNT'!Q:Q,0,0,1) -> Cumple | AI29: =+_xlfn.XLOOKUP(PROYECTOS[[#This Row],[MUNICIPIO]],'4.CAP_ENDMNT'!B:B,'4.CAP_ENDMNT'!V:V,0,0,1) -> 4.9856688e+09 | AJ29: =+_xlfn.XLOOKUP(PROYECTOS[[#This Row],[MUNICIPIO]],'4.CAP_ENDMNT'!B:B,'4.CAP_ENDMNT'!Y:Y,0,0,1) -> -3.1357431e+10
A30: 32 | B30: Construcción de pavimento en el barrio Brisas de Urabá del municipio de San Pedro de Urabá Antioquia | C30: =+_xlfn.XLOOKUP(PROYECTOS[[#This Row],[ID_NECESIDAD]],'1.RADICADOS'!G:G,'1.RADICADOS'!C:C,0,0,1)*1 -> 45388 | D30: San Pedro de Urabá | E30: =+_xlfn.XLOOKUP(PROYECTOS[[#This Row],[MUNICIPIO]],MUNICIPIOS!A:A,MUNICIPIOS!E:E,0,0,1) -> Urabá | F30: =+_xlfn.XLOOKUP(PROYECTOS[[#This Row],[MUNICIPIO]],MUNICIPIOS!A:A,MUNICIPIOS!F:F,0,0,1) -> -76.380567 | G30: =+_xlfn.XLOOKUP(PROYECTOS[[#This Row],[MUNICIPIO]],MUNICIPIOS!A:A,MUNICIPIOS!G:G,0,0,1) -> 8,276884 | H30: =+_xlfn.XLOOKUP(PROYECTOS[[#This Row],[MUNICIPIO]],MUNICIPIOS!A:A,MUNICIPIOS!B:B,0,0,1) -> 1 | I30: =+_xlfn.XLOOKUP(PROYECTOS[[#This Row],[MUNICIPIO]],MUNICIPIOS!A:A,MUNICIPIOS!C:C,0,0,1) -> 1 | J30: {=_xlfn.TEXTJOIN(" ", TRUE, IF(radicados[ID PROYECTOS]=A30, radicados[RADICADO], ""))} -> 2024010246827 | K30: 3 | L30: 2256305783 | M30: Pavimento Flexible | N30: Urbana | O30: Vía urbana mejorada | T30: =+_xlfn.XLOOKUP(PROYECTOS[[#This Row],[MUNICIPIO]],'4.CAP_ENDMNT'!B:B,'4.CAP_ENDMNT'!C:C,0,0,1) -> 6 | U30: =+_xlfn.XLOOKUP(PROYECTOS[[#This Row],[MUNICIPIO]],'4.CAP_ENDMNT'!B:B,'4.CAP_ENDMNT'!D:D,0,0,1) -> 1.9508373e+10 | V30: =+_xlfn.XLOOKUP(PROYECTOS[[#This Row],[MUNICIPIO]],'4.CAP_ENDMNT'!B:B,'4.CAP_ENDMNT'!E:E,0,0,1) -> 5.3898343e+09 | W30: =+_xlfn.XLOOKUP(PROYECTOS[[#This Row],[MUNICIPIO]],'4.CAP_ENDMNT'!B:B,'4.CAP_ENDMNT'!F:F,0,0,1) -> 1.4118538e+10 | X30: =+_xlfn.XLOOKUP(PROYECTOS[[#This Row],[MUNICIPIO]],'4.CAP_ENDMNT'!B:B,'4.CAP_ENDMNT'!G:G,0,0,1) -> 2594281047 | Y30: =+_xlfn.XLOOKUP(PROYECTOS[[#This Row],[MUNICIPIO]],'4.CAP_ENDMNT'!B:B,'4.CAP_ENDMNT'!H:H,0,0,1) -> 1833333333 | Z30: =+_xlfn.XLOOKUP(PROYECTOS[[#This Row],[MUNICIPIO]],'4.CAP_ENDMNT'!B:B,'4.CAP_ENDMNT'!I:I,0,0,1) -> 4427614380 | AA30: =+_xlfn.XLOOKUP(PROYECTOS[[#This Row],[MUNICIPIO]],'4.CAP_ENDMNT'!B:B,'4.CAP_ENDMNT'!J:J,0,0,1) -> 0.2269597 | AB30: =+_xlfn.XLOOKUP(PROYECTOS[[#This Row],[MUNICIPIO]],'4.CAP_ENDMNT'!B:B,'4.CAP_ENDMNT'!K:K,0,0,1) -> 1.5080758e+10 | AC30: =+_xlfn.XLOOKUP(PROYECTOS[[#This Row],[MUNICIPIO]],'4.CAP_ENDMNT'!B:B,'4.CAP_ENDMNT'!L:L,0,0,1) -> 1.2064607e+10 | AD30: =+_xlfn.XLOOKUP(PROYECTOS[[#This Row],[MUNICIPIO]],'4.CAP_ENDMNT'!B:B,'4.CAP_ENDMNT'!M:M,0,0,1) -> 9.048455e+09 | AE30: =+_xlfn.XLOOKUP(PROYECTOS[[#This Row],[MUNICIPIO]],'4.CAP_ENDMNT'!B:B,'4.CAP_ENDMNT'!N:N,0,0,1) -> 0.58593202 | AF30: =+_xlfn.XLOOKUP(PROYECTOS[[#This Row],[MUNICIPIO]],'4.CAP_ENDMNT'!B:B,'4.CAP_ENDMNT'!O:O,0,0,1) -> 0.58851113 | AG30: =+_xlfn.XLOOKUP(PROYECTOS[[#This Row],[MUNICIPIO]],'4.CAP_ENDMNT'!B:B,'4.CAP_ENDMNT'!P:P,0,0,1) -> 0.8 | AH30: =+_xlfn.XLOOKUP(PROYECTOS[[#This Row],[MUNICIPIO]],'4.CAP_ENDMNT'!B:B,'4.CAP_ENDMNT'!Q:Q,0,0,1) -> Cumple | AI30: =+_xlfn.XLOOKUP(PROYECTOS[[#This Row],[MUNICIPIO]],'4.CAP_ENDMNT'!B:B,'4.CAP_ENDMNT'!V:V,0,0,1) -> 1.809691e+09 | AJ30: =+_xlfn.XLOOKUP(PROYECTOS[[#This Row],[MUNICIPIO]],'4.CAP_ENDMNT'!B:B,'4.CAP_ENDMNT'!Y:Y,0,0,1) -> -1.2348844e+10
A31: 33 | B31: Mejoramiento de vías del circuito productivo Pueblorrico . Ye a la Bodega - La Bodega (Andes) | C31: =+_xlfn.XLOOKUP(PROYECTOS[[#This Row],[ID_NECESIDAD]],'1.RADICADOS'!G:G,'1.RADICADOS'!C:C,0,0,1)*1 -> 45602 | D31: Pueblorrico | E31: =+_xlfn.XLOOKUP(PROYECTOS[[#This Row],[MUNICIPIO]],MUNICIPIOS!A:A,MUNICIPIOS!E:E,0,0,1) -> Suroeste | F31: =+_xlfn.XLOOKUP(PROYECTOS[[#This Row],[MUNICIPIO]],MUNICIPIOS!A:A,MUNICIPIOS!F:F,0,0,1) -> -75.839903 | G31: =+_xlfn.XLOOKUP(PROYECTOS[[#This Row],[MUNICIPIO]],MUNICIPIOS!A:A,MUNICIPIOS!G:G,0,0,1) -> 5,79158 | H31: =+_xlfn.XLOOKUP(PROYECTOS[[#This Row],[MUNICIPIO]],MUNICIPIOS!A:A,MUNICIPIOS!B:B,0,0,1) -> 0 | I31: =+_xlfn.XLOOKUP(PROYECTOS[[#This Row],[MUNICIPIO]],MUNICIPIOS!A:A,MUNICIPIOS!C:C,0,0,1) -> 0 | J31: {=_xlfn.TEXTJOIN(" ", TRUE, IF(radicados[ID PROYECTOS]=A31, radicados[RADICADO], ""))} -> 2024010258317 | K31: 3 | L31: 4943542014 | M31: Pavimento Flexible | N31: Segundo Orden | O31: Vías secundarias mejoradas | P31: EL proyecto sera desarrollado entre el K0+000 saliendo de la cabecera municipal de Pueblorrico hasta el K1+580 sector El Barcino | T31: =+_xlfn.XLOOKUP(PROYECTOS[[#This Row],[MUNICIPIO]],'4.CAP_ENDMNT'!B:B,'4.CAP_ENDMNT'!C:C,0,0,1) -> 6 | U31: =+_xlfn.XLOOKUP(PROYECTOS[[#This Row],[MUNICIPIO]],'4.CAP_ENDMNT'!B:B,'4.CAP_ENDMNT'!D:D,0,0,1) -> 7.4089579e+09 | V31: =+_xlfn.XLOOKUP(PROYECTOS[[#This Row],[MUNICIPIO]],'4.CAP_ENDMNT'!B:B,'4.CAP_ENDMNT'!E:E,0,0,1) -> 2.7261792e+09 | W31: =+_xlfn.XLOOKUP(PROYECTOS[[#This Row],[MUNICIPIO]],'4.CAP_ENDMNT'!B:B,'4.CAP_ENDMNT'!F:F,0,0,1) -> 4.6827787e+09 | X31: =+_xlfn.XLOOKUP(PROYECTOS[[#This Row],[MUNICIPIO]],'4.CAP_ENDMNT'!B:B,'4.CAP_ENDMNT'!G:G,0,0,1) -> 1117539497 | Y31: =+_xlfn.XLOOKUP(PROYECTOS[[#This Row],[MUNICIPIO]],'4.CAP_ENDMNT'!B:B,'4.CAP_ENDMNT'!H:H,0,0,1) -> 0 | Z31: =+_xlfn.XLOOKUP(PROYECTOS[[#This Row],[MUNICIPIO]],'4.CAP_ENDMNT'!B:B,'4.CAP_ENDMNT'!I:I,0,0,1) -> 1117539497 | AA31: =+_xlfn.XLOOKUP(PROYECTOS[[#This Row],[MUNICIPIO]],'4.CAP_ENDMNT'!B:B,'4.CAP_ENDMNT'!J:J,0,0,1) -> 0.15083626 | AB31: =+_xlfn.XLOOKUP(PROYECTOS[[#This Row],[MUNICIPIO]],'4.CAP_ENDMNT'!B:B,'4.CAP_ENDMNT'!K:K,0,0,1) -> 6.2914184e+09 | AC31: =+_xlfn.XLOOKUP(PROYECTOS[[#This Row],[MUNICIPIO]],'4.CAP_ENDMNT'!B:B,'4.CAP_ENDMNT'!L:L,0,0,1) -> 5.0331348e+09 | AD31: =+_xlfn.XLOOKUP(PROYECTOS[[#This Row],[MUNICIPIO]],'4.CAP_ENDMNT'!B:B,'4.CAP_ENDMNT'!M:M,0,0,1) -> 3.7748511e+09 | AE31: =+_xlfn.XLOOKUP(PROYECTOS[[#This Row],[MUNICIPIO]],'4.CAP_ENDMNT'!B:B,'4.CAP_ENDMNT'!N:N,0,0,1) -> 1 | AF31: =+_xlfn.XLOOKUP(PROYECTOS[[#This Row],[MUNICIPIO]],'4.CAP_ENDMNT'!B:B,'4.CAP_ENDMNT'!O:O,0,0,1) -> 0.78495374 | AG31: =+_xlfn.XLOOKUP(PROYECTOS[[#This Row],[MUNICIPIO]],'4.CAP_ENDMNT'!B:B,'4.CAP_ENDMNT'!P:P,0,0,1) -> 0.8 | AH31: =+_xlfn.XLOOKUP(PROYECTOS[[#This Row],[MUNICIPIO]],'4.CAP_ENDMNT'!B:B,'4.CAP_ENDMNT'!Q:Q,0,0,1) -> Riesgo | AI31: =+_xlfn.XLOOKUP(PROYECTOS[[#This Row],[MUNICIPIO]],'4.CAP_ENDMNT'!B:B,'4.CAP_ENDMNT'!V:V,0,0,1) -> 7.5497021e+08 | AJ31: =+_xlfn.XLOOKUP(PROYECTOS[[#This Row],[MUNICIPIO]],'4.CAP_ENDMNT'!B:B,'4.CAP_ENDMNT'!Y:Y,0,0,1) -> -4.5201446e+09
A32: 34 | B32: Parque principal - Segunda etapa | C32: =+_xlfn.XLOOKUP(PROYECTOS[[#This Row],[ID_NECESIDAD]],'1.RADICADOS'!G:G,'1.RADICADOS'!C:C,0,0,1)*1 -> 45539 | D32: Valparaíso | E32: =+_xlfn.XLOOKUP(PROYECTOS[[#This Row],[MUNICIPIO]],MUNICIPIOS!A:A,MUNICIPIOS!E:E,0,0,1) -> Suroeste | F32: =+_xlfn.XLOOKUP(PROYECTOS[[#This Row],[MUNICIPIO]],MUNICIPIOS!A:A,MUNICIPIOS!F:F,0,0,1) -> -75.624452 | G32: =+_xlfn.XLOOKUP(PROYECTOS[[#This Row],[MUNICIPIO]],MUNICIPIOS!A:A,MUNICIPIOS!G:G,0,0,1) -> 5.614555 | H32: =+_xlfn.XLOOKUP(PROYECTOS[[#This Row],[MUNICIPIO]],MUNICIPIOS!A:A,MUNICIPIOS!B:B,0,0,1) -> 0 | I32: =+_xlfn.XLOOKUP(PROYECTOS[[#This Row],[MUNICIPIO]],MUNICIPIOS!A:A,MUNICIPIOS!C:C,0,0,1) -> 0 | J32: {=_xlfn.TEXTJOIN(" ", TRUE, IF(radicados[ID PROYECTOS]=A32, radicados[RADICADO], ""))} -> 2024010152199 | K32: 1 | M32: Parque | N32: N/A | O32: Espacio público adecuado | P32: peticion de cooperar con la construccion de la segunda etapa del parque principal | T32: =+_xlfn.XLOOKUP(PROYECTOS[[#This Row],[MUNICIPIO]],'4.CAP_ENDMNT'!B:B,'4.CAP_ENDMNT'!C:C,0,0,1) -> 6 | U32: =+_xlfn.XLOOKUP(PROYECTOS[[#This Row],[MUNICIPIO]],'4.CAP_ENDMNT'!B:B,'4.CAP_ENDMNT'!D:D,0,0,1) -> 6.4857157e+09 | V32: =+_xlfn.XLOOKUP(PROYECTOS[[#This Row],[MUNICIPIO]],'4.CAP_ENDMNT'!B:B,'4.CAP_ENDMNT'!E:E,0,0,1) -> 3.71711e+09 | W32: =+_xlfn.XLOOKUP(PROYECTOS[[#This Row],[MUNICIPIO]],'4.CAP_ENDMNT'!B:B,'4.CAP_ENDMNT'!F:F,0,0,1) -> 2.7686057e+09 | X32: =+_xlfn.XLOOKUP(PROYECTOS[[#This Row],[MUNICIPIO]],'4.CAP_ENDMNT'!B:B,'4.CAP_ENDMNT'!G:G,0,0,1) -> 5.9856176e+08 | Y32: =+_xlfn.XLOOKUP(PROYECTOS[[#This Row],[MUNICIPIO]],'4.CAP_ENDMNT'!B:B,'4.CAP_ENDMNT'!H:H,0,0,1) -> 823222224 | Z32: =+_xlfn.XLOOKUP(PROYECTOS[[#This Row],[MUNICIPIO]],'4.CAP_ENDMNT'!B:B,'4.CAP_ENDMNT'!I:I,0,0,1) -> 1.421784e+09 | AA32: =+_xlfn.XLOOKUP(PROYECTOS[[#This Row],[MUNICIPIO]],'4.CAP_ENDMNT'!B:B,'4.CAP_ENDMNT'!J:J,0,0,1) -> 0.21921775 | AB32: =+_xlfn.XLOOKUP(PROYECTOS[[#This Row],[MUNICIPIO]],'4.CAP_ENDMNT'!B:B,'4.CAP_ENDMNT'!K:K,0,0,1) -> 5.0639317e+09 | AC32: =+_xlfn.XLOOKUP(PROYECTOS[[#This Row],[MUNICIPIO]],'4.CAP_ENDMNT'!B:B,'4.CAP_ENDMNT'!L:L,0,0,1) -> 4.0511454e+09 | AD32: =+_xlfn.XLOOKUP(PROYECTOS[[#This Row],[MUNICIPIO]],'4.CAP_ENDMNT'!B:B,'4.CAP_ENDMNT'!M:M,0,0,1) -> 3.038359e+09 | AE32: =+_xlfn.XLOOKUP(PROYECTOS[[#This Row],[MUNICIPIO]],'4.CAP_ENDMNT'!B:B,'4.CAP_ENDMNT'!N:N,0,0,1) -> 0.42099346 | AF32: =+_xlfn.XLOOKUP(PROYECTOS[[#This Row],[MUNICIPIO]],'4.CAP_ENDMNT'!B:B,'4.CAP_ENDMNT'!O:O,0,0,1) -> 0.68598337 | AG32: =+_xlfn.XLOOKUP(PROYECTOS[[#This Row],[MUNICIPIO]],'4.CAP_ENDMNT'!B:B,'4.CAP_ENDMNT'!P:P,0,0,1) -> 0.8 | AH32: =+_xlfn.XLOOKUP(PROYECTOS[[#This Row],[MUNICIPIO]],'4.CAP_ENDMNT'!B:B,'4.CAP_ENDMNT'!Q:Q,0,0,1) -> Cumple | AI32: =+_xlfn.XLOOKUP(PROYECTOS[[#This Row],[MUNICIPIO]],'4.CAP_ENDMNT'!B:B,'4.CAP_ENDMNT'!V:V,0,0,1) -> 6.0767181e+08 | AJ32: =+_xlfn.XLOOKUP(PROYECTOS[[#This Row],[MUNICIPIO]],'4.CAP_ENDMNT'!B:B,'4.CAP_ENDMNT'!Y:Y,0,0,1) -> -1.7013363e+09
A33: 35 | B33: Construcción de la antigua plaza de mercado para adecuar y poner en funcionamiento la casa de justicia o centro de convivencia | C33: =+_xlfn.XLOOKUP(PROYECTOS[[#This Row],[ID_NECESIDAD]],'1.RADICADOS'!G:G,'1.RADICADOS'!C:C,0,0,1)*1 -> 45630 | D33: Amagá | E33: =+_xlfn.XLOOKUP(PROYECTOS[[#This Row],[MUNICIPIO]],MUNICIPIOS!A:A,MUNICIPIOS!E:E,0,0,1) -> Suroeste | F33: =+_xlfn.XLOOKUP(PROYECTOS[[#This Row],[MUNICIPIO]],MUNICIPIOS!A:A,MUNICIPIOS!F:F,0,0,1) -> -75.702188 | G33: =+_xlfn.XLOOKUP(PROYECTOS[[#This Row],[MUNICIPIO]],MUNICIPIOS!A:A,MUNICIPIOS!G:G,0,0,1) -> 6,038708 | H33: =+_xlfn.XLOOKUP(PROYECTOS[[#This Row],[MUNICIPIO]],MUNICIPIOS!A:A,MUNICIPIOS!B:B,0,0,1) -> 0 | I33: =+_xlfn.XLOOKUP(PROYECTOS[[#This Row],[MUNICIPIO]],MUNICIPIOS!A:A,MUNICIPIOS!C:C,0,0,1) -> 0 | J33: {=_xlfn.TEXTJOIN(" ", TRUE, IF(radicados[ID PROYECTOS]=A33, radicados[RADICADO], ""))} -> 2024010159071 2024020058554 | K33: 2 | M33: Plaza de Mercado | N33: N/A | O33: Equipamientos construidos | P33: Plaza de mercado postulada para adecuar y poner en funcionamiento la casa de justicia o centro de convivencia | T33: =+_xlfn.XLOOKUP(PROYECTOS[[#This Row],[MUNICIPIO]],'4.CAP_ENDMNT'!B:B,'4.CAP_ENDMNT'!C:C,0,0,1) -> 6 | U33: =+_xlfn.XLOOKUP(PROYECTOS[[#This Row],[MUNICIPIO]],'4.CAP_ENDMNT'!B:B,'4.CAP_ENDMNT'!D:D,0,0,1) -> 2.5390387e+10 | V33: =+_xlfn.XLOOKUP(PROYECTOS[[#This Row],[MUNICIPIO]],'4.CAP_ENDMNT'!B:B,'4.CAP_ENDMNT'!E:E,0,0,1) -> 8.3578336e+09 | W33: =+_xlfn.XLOOKUP(PROYECTOS[[#This Row],[MUNICIPIO]],'4.CAP_ENDMNT'!B:B,'4.CAP_ENDMNT'!F:F,0,0,1) -> 1.7032554e+10 | X33: =+_xlfn.XLOOKUP(PROYECTOS[[#This Row],[MUNICIPIO]],'4.CAP_ENDMNT'!B:B,'4.CAP_ENDMNT'!G:G,0,0,1) -> 4689987006 | Y33: =+_xlfn.XLOOKUP(PROYECTOS[[#This Row],[MUNICIPIO]],'4.CAP_ENDMNT'!B:B,'4.CAP_ENDMNT'!H:H,0,0,1) -> 6272045606 | Z33: =+_xlfn.XLOOKUP(PROYECTOS[[#This Row],[MUNICIPIO]],'4.CAP_ENDMNT'!B:B,'4.CAP_ENDMNT'!I:I,0,0,1) -> 10962032612 | AA33: =+_xlfn.XLOOKUP(PROYECTOS[[#This Row],[MUNICIPIO]],'4.CAP_ENDMNT'!B:B,'4.CAP_ENDMNT'!J:J,0,0,1) -> 0.43173948 | AB33: =+_xlfn.XLOOKUP(PROYECTOS[[#This Row],[MUNICIPIO]],'4.CAP_ENDMNT'!B:B,'4.CAP_ENDMNT'!K:K,0,0,1) -> 1.4428355e+10 | AC33: =+_xlfn.XLOOKUP(PROYECTOS[[#This Row],[MUNICIPIO]],'4.CAP_ENDMNT'!B:B,'4.CAP_ENDMNT'!L:L,0,0,1) -> 1.1542684e+10 | AD33: =+_xlfn.XLOOKUP(PROYECTOS[[#This Row],[MUNICIPIO]],'4.CAP_ENDMNT'!B:B,'4.CAP_ENDMNT'!M:M,0,0,1) -> 8.6570129e+09 | AE33: =+_xlfn.XLOOKUP(PROYECTOS[[#This Row],[MUNICIPIO]],'4.CAP_ENDMNT'!B:B,'4.CAP_ENDMNT'!N:N,0,0,1) -> 0.42783918 | AF33: =+_xlfn.XLOOKUP(PROYECTOS[[#This Row],[MUNICIPIO]],'4.CAP_ENDMNT'!B:B,'4.CAP_ENDMNT'!O:O,0,0,1) -> 0.46347627 | AG33: =+_xlfn.XLOOKUP(PROYECTOS[[#This Row],[MUNICIPIO]],'4.CAP_ENDMNT'!B:B,'4.CAP_ENDMNT'!P:P,0,0,1) -> 0.8 | AH33: =+_xlfn.XLOOKUP(PROYECTOS[[#This Row],[MUNICIPIO]],'4.CAP_ENDMNT'!B:B,'4.CAP_ENDMNT'!Q:Q,0,0,1) -> Cumple | AI33: =+_xlfn.XLOOKUP(PROYECTOS[[#This Row],[MUNICIPIO]],'4.CAP_ENDMNT'!B:B,'4.CAP_ENDMNT'!V:V,0,0,1) -> 1.7314026e+09 | AJ33: =+_xlfn.XLOOKUP(PROYECTOS[[#This Row],[MUNICIPIO]],'4.CAP_ENDMNT'!B:B,'4.CAP_ENDMNT'!Y:Y,0,0,1) -> 4.8067604e+09
A34: 36 | B34: Construcción del ecoparque lineal La Vara en el municipio de San Pedro de Urabá | C34: =+_xlfn.XLOOKUP(PROYECTOS[[#This Row],[ID_NECESIDAD]],'1.RADICADOS'!G:G,'1.RADICADOS'!C:C,0,0,1)*1 -> 45398 | D34: San Pedro de Urabá | E34: =+_xlfn.XLOOKUP(PROYECTOS[[#This Row],[MUNICIPIO]],MUNICIPIOS!A:A,MUNICIPIOS!E:E,0,0,1) -> Urabá | F34: =+_xlfn.XLOOKUP(PROYECTOS[[#This Row],[MUNICIPIO]],MUNICIPIOS!A:A,MUNICIPIOS!F:F,0,0,1) -> -76.380567 | G34: =+_xlfn.XLOOKUP(PROYECTOS[[#This Row],[MUNICIPIO]],MUNICIPIOS!A:A,MUNICIPIOS!G:G,0,0,1) -> 8,276884 | H34: =+_xlfn.XLOOKUP(PROYECTOS[[#This Row],[MUNICIPIO]],MUNICIPIOS!A:A,MUNICIPIOS!B:B,0,0,1) -> 1 | I34: =+_xlfn.XLOOKUP(PROYECTOS[[#This Row],[MUNICIPIO]],MUNICIPIOS!A:A,MUNICIPIOS!C:C,0,0,1) -> 1 | J34: {=_xlfn.TEXTJOIN(" ", TRUE, IF(radicados[ID PROYECTOS]=A34, radicados[RADICADO], ""))} -> 2024010163837 | K34: 3 | L34: 2500751722 | M34: Parque | N34: N/A | O34: Espacio público adecuado | T34: =+_xlfn.XLOOKUP(PROYECTOS[[#This Row],[MUNICIPIO]],'4.CAP_ENDMNT'!B:B,'4.CAP_ENDMNT'!C:C,0,0,1) -> 6 | U34: =+_xlfn.XLOOKUP(PROYECTOS[[#This Row],[MUNICIPIO]],'4.CAP_ENDMNT'!B:B,'4.CAP_ENDMNT'!D:D,0,0,1) -> 1.9508373e+10 | V34: =+_xlfn.XLOOKUP(PROYECTOS[[#This Row],[MUNICIPIO]],'4.CAP_ENDMNT'!B:B,'4.CAP_ENDMNT'!E:E,0,0,1) -> 5.3898343e+09 | W34: =+_xlfn.XLOOKUP(PROYECTOS[[#This Row],[MUNICIPIO]],'4.CAP_ENDMNT'!B:B,'4.CAP_ENDMNT'!F:F,0,0,1) -> 1.4118538e+10 | X34: =+_xlfn.XLOOKUP(PROYECTOS[[#This Row],[MUNICIPIO]],'4.CAP_ENDMNT'!B:B,'4.CAP_ENDMNT'!G:G,0,0,1) -> 2594281047 | Y34: =+_xlfn.XLOOKUP(PROYECTOS[[#This Row],[MUNICIPIO]],'4.CAP_ENDMNT'!B:B,'4.CAP_ENDMNT'!H:H,0,0,1) -> 1833333333 | Z34: =+_xlfn.XLOOKUP(PROYECTOS[[#This Row],[MUNICIPIO]],'4.CAP_ENDMNT'!B:B,'4.CAP_ENDMNT'!I:I,0,0,1) -> 4427614380 | AA34: =+_xlfn.XLOOKUP(PROYECTOS[[#This Row],[MUNICIPIO]],'4.CAP_ENDMNT'!B:B,'4.CAP_ENDMNT'!J:J,0,0,1) -> 0.2269597 | AB34: =+_xlfn.XLOOKUP(PROYECTOS[[#This Row],[MUNICIPIO]],'4.CAP_ENDMNT'!B:B,'4.CAP_ENDMNT'!K:K,0,0,1) -> 1.5080758e+10 | AC34: =+_xlfn.XLOOKUP(PROYECTOS[[#This Row],[MUNICIPIO]],'4.CAP_ENDMNT'!B:B,'4.CAP_ENDMNT'!L:L,0,0,1) -> 1.2064607e+10 | AD34: =+_xlfn.XLOOKUP(PROYECTOS[[#This Row],[MUNICIPIO]],'4.CAP_ENDMNT'!B:B,'4.CAP_ENDMNT'!M:M,0,0,1) -> 9.048455e+09 | AE34: =+_xlfn.XLOOKUP(PROYECTOS[[#This Row],[MUNICIPIO]],'4.CAP_ENDMNT'!B:B,'4.CAP_ENDMNT'!N:N,0,0,1) -> 0.58593202 | AF34: =+_xlfn.XLOOKUP(PROYECTOS[[#This Row],[MUNICIPIO]],'4.CAP_ENDMNT'!B:B,'4.CAP_ENDMNT'!O:O,0,0,1) -> 0.58851113 | AG34: =+_xlfn.XLOOKUP(PROYECTOS[[#This Row],[MUNICIPIO]],'4.CAP_ENDMNT'!B:B,'4.CAP_ENDMNT'!P:P,0,0,1) -> 0.8 | AH34: =+_xlfn.XLOOKUP(PROYECTOS[[#This Row],[MUNICIPIO]],'4.CAP_ENDMNT'!B:B,'4.CAP_ENDMNT'!Q:Q,0,0,1) -> Cumple | AI34: =+_xlfn.XLOOKUP(PROYECTOS[[#This Row],[MUNICIPIO]],'4.CAP_ENDMNT'!B:B,'4.CAP_ENDMNT'!V:V,0,0,1) -> 1.809691e+09 | AJ34: =+_xlfn.XLOOKUP(PROYECTOS[[#This Row],[MUNICIPIO]],'4.CAP_ENDMNT'!B:B,'4.CAP_ENDMNT'!Y:Y,0,0,1) -> -1.2348844e+10
A35: 37 | B35: Proyecto de pavimentación en la vía Sopetrán - Belmira | C35: =+_xlfn.XLOOKUP(PROYECTOS[[#This Row],[ID_NECESIDAD]],'1.RADICADOS'!G:G,'1.RADICADOS'!C:C,0,0,1)*1 -> 45440 | D35: Sopetrán | E35: =+_xlfn.XLOOKUP(PROYECTOS[[#This Row],[MUNICIPIO]],MUNICIPIOS!A:A,MUNICIPIOS!E:E,0,0,1) -> Occidente | F35: =+_xlfn.XLOOKUP(PROYECTOS[[#This Row],[MUNICIPIO]],MUNICIPIOS!A:A,MUNICIPIOS!F:F,0,0,1) -> -75.747378 | G35: =+_xlfn.XLOOKUP(PROYECTOS[[#This Row],[MUNICIPIO]],MUNICIPIOS!A:A,MUNICIPIOS!G:G,0,0,1) -> 6.500745 | H35: =+_xlfn.XLOOKUP(PROYECTOS[[#This Row],[MUNICIPIO]],MUNICIPIOS!A:A,MUNICIPIOS!B:B,0,0,1) -> 0 | I35: =+_xlfn.XLOOKUP(PROYECTOS[[#This Row],[MUNICIPIO]],MUNICIPIOS!A:A,MUNICIPIOS!C:C,0,0,1) -> 0 | J35: {=_xlfn.TEXTJOIN(" ", TRUE, IF(radicados[ID PROYECTOS]=A35, radicados[RADICADO], ""))} -> 2024010238039 | K35: 3 | L35: 16955817824 | M35: Pavimento Flexible | N35: Segundo Orden | O35: Vías secundarias mejoradas | T35: =+_xlfn.XLOOKUP(PROYECTOS[[#This Row],[MUNICIPIO]],'4.CAP_ENDMNT'!B:B,'4.CAP_ENDMNT'!C:C,0,0,1) -> 6 | U35: =+_xlfn.XLOOKUP(PROYECTOS[[#This Row],[MUNICIPIO]],'4.CAP_ENDMNT'!B:B,'4.CAP_ENDMNT'!D:D,0,0,1) -> 1.6347842e+10 | V35: =+_xlfn.XLOOKUP(PROYECTOS[[#This Row],[MUNICIPIO]],'4.CAP_ENDMNT'!B:B,'4.CAP_ENDMNT'!E:E,0,0,1) -> 7.9016432e+09 | W35: =+_xlfn.XLOOKUP(PROYECTOS[[#This Row],[MUNICIPIO]],'4.CAP_ENDMNT'!B:B,'4.CAP_ENDMNT'!F:F,0,0,1) -> 8.4461989e+09 | X35: =+_xlfn.XLOOKUP(PROYECTOS[[#This Row],[MUNICIPIO]],'4.CAP_ENDMNT'!B:B,'4.CAP_ENDMNT'!G:G,0,0,1) -> 1.620906e+09 | Y35: =+_xlfn.XLOOKUP(PROYECTOS[[#This Row],[MUNICIPIO]],'4.CAP_ENDMNT'!B:B,'4.CAP_ENDMNT'!H:H,0,0,1) -> 2416666620 | Z35: =+_xlfn.XLOOKUP(PROYECTOS[[#This Row],[MUNICIPIO]],'4.CAP_ENDMNT'!B:B,'4.CAP_ENDMNT'!I:I,0,0,1) -> 4.0375726e+09 | AA35: =+_xlfn.XLOOKUP(PROYECTOS[[#This Row],[MUNICIPIO]],'4.CAP_ENDMNT'!B:B,'4.CAP_ENDMNT'!J:J,0,0,1) -> 0.24697893 | AB35: =+_xlfn.XLOOKUP(PROYECTOS[[#This Row],[MUNICIPIO]],'4.CAP_ENDMNT'!B:B,'4.CAP_ENDMNT'!K:K,0,0,1) -> 1.2310269e+10 | AC35: =+_xlfn.XLOOKUP(PROYECTOS[[#This Row],[MUNICIPIO]],'4.CAP_ENDMNT'!B:B,'4.CAP_ENDMNT'!L:L,0,0,1) -> 9.8482156e+09 | AD35: =+_xlfn.XLOOKUP(PROYECTOS[[#This Row],[MUNICIPIO]],'4.CAP_ENDMNT'!B:B,'4.CAP_ENDMNT'!M:M,0,0,1) -> 7.3861617e+09 | AE35: =+_xlfn.XLOOKUP(PROYECTOS[[#This Row],[MUNICIPIO]],'4.CAP_ENDMNT'!B:B,'4.CAP_ENDMNT'!N:N,0,0,1) -> 0.40145556 | AF35: =+_xlfn.XLOOKUP(PROYECTOS[[#This Row],[MUNICIPIO]],'4.CAP_ENDMNT'!B:B,'4.CAP_ENDMNT'!O:O,0,0,1) -> 0.58521535 | AG35: =+_xlfn.XLOOKUP(PROYECTOS[[#This Row],[MUNICIPIO]],'4.CAP_ENDMNT'!B:B,'4.CAP_ENDMNT'!P:P,0,0,1) -> 0.8 | AH35: =+_xlfn.XLOOKUP(PROYECTOS[[#This Row],[MUNICIPIO]],'4.CAP_ENDMNT'!B:B,'4.CAP_ENDMNT'!Q:Q,0,0,1) -> Cumple | AI35: =+_xlfn.XLOOKUP(PROYECTOS[[#This Row],[MUNICIPIO]],'4.CAP_ENDMNT'!B:B,'4.CAP_ENDMNT'!V:V,0,0,1) -> 1.4772323e+09 | AJ35: =+_xlfn.XLOOKUP(PROYECTOS[[#This Row],[MUNICIPIO]],'4.CAP_ENDMNT'!B:B,'4.CAP_ENDMNT'!Y:Y,0,0,1) -> -1.1946219e+10
A36: 39 | B36: Pavimentación de 3 kilómetros de la vía Bellavista - Riogrande | C36: =+_xlfn.XLOOKUP(PROYECTOS[[#This Row],[ID_NECESIDAD]],'1.RADICADOS'!G:G,'1.RADICADOS'!C:C,0,0,1)*1 -> 45554 | D36: Donmatías | E36: =+_xlfn.XLOOKUP(PROYECTOS[[#This Row],[MUNICIPIO]],MUNICIPIOS!A:A,MUNICIPIOS!E:E,0,0,1) -> Norte | F36: =+_xlfn.XLOOKUP(PROYECTOS[[#This Row],[MUNICIPIO]],MUNICIPIOS!A:A,MUNICIPIOS!F:F,0,0,1) -> -75.39263 | G36: =+_xlfn.XLOOKUP(PROYECTOS[[#This Row],[MUNICIPIO]],MUNICIPIOS!A:A,MUNICIPIOS!G:G,0,0,1) -> 6,485603 | H36: =+_xlfn.XLOOKUP(PROYECTOS[[#This Row],[MUNICIPIO]],MUNICIPIOS!A:A,MUNICIPIOS!B:B,0,0,1) -> 0 | I36: =+_xlfn.XLOOKUP(PROYECTOS[[#This Row],[MUNICIPIO]],MUNICIPIOS!A:A,MUNICIPIOS!C:C,0,0,1) -> 0 | J36: {=_xlfn.TEXTJOIN(" ", TRUE, IF(radicados[ID PROYECTOS]=A36, radicados[RADICADO], ""))} -> 2024010273696 2024010429631 | K36: 3 | L36: 7948407205 | M36: Pavimento Flexible | N36: Tercer Orden | O36: Vías terciarias mejoradas | T36: =+_xlfn.XLOOKUP(PROYECTOS[[#This Row],[MUNICIPIO]],'4.CAP_ENDMNT'!B:B,'4.CAP_ENDMNT'!C:C,0,0,1) -> 6 | U36: =+_xlfn.XLOOKUP(PROYECTOS[[#This Row],[MUNICIPIO]],'4.CAP_ENDMNT'!B:B,'4.CAP_ENDMNT'!D:D,0,0,1) -> 2.4529039e+10 | V36: =+_xlfn.XLOOKUP(PROYECTOS[[#This Row],[MUNICIPIO]],'4.CAP_ENDMNT'!B:B,'4.CAP_ENDMNT'!E:E,0,0,1) -> 8.9730124e+09 | W36: =+_xlfn.XLOOKUP(PROYECTOS[[#This Row],[MUNICIPIO]],'4.CAP_ENDMNT'!B:B,'4.CAP_ENDMNT'!F:F,0,0,1) -> 1.5556027e+10 | X36: =+_xlfn.XLOOKUP(PROYECTOS[[#This Row],[MUNICIPIO]],'4.CAP_ENDMNT'!B:B,'4.CAP_ENDMNT'!G:G,0,0,1) -> 7973050390 | Y36: =+_xlfn.XLOOKUP(PROYECTOS[[#This Row],[MUNICIPIO]],'4.CAP_ENDMNT'!B:B,'4.CAP_ENDMNT'!H:H,0,0,1) -> 1625381984 | Z36: =+_xlfn.XLOOKUP(PROYECTOS[[#This Row],[MUNICIPIO]],'4.CAP_ENDMNT'!B:B,'4.CAP_ENDMNT'!I:I,0,0,1) -> 9598432374 | AA36: =+_xlfn.XLOOKUP(PROYECTOS[[#This Row],[MUNICIPIO]],'4.CAP_ENDMNT'!B:B,'4.CAP_ENDMNT'!J:J,0,0,1) -> 0.39130894 | AB36: =+_xlfn.XLOOKUP(PROYECTOS[[#This Row],[MUNICIPIO]],'4.CAP_ENDMNT'!B:B,'4.CAP_ENDMNT'!K:K,0,0,1) -> 1.4930607e+10 | AC36: =+_xlfn.XLOOKUP(PROYECTOS[[#This Row],[MUNICIPIO]],'4.CAP_ENDMNT'!B:B,'4.CAP_ENDMNT'!L:L,0,0,1) -> 1.1944486e+10 | AD36: =+_xlfn.XLOOKUP(PROYECTOS[[#This Row],[MUNICIPIO]],'4.CAP_ENDMNT'!B:B,'4.CAP_ENDMNT'!M:M,0,0,1) -> 8.9583642e+09 | AE36: =+_xlfn.XLOOKUP(PROYECTOS[[#This Row],[MUNICIPIO]],'4.CAP_ENDMNT'!B:B,'4.CAP_ENDMNT'!N:N,0,0,1) -> 0.83066172 | AF36: =+_xlfn.XLOOKUP(PROYECTOS[[#This Row],[MUNICIPIO]],'4.CAP_ENDMNT'!B:B,'4.CAP_ENDMNT'!O:O,0,0,1) -> 0.53024344 | AG36: =+_xlfn.XLOOKUP(PROYECTOS[[#This Row],[MUNICIPIO]],'4.CAP_ENDMNT'!B:B,'4.CAP_ENDMNT'!P:P,0,0,1) -> 0.8 | AH36: =+_xlfn.XLOOKUP(PROYECTOS[[#This Row],[MUNICIPIO]],'4.CAP_ENDMNT'!B:B,'4.CAP_ENDMNT'!Q:Q,0,0,1) -> Cumple | AI36: =+_xlfn.XLOOKUP(PROYECTOS[[#This Row],[MUNICIPIO]],'4.CAP_ENDMNT'!B:B,'4.CAP_ENDMNT'!V:V,0,0,1) -> 1.7916728e+09 | AJ36: =+_xlfn.XLOOKUP(PROYECTOS[[#This Row],[MUNICIPIO]],'4.CAP_ENDMNT'!B:B,'4.CAP_ENDMNT'!Y:Y,0,0,1) -> -8.1641356e+09
A37: 40 | B37: Mejoramiento con pavimento rígido de las vías del circuito productivo rural de la subregión suroeste en el municipio de Pueblorrico | C37: =+_xlfn.XLOOKUP(PROYECTOS[[#This Row],[ID_NECESIDAD]],'1.RADICADOS'!G:G,'1.RADICADOS'!C:C,0,0,1)*1 -> 45464 | D37: Pueblorrico | E37: =+_xlfn.XLOOKUP(PROYECTOS[[#This Row],[MUNICIPIO]],MUNICIPIOS!A:A,MUNICIPIOS!E:E,0,0,1) -> Suroeste | F37: =+_xlfn.XLOOKUP(PROYECTOS[[#This Row],[MUNICIPIO]],MUNICIPIOS!A:A,MUNICIPIOS!F:F,0,0,1) -> -75.839903 | G37: =+_xlfn.XLOOKUP(PROYECTOS[[#This Row],[MUNICIPIO]],MUNICIPIOS!A:A,MUNICIPIOS!G:G,0,0,1) -> 5,79158 | H37: =+_xlfn.XLOOKUP(PROYECTOS[[#This Row],[MUNICIPIO]],MUNICIPIOS!A:A,MUNICIPIOS!B:B,0,0,1) -> 0 | I37: =+_xlfn.XLOOKUP(PROYECTOS[[#This Row],[MUNICIPIO]],MUNICIPIOS!A:A,MUNICIPIOS!C:C,0,0,1) -> 0 | J37: {=_xlfn.TEXTJOIN(" ", TRUE, IF(radicados[ID PROYECTOS]=A37, radicados[RADICADO], ""))} -> 2024010277200 | K37: 3 | L37: 4106423860 | M37: Pavimento Rígido | N37: Tercer Orden | O37: Vías terciarias mejoradas | P37: El proyecto será desarrollado en la zona Rural del municipio de Pueblorrico; en la vía de tercer orden 25BAN03: Pueblorrico - Sinaí - La Bodega- Peñalisa que comunica el casco urbano con las Veredas Corinto Mulatos Sinaí Sevilla y Morrón; entre el km 2+100 desde la salida de la cabecera municipal sobre la calle 30 (Tiendas D1 Pueblorrico y Capilla San José) y el km 3+500 | T37: =+_xlfn.XLOOKUP(PROYECTOS[[#This Row],[MUNICIPIO]],'4.CAP_ENDMNT'!B:B,'4.CAP_ENDMNT'!C:C,0,0,1) -> 6 | U37: =+_xlfn.XLOOKUP(PROYECTOS[[#This Row],[MUNICIPIO]],'4.CAP_ENDMNT'!B:B,'4.CAP_ENDMNT'!D:D,0,0,1) -> 7.4089579e+09 | V37: =+_xlfn.XLOOKUP(PROYECTOS[[#This Row],[MUNICIPIO]],'4.CAP_ENDMNT'!B:B,'4.CAP_ENDMNT'!E:E,0,0,1) -> 2.7261792e+09 | W37: =+_xlfn.XLOOKUP(PROYECTOS[[#This Row],[MUNICIPIO]],'4.CAP_ENDMNT'!B:B,'4.CAP_ENDMNT'!F:F,0,0,1) -> 4.6827787e+09 | X37: =+_xlfn.XLOOKUP(PROYECTOS[[#This Row],[MUNICIPIO]],'4.CAP_ENDMNT'!B:B,'4.CAP_ENDMNT'!G:G,0,0,1) -> 1117539497 | Y37: =+_xlfn.XLOOKUP(PROYECTOS[[#This Row],[MUNICIPIO]],'4.CAP_ENDMNT'!B:B,'4.CAP_ENDMNT'!H:H,0,0,1) -> 0 | Z37: =+_xlfn.XLOOKUP(PROYECTOS[[#This Row],[MUNICIPIO]],'4.CAP_ENDMNT'!B:B,'4.CAP_ENDMNT'!I:I,0,0,1) -> 1117539497 | AA37: =+_xlfn.XLOOKUP(PROYECTOS[[#This Row],[MUNICIPIO]],'4.CAP_ENDMNT'!B:B,'4.CAP_ENDMNT'!J:J,0,0,1) -> 0.15083626 | AB37: =+_xlfn.XLOOKUP(PROYECTOS[[#This Row],[MUNICIPIO]],'4.CAP_ENDMNT'!B:B,'4.CAP_ENDMNT'!K:K,0,0,1) -> 6.2914184e+09 | AC37: =+_xlfn.XLOOKUP(PROYECTOS[[#This Row],[MUNICIPIO]],'4.CAP_ENDMNT'!B:B,'4.CAP_ENDMNT'!L:L,0,0,1) -> 5.0331348e+09 | AD37: =+_xlfn.XLOOKUP(PROYECTOS[[#This Row],[MUNICIPIO]],'4.CAP_ENDMNT'!B:B,'4.CAP_ENDMNT'!M:M,0,0,1) -> 3.7748511e+09 | AE37: =+_xlfn.XLOOKUP(PROYECTOS[[#This Row],[MUNICIPIO]],'4.CAP_ENDMNT'!B:B,'4.CAP_ENDMNT'!N:N,0,0,1) -> 1 | AF37: =+_xlfn.XLOOKUP(PROYECTOS[[#This Row],[MUNICIPIO]],'4.CAP_ENDMNT'!B:B,'4.CAP_ENDMNT'!O:O,0,0,1) -> 0.78495374 | AG37: =+_xlfn.XLOOKUP(PROYECTOS[[#This Row],[MUNICIPIO]],'4.CAP_ENDMNT'!B:B,'4.CAP_ENDMNT'!P:P,0,0,1) -> 0.8 | AH37: =+_xlfn.XLOOKUP(PROYECTOS[[#This Row],[MUNICIPIO]],'4.CAP_ENDMNT'!B:B,'4.CAP_ENDMNT'!Q:Q,0,0,1) -> Riesgo | AI37: =+_xlfn.XLOOKUP(PROYECTOS[[#This Row],[MUNICIPIO]],'4.CAP_ENDMNT'!B:B,'4.CAP_ENDMNT'!V:V,0,0,1) -> 7.5497021e+08 | AJ37: =+_xlfn.XLOOKUP(PROYECTOS[[#This Row],[MUNICIPIO]],'4.CAP_ENDMNT'!B:B,'4.CAP_ENDMNT'!Y:Y,0,0,1) -> -4.5201446e+09
A38: 42 | B38: Pavimentación de 870 m de la vía Concepción - Alejandría 'Los Pomos' SOLO PRESENTA INFORME DE INSPECCIÓN OCULAR | C38: =+_xlfn.XLOOKUP(PROYECTOS[[#This Row],[ID_NECESIDAD]],'1.RADICADOS'!G:G,'1.RADICADOS'!C:C,0,0,1)*1 -> 45429 | D38: Concepción | E38: =+_xlfn.XLOOKUP(PROYECTOS[[#This Row],[MUNICIPIO]],MUNICIPIOS!A:A,MUNICIPIOS!E:E,0,0,1) -> Oriente | F38: =+_xlfn.XLOOKUP(PROYECTOS[[#This Row],[MUNICIPIO]],MUNICIPIOS!A:A,MUNICIPIOS!F:F,0,0,1) -> -75.257587 | G38: =+_xlfn.XLOOKUP(PROYECTOS[[#This Row],[MUNICIPIO]],MUNICIPIOS!A:A,MUNICIPIOS!G:G,0,0,1) -> 6,394348 | H38: =+_xlfn.XLOOKUP(PROYECTOS[[#This Row],[MUNICIPIO]],MUNICIPIOS!A:A,MUNICIPIOS!B:B,0,0,1) -> 0 | I38: =+_xlfn.XLOOKUP(PROYECTOS[[#This Row],[MUNICIPIO]],MUNICIPIOS!A:A,MUNICIPIOS!C:C,0,0,1) -> 1 | J38: {=_xlfn.TEXTJOIN(" ", TRUE, IF(radicados[ID PROYECTOS]=A38, radicados[RADICADO], ""))} -> 2024010279803 | K38: 1 | M38: Pavimento Flexible | N38: Segundo Orden | O38: Vías secundarias mejoradas | P38: Solo presenta informe con inspeccion ocular | T38: =+_xlfn.XLOOKUP(PROYECTOS[[#This Row],[MUNICIPIO]],'4.CAP_ENDMNT'!B:B,'4.CAP_ENDMNT'!C:C,0,0,1) -> 6 | U38: =+_xlfn.XLOOKUP(PROYECTOS[[#This Row],[MUNICIPIO]],'4.CAP_ENDMNT'!B:B,'4.CAP_ENDMNT'!D:D,0,0,1) -> 8.7257241e+09 | V38: =+_xlfn.XLOOKUP(PROYECTOS[[#This Row],[MUNICIPIO]],'4.CAP_ENDMNT'!B:B,'4.CAP_ENDMNT'!E:E,0,0,1) -> 1.9352902e+09 | W38: =+_xlfn.XLOOKUP(PROYECTOS[[#This Row],[MUNICIPIO]],'4.CAP_ENDMNT'!B:B,'4.CAP_ENDMNT'!F:F,0,0,1) -> 6.7904338e+09 | X38: =+_xlfn.XLOOKUP(PROYECTOS[[#This Row],[MUNICIPIO]],'4.CAP_ENDMNT'!B:B,'4.CAP_ENDMNT'!G:G,0,0,1) -> 661232494 | Y38: =+_xlfn.XLOOKUP(PROYECTOS[[#This Row],[MUNICIPIO]],'4.CAP_ENDMNT'!B:B,'4.CAP_ENDMNT'!H:H,0,0,1) -> 0 | Z38: =+_xlfn.XLOOKUP(PROYECTOS[[#This Row],[MUNICIPIO]],'4.CAP_ENDMNT'!B:B,'4.CAP_ENDMNT'!I:I,0,0,1) -> 661232494 | AA38: =+_xlfn.XLOOKUP(PROYECTOS[[#This Row],[MUNICIPIO]],'4.CAP_ENDMNT'!B:B,'4.CAP_ENDMNT'!J:J,0,0,1) -> 0.07577967 | AB38: =+_xlfn.XLOOKUP(PROYECTOS[[#This Row],[MUNICIPIO]],'4.CAP_ENDMNT'!B:B,'4.CAP_ENDMNT'!K:K,0,0,1) -> 8.0644916e+09 | AC38: =+_xlfn.XLOOKUP(PROYECTOS[[#This Row],[MUNICIPIO]],'4.CAP_ENDMNT'!B:B,'4.CAP_ENDMNT'!L:L,0,0,1) -> 6.4515933e+09 | AD38: =+_xlfn.XLOOKUP(PROYECTOS[[#This Row],[MUNICIPIO]],'4.CAP_ENDMNT'!B:B,'4.CAP_ENDMNT'!M:M,0,0,1) -> 4.8386949e+09 | AE38: =+_xlfn.XLOOKUP(PROYECTOS[[#This Row],[MUNICIPIO]],'4.CAP_ENDMNT'!B:B,'4.CAP_ENDMNT'!N:N,0,0,1) -> 1 | AF38: =+_xlfn.XLOOKUP(PROYECTOS[[#This Row],[MUNICIPIO]],'4.CAP_ENDMNT'!B:B,'4.CAP_ENDMNT'!O:O,0,0,1) -> 0.53402239 | AG38: =+_xlfn.XLOOKUP(PROYECTOS[[#This Row],[MUNICIPIO]],'4.CAP_ENDMNT'!B:B,'4.CAP_ENDMNT'!P:P,0,0,1) -> 0.8 | AH38: =+_xlfn.XLOOKUP(PROYECTOS[[#This Row],[MUNICIPIO]],'4.CAP_ENDMNT'!B:B,'4.CAP_ENDMNT'!Q:Q,0,0,1) -> Cumple | AI38: =+_xlfn.XLOOKUP(PROYECTOS[[#This Row],[MUNICIPIO]],'4.CAP_ENDMNT'!B:B,'4.CAP_ENDMNT'!V:V,0,0,1) -> 9.6773899e+08 | AJ38: =+_xlfn.XLOOKUP(PROYECTOS[[#This Row],[MUNICIPIO]],'4.CAP_ENDMNT'!B:B,'4.CAP_ENDMNT'!Y:Y,0,0,1) -> 5.8064339e+09
A39: 43 | B39: Construcción e implementación de la ciudadela de innovación agroempresarial regional en el municipio de Sonsón | C39: =+_xlfn.XLOOKUP(PROYECTOS[[#This Row],[ID_NECESIDAD]],'1.RADICADOS'!G:G,'1.RADICADOS'!C:C,0,0,1)*1 -> 45442 | D39: Sonsón | E39: =+_xlfn.XLOOKUP(PROYECTOS[[#This Row],[MUNICIPIO]],MUNICIPIOS!A:A,MUNICIPIOS!E:E,0,0,1) -> Oriente | F39: =+_xlfn.XLOOKUP(PROYECTOS[[#This Row],[MUNICIPIO]],MUNICIPIOS!A:A,MUNICIPIOS!F:F,0,0,1) -> -75.309596 | G39: =+_xlfn.XLOOKUP(PROYECTOS[[#This Row],[MUNICIPIO]],MUNICIPIOS!A:A,MUNICIPIOS!G:G,0,0,1) -> 5,714851 | H39: =+_xlfn.XLOOKUP(PROYECTOS[[#This Row],[MUNICIPIO]],MUNICIPIOS!A:A,MUNICIPIOS!B:B,0,0,1) -> 0 | I39: =+_xlfn.XLOOKUP(PROYECTOS[[#This Row],[MUNICIPIO]],MUNICIPIOS!A:A,MUNICIPIOS!C:C,0,0,1) -> 1 | J39: {=_xlfn.TEXTJOIN(" ", TRUE, IF(radicados[ID PROYECTOS]=A39, radicados[RADICADO], ""))} -> 2024010220650 | K39: 3 | L39: 11094609252 | M39: Equipamento | N39: N/A | O39: Equipamientos construidos | T39: =+_xlfn.XLOOKUP(PROYECTOS[[#This Row],[MUNICIPIO]],'4.CAP_ENDMNT'!B:B,'4.CAP_ENDMNT'!C:C,0,0,1) -> 5 | U39: =+_xlfn.XLOOKUP(PROYECTOS[[#This Row],[MUNICIPIO]],'4.CAP_ENDMNT'!B:B,'4.CAP_ENDMNT'!D:D,0,0,1) -> 3.5695768e+10 | V39: =+_xlfn.XLOOKUP(PROYECTOS[[#This Row],[MUNICIPIO]],'4.CAP_ENDMNT'!B:B,'4.CAP_ENDMNT'!E:E,0,0,1) -> 1.3532488e+10 | W39: =+_xlfn.XLOOKUP(PROYECTOS[[#This Row],[MUNICIPIO]],'4.CAP_ENDMNT'!B:B,'4.CAP_ENDMNT'!F:F,0,0,1) -> 2.2163279e+10 | X39: =+_xlfn.XLOOKUP(PROYECTOS[[#This Row],[MUNICIPIO]],'4.CAP_ENDMNT'!B:B,'4.CAP_ENDMNT'!G:G,0,0,1) -> 1067761948 | Y39: =+_xlfn.XLOOKUP(PROYECTOS[[#This Row],[MUNICIPIO]],'4.CAP_ENDMNT'!B:B,'4.CAP_ENDMNT'!H:H,0,0,1) -> 4932032890 | Z39: =+_xlfn.XLOOKUP(PROYECTOS[[#This Row],[MUNICIPIO]],'4.CAP_ENDMNT'!B:B,'4.CAP_ENDMNT'!I:I,0,0,1) -> 5999794838 | AA39: =+_xlfn.XLOOKUP(PROYECTOS[[#This Row],[MUNICIPIO]],'4.CAP_ENDMNT'!B:B,'4.CAP_ENDMNT'!J:J,0,0,1) -> 0.16808141 | AB39: =+_xlfn.XLOOKUP(PROYECTOS[[#This Row],[MUNICIPIO]],'4.CAP_ENDMNT'!B:B,'4.CAP_ENDMNT'!K:K,0,0,1) -> 2.9695973e+10 | AC39: =+_xlfn.XLOOKUP(PROYECTOS[[#This Row],[MUNICIPIO]],'4.CAP_ENDMNT'!B:B,'4.CAP_ENDMNT'!L:L,0,0,1) -> 2.3756778e+10 | AD39: =+_xlfn.XLOOKUP(PROYECTOS[[#This Row],[MUNICIPIO]],'4.CAP_ENDMNT'!B:B,'4.CAP_ENDMNT'!M:M,0,0,1) -> 1.7817584e+10 | AE39: =+_xlfn.XLOOKUP(PROYECTOS[[#This Row],[MUNICIPIO]],'4.CAP_ENDMNT'!B:B,'4.CAP_ENDMNT'!N:N,0,0,1) -> 0.17796641 | AF39: =+_xlfn.XLOOKUP(PROYECTOS[[#This Row],[MUNICIPIO]],'4.CAP_ENDMNT'!B:B,'4.CAP_ENDMNT'!O:O,0,0,1) -> 0.40167298 | AG39: =+_xlfn.XLOOKUP(PROYECTOS[[#This Row],[MUNICIPIO]],'4.CAP_ENDMNT'!B:B,'4.CAP_ENDMNT'!P:P,0,0,1) -> 0.8 | AH39: =+_xlfn.XLOOKUP(PROYECTOS[[#This Row],[MUNICIPIO]],'4.CAP_ENDMNT'!B:B,'4.CAP_ENDMNT'!Q:Q,0,0,1) -> Cumple | AI39: =+_xlfn.XLOOKUP(PROYECTOS[[#This Row],[MUNICIPIO]],'4.CAP_ENDMNT'!B:B,'4.CAP_ENDMNT'!V:V,0,0,1) -> 3.5635167e+09 | AJ39: =+_xlfn.XLOOKUP(PROYECTOS[[#This Row],[MUNICIPIO]],'4.CAP_ENDMNT'!B:B,'4.CAP_ENDMNT'!Y:Y,0,0,1) -> -4.6557238e+10
A40: 44 | B40: ADICION - Mejoramiento de vías terciarias de las veredas Mulatico Patio Bonito y Morrón del municipio de Tarso Antioquia mediante la construcción de pavimentación de Placa huella | C40: =+_xlfn.XLOOKUP(PROYECTOS[[#This Row],[ID_NECESIDAD]],'1.RADICADOS'!G:G,'1.RADICADOS'!C:C,0,0,1)*1 -> 45464 | D40: Tarso | E40: =+_xlfn.XLOOKUP(PROYECTOS[[#This Row],[MUNICIPIO]],MUNICIPIOS!A:A,MUNICIPIOS!E:E,0,0,1) -> Suroeste | F40: =+_xlfn.XLOOKUP(PROYECTOS[[#This Row],[MUNICIPIO]],MUNICIPIOS!A:A,MUNICIPIOS!F:F,0,0,1) -> -75.822956 | G40: =+_xlfn.XLOOKUP(PROYECTOS[[#This Row],[MUNICIPIO]],MUNICIPIOS!A:A,MUNICIPIOS!G:G,0,0,1) -> 5.864542 | H40: =+_xlfn.XLOOKUP(PROYECTOS[[#This Row],[MUNICIPIO]],MUNICIPIOS!A:A,MUNICIPIOS!B:B,0,0,1) -> 0 | I40: =+_xlfn.XLOOKUP(PROYECTOS[[#This Row],[MUNICIPIO]],MUNICIPIOS!A:A,MUNICIPIOS!C:C,0,0,1) -> 0 | J40: {=_xlfn.TEXTJOIN(" ", TRUE, IF(radicados[ID PROYECTOS]=A40, radicados[RADICADO], ""))} -> 2024010242499 | K40: 3 | L40: 288779865 | M40: Placa huella | N40: Tercer Orden | O40: Vías terciarias mejoradas | P40: Adicion a proyecto en ejecucion | T40: =+_xlfn.XLOOKUP(PROYECTOS[[#This Row],[MUNICIPIO]],'4.CAP_ENDMNT'!B:B,'4.CAP_ENDMNT'!C:C,0,0,1) -> 6 | U40: =+_xlfn.XLOOKUP(PROYECTOS[[#This Row],[MUNICIPIO]],'4.CAP_ENDMNT'!B:B,'4.CAP_ENDMNT'!D:D,0,0,1) -> 9.2972046e+09 | V40: =+_xlfn.XLOOKUP(PROYECTOS[[#This Row],[MUNICIPIO]],'4.CAP_ENDMNT'!B:B,'4.CAP_ENDMNT'!E:E,0,0,1) -> 4.6509009e+09 | W40: =+_xlfn.XLOOKUP(PROYECTOS[[#This Row],[MUNICIPIO]],'4.CAP_ENDMNT'!B:B,'4.CAP_ENDMNT'!F:F,0,0,1) -> 4.6463037e+09 | X40: =+_xlfn.XLOOKUP(PROYECTOS[[#This Row],[MUNICIPIO]],'4.CAP_ENDMNT'!B:B,'4.CAP_ENDMNT'!G:G,0,0,1) -> 1308996768 | Y40: =+_xlfn.XLOOKUP(PROYECTOS[[#This Row],[MUNICIPIO]],'4.CAP_ENDMNT'!B:B,'4.CAP_ENDMNT'!H:H,0,0,1) -> 0 | Z40: =+_xlfn.XLOOKUP(PROYECTOS[[#This Row],[MUNICIPIO]],'4.CAP_ENDMNT'!B:B,'4.CAP_ENDMNT'!I:I,0,0,1) -> 1308996768 | AA40: =+_xlfn.XLOOKUP(PROYECTOS[[#This Row],[MUNICIPIO]],'4.CAP_ENDMNT'!B:B,'4.CAP_ENDMNT'!J:J,0,0,1) -> 0.14079466 | AB40: =+_xlfn.XLOOKUP(PROYECTOS[[#This Row],[MUNICIPIO]],'4.CAP_ENDMNT'!B:B,'4.CAP_ENDMNT'!K:K,0,0,1) -> 7.9882078e+09 | AC40: =+_xlfn.XLOOKUP(PROYECTOS[[#This Row],[MUNICIPIO]],'4.CAP_ENDMNT'!B:B,'4.CAP_ENDMNT'!L:L,0,0,1) -> 6.3905663e+09 | AD40: =+_xlfn.XLOOKUP(PROYECTOS[[#This Row],[MUNICIPIO]],'4.CAP_ENDMNT'!B:B,'4.CAP_ENDMNT'!M:M,0,0,1) -> 4.7929247e+09 | AE40: =+_xlfn.XLOOKUP(PROYECTOS[[#This Row],[MUNICIPIO]],'4.CAP_ENDMNT'!B:B,'4.CAP_ENDMNT'!N:N,0,0,1) -> 1 | AF40: =+_xlfn.XLOOKUP(PROYECTOS[[#This Row],[MUNICIPIO]],'4.CAP_ENDMNT'!B:B,'4.CAP_ENDMNT'!O:O,0,0,1) -> 0.67267671 | AG40: =+_xlfn.XLOOKUP(PROYECTOS[[#This Row],[MUNICIPIO]],'4.CAP_ENDMNT'!B:B,'4.CAP_ENDMNT'!P:P,0,0,1) -> 0.8 | AH40: =+_xlfn.XLOOKUP(PROYECTOS[[#This Row],[MUNICIPIO]],'4.CAP_ENDMNT'!B:B,'4.CAP_ENDMNT'!Q:Q,0,0,1) -> Cumple | AI40: =+_xlfn.XLOOKUP(PROYECTOS[[#This Row],[MUNICIPIO]],'4.CAP_ENDMNT'!B:B,'4.CAP_ENDMNT'!V:V,0,0,1) -> 9.5858494e+08 | AJ40: =+_xlfn.XLOOKUP(PROYECTOS[[#This Row],[MUNICIPIO]],'4.CAP_ENDMNT'!B:B,'4.CAP_ENDMNT'!Y:Y,0,0,1) -> -1.2177885e+09
A41: 45 | B41: Construcción de la nueva Plaza e mercadi del Municipio de Rionegro y la renovación urbana de su entorno | C41: =+_xlfn.XLOOKUP(PROYECTOS[[#This Row],[ID_NECESIDAD]],'1.RADICADOS'!G:G,'1.RADICADOS'!C:C,0,0,1)*1 -> 45441 | D41: Rionegro | E41: =+_xlfn.XLOOKUP(PROYECTOS[[#This Row],[MUNICIPIO]],MUNICIPIOS!A:A,MUNICIPIOS!E:E,0,0,1) -> Oriente | F41: =+_xlfn.XLOOKUP(PROYECTOS[[#This Row],[MUNICIPIO]],MUNICIPIOS!A:A,MUNICIPIOS!F:F,0,0,1) -> -75.377316 | G41: =+_xlfn.XLOOKUP(PROYECTOS[[#This Row],[MUNICIPIO]],MUNICIPIOS!A:A,MUNICIPIOS!G:G,0,0,1) -> 6,147148 | H41: =+_xlfn.XLOOKUP(PROYECTOS[[#This Row],[MUNICIPIO]],MUNICIPIOS!A:A,MUNICIPIOS!B:B,0,0,1) -> 0 | I41: =+_xlfn.XLOOKUP(PROYECTOS[[#This Row],[MUNICIPIO]],MUNICIPIOS!A:A,MUNICIPIOS!C:C,0,0,1) -> 0 | J41: {=_xlfn.TEXTJOIN(" ", TRUE, IF(radicados[ID PROYECTOS]=A41, radicados[RADICADO], ""))} -> 2024010278154 | K41: 3 | M41: Plaza de Mercado | N41: N/A | O41: Equipamientos construidos | P41: Radicado no tiene mayor informacion | T41: =+_xlfn.XLOOKUP(PROYECTOS[[#This Row],[MUNICIPIO]],'4.CAP_ENDMNT'!B:B,'4.CAP_ENDMNT'!C:C,0,0,1) -> 1 | U41: =+_xlfn.XLOOKUP(PROYECTOS[[#This Row],[MUNICIPIO]],'4.CAP_ENDMNT'!B:B,'4.CAP_ENDMNT'!D:D,0,0,1) -> 5.0123644e+11 | V41: =+_xlfn.XLOOKUP(PROYECTOS[[#This Row],[MUNICIPIO]],'4.CAP_ENDMNT'!B:B,'4.CAP_ENDMNT'!E:E,0,0,1) -> 1.1250202e+11 | W41: =+_xlfn.XLOOKUP(PROYECTOS[[#This Row],[MUNICIPIO]],'4.CAP_ENDMNT'!B:B,'4.CAP_ENDMNT'!F:F,0,0,1) -> 3.8873442e+11 | X41: =+_xlfn.XLOOKUP(PROYECTOS[[#This Row],[MUNICIPIO]],'4.CAP_ENDMNT'!B:B,'4.CAP_ENDMNT'!G:G,0,0,1) -> 85394840514 | Y41: =+_xlfn.XLOOKUP(PROYECTOS[[#This Row],[MUNICIPIO]],'4.CAP_ENDMNT'!B:B,'4.CAP_ENDMNT'!H:H,0,0,1) -> 1.1410989e+11 | Z41: =+_xlfn.XLOOKUP(PROYECTOS[[#This Row],[MUNICIPIO]],'4.CAP_ENDMNT'!B:B,'4.CAP_ENDMNT'!I:I,0,0,1) -> 1.9950473e+11 | AA41: =+_xlfn.XLOOKUP(PROYECTOS[[#This Row],[MUNICIPIO]],'4.CAP_ENDMNT'!B:B,'4.CAP_ENDMNT'!J:J,0,0,1) -> 0.39802519 | AB41: =+_xlfn.XLOOKUP(PROYECTOS[[#This Row],[MUNICIPIO]],'4.CAP_ENDMNT'!B:B,'4.CAP_ENDMNT'!K:K,0,0,1) -> 3.0173171e+11 | AC41: =+_xlfn.XLOOKUP(PROYECTOS[[#This Row],[MUNICIPIO]],'4.CAP_ENDMNT'!B:B,'4.CAP_ENDMNT'!L:L,0,0,1) -> 2.4138537e+11 | AD41: =+_xlfn.XLOOKUP(PROYECTOS[[#This Row],[MUNICIPIO]],'4.CAP_ENDMNT'!B:B,'4.CAP_ENDMNT'!M:M,0,0,1) -> 1.8103903e+11 | AE41: =+_xlfn.XLOOKUP(PROYECTOS[[#This Row],[MUNICIPIO]],'4.CAP_ENDMNT'!B:B,'4.CAP_ENDMNT'!N:N,0,0,1) -> 0.42803417 | AF41: =+_xlfn.XLOOKUP(PROYECTOS[[#This Row],[MUNICIPIO]],'4.CAP_ENDMNT'!B:B,'4.CAP_ENDMNT'!O:O,0,0,1) -> 0.23207277 | AG41: =+_xlfn.XLOOKUP(PROYECTOS[[#This Row],[MUNICIPIO]],'4.CAP_ENDMNT'!B:B,'4.CAP_ENDMNT'!P:P,0,0,1) -> 0.65 | AH41: =+_xlfn.XLOOKUP(PROYECTOS[[#This Row],[MUNICIPIO]],'4.CAP_ENDMNT'!B:B,'4.CAP_ENDMNT'!Q:Q,0,0,1) -> Cumple | AI41: =+_xlfn.XLOOKUP(PROYECTOS[[#This Row],[MUNICIPIO]],'4.CAP_ENDMNT'!B:B,'4.CAP_ENDMNT'!V:V,0,0,1) -> 3.6207806e+10 | AJ41: =+_xlfn.XLOOKUP(PROYECTOS[[#This Row],[MUNICIPIO]],'4.CAP_ENDMNT'!B:B,'4.CAP_ENDMNT'!Y:Y,0,0,1) -> 1.9947085e+11
A42: 46 | B42: Construcción del parque Villa Esperanza del municipio de San Pedro de Urabá Antioquia | C42: =+_xlfn.XLOOKUP(PROYECTOS[[#This Row],[ID_NECESIDAD]],'1.RADICADOS'!G:G,'1.RADICADOS'!C:C,0,0,1)*1 -> 45441 | D42: San Pedro de Urabá | E42: =+_xlfn.XLOOKUP(PROYECTOS[[#This Row],[MUNICIPIO]],MUNICIPIOS!A:A,MUNICIPIOS!E:E,0,0,1) -> Urabá | F42: =+_xlfn.XLOOKUP(PROYECTOS[[#This Row],[MUNICIPIO]],MUNICIPIOS!A:A,MUNICIPIOS!F:F,0,0,1) -> -76.380567 | G42: =+_xlfn.XLOOKUP(PROYECTOS[[#This Row],[MUNICIPIO]],MUNICIPIOS!A:A,MUNICIPIOS!G:G,0,0,1) -> 8,276884 | H42: =+_xlfn.XLOOKUP(PROYECTOS[[#This Row],[MUNICIPIO]],MUNICIPIOS!A:A,MUNICIPIOS!B:B,0,0,1) -> 1 | I42: =+_xlfn.XLOOKUP(PROYECTOS[[#This Row],[MUNICIPIO]],MUNICIPIOS!A:A,MUNICIPIOS!C:C,0,0,1) -> 1 | J42: {=_xlfn.TEXTJOIN(" ", TRUE, IF(radicados[ID PROYECTOS]=A42, radicados[RADICADO], ""))} -> 2024010240568 | K42: 3 | L42: 883515930 | M42: Parque | N42: N/A | O42: Espacio público adecuado | T42: =+_xlfn.XLOOKUP(PROYECTOS[[#This Row],[MUNICIPIO]],'4.CAP_ENDMNT'!B:B,'4.CAP_ENDMNT'!C:C,0,0,1) -> 6 | U42: =+_xlfn.XLOOKUP(PROYECTOS[[#This Row],[MUNICIPIO]],'4.CAP_ENDMNT'!B:B,'4.CAP_ENDMNT'!D:D,0,0,1) -> 1.9508373e+10 | V42: =+_xlfn.XLOOKUP(PROYECTOS[[#This Row],[MUNICIPIO]],'4.CAP_ENDMNT'!B:B,'4.CAP_ENDMNT'!E:E,0,0,1) -> 5.3898343e+09 | W42: =+_xlfn.XLOOKUP(PROYECTOS[[#This Row],[MUNICIPIO]],'4.CAP_ENDMNT'!B:B,'4.CAP_ENDMNT'!F:F,0,0,1) -> 1.4118538e+10 | X42: =+_xlfn.XLOOKUP(PROYECTOS[[#This Row],[MUNICIPIO]],'4.CAP_ENDMNT'!B:B,'4.CAP_ENDMNT'!G:G,0,0,1) -> 2594281047 | Y42: =+_xlfn.XLOOKUP(PROYECTOS[[#This Row],[MUNICIPIO]],'4.CAP_ENDMNT'!B:B,'4.CAP_ENDMNT'!H:H,0,0,1) -> 1833333333 | Z42: =+_xlfn.XLOOKUP(PROYECTOS[[#This Row],[MUNICIPIO]],'4.CAP_ENDMNT'!B:B,'4.CAP_ENDMNT'!I:I,0,0,1) -> 4427614380 | AA42: =+_xlfn.XLOOKUP(PROYECTOS[[#This Row],[MUNICIPIO]],'4.CAP_ENDMNT'!B:B,'4.CAP_ENDMNT'!J:J,0,0,1) -> 0.2269597 | AB42: =+_xlfn.XLOOKUP(PROYECTOS[[#This Row],[MUNICIPIO]],'4.CAP_ENDMNT'!B:B,'4.CAP_ENDMNT'!K:K,0,0,1) -> 1.5080758e+10 | AC42: =+_xlfn.XLOOKUP(PROYECTOS[[#This Row],[MUNICIPIO]],'4.CAP_ENDMNT'!B:B,'4.CAP_ENDMNT'!L:L,0,0,1) -> 1.2064607e+10 | AD42: =+_xlfn.XLOOKUP(PROYECTOS[[#This Row],[MUNICIPIO]],'4.CAP_ENDMNT'!B:B,'4.CAP_ENDMNT'!M:M,0,0,1) -> 9.048455e+09 | AE42: =+_xlfn.XLOOKUP(PROYECTOS[[#This Row],[MUNICIPIO]],'4.CAP_ENDMNT'!B:B,'4.CAP_ENDMNT'!N:N,0,0,1) -> 0.58593202 | AF42: =+_xlfn.XLOOKUP(PROYECTOS[[#This Row],[MUNICIPIO]],'4.CAP_ENDMNT'!B:B,'4.CAP_ENDMNT'!O:O,0,0,1) -> 0.58851113 | AG42: =+_xlfn.XLOOKUP(PROYECTOS[[#This Row],[MUNICIPIO]],'4.CAP_ENDMNT'!B:B,'4.CAP_ENDMNT'!P:P,0,0,1) -> 0.8 | AH42: =+_xlfn.XLOOKUP(PROYECTOS[[#This Row],[MUNICIPIO]],'4.CAP_ENDMNT'!B:B,'4.CAP_ENDMNT'!Q:Q,0,0,1) -> Cumple | AI42: =+_xlfn.XLOOKUP(PROYECTOS[[#This Row],[MUNICIPIO]],'4.CAP_ENDMNT'!B:B,'4.CAP_ENDMNT'!V:V,0,0,1) -> 1.809691e+09 | AJ42: =+_xlfn.XLOOKUP(PROYECTOS[[#This Row],[MUNICIPIO]],'4.CAP_ENDMNT'!B:B,'4.CAP_ENDMNT'!Y:Y,0,0,1) -> -1.2348844e+10
A43: 47 | B43: Solicitud de mesas técnicas para proyectos presentados por parte del municipio | C43: =+_xlfn.XLOOKUP(PROYECTOS[[#This Row],[ID_NECESIDAD]],'1.RADICADOS'!G:G,'1.RADICADOS'!C:C,0,0,1)*1 -> 45542 | D43: San Pedro de Urabá | E43: =+_xlfn.XLOOKUP(PROYECTOS[[#This Row],[MUNICIPIO]],MUNICIPIOS!A:A,MUNICIPIOS!E:E,0,0,1) -> Urabá | F43: =+_xlfn.XLOOKUP(PROYECTOS[[#This Row],[MUNICIPIO]],MUNICIPIOS!A:A,MUNICIPIOS!F:F,0,0,1) -> -76.380567 | G43: =+_xlfn.XLOOKUP(PROYECTOS[[#This Row],[MUNICIPIO]],MUNICIPIOS!A:A,MUNICIPIOS!G:G,0,0,1) -> 8,276884 | H43: =+_xlfn.XLOOKUP(PROYECTOS[[#This Row],[MUNICIPIO]],MUNICIPIOS!A:A,MUNICIPIOS!B:B,0,0,1) -> 1 | I43: =+_xlfn.XLOOKUP(PROYECTOS[[#This Row],[MUNICIPIO]],MUNICIPIOS!A:A,MUNICIPIOS!C:C,0,0,1) -> 1 | J43: {=_xlfn.TEXTJOIN(" ", TRUE, IF(radicados[ID PROYECTOS]=A43, radicados[RADICADO], ""))} -> 2024010240685 | K43: N/A | M43: Otros | N43: N/A | O43: Otros | T43: =+_xlfn.XLOOKUP(PROYECTOS[[#This Row],[MUNICIPIO]],'4.CAP_ENDMNT'!B:B,'4.CAP_ENDMNT'!C:C,0,0,1) -> 6 | U43: =+_xlfn.XLOOKUP(PROYECTOS[[#This Row],[MUNICIPIO]],'4.CAP_ENDMNT'!B:B,'4.CAP_ENDMNT'!D:D,0,0,1) -> 1.9508373e+10 | V43: =+_xlfn.XLOOKUP(PROYECTOS[[#This Row],[MUNICIPIO]],'4.CAP_ENDMNT'!B:B,'4.CAP_ENDMNT'!E:E,0,0,1) -> 5.3898343e+09 | W43: =+_xlfn.XLOOKUP(PROYECTOS[[#This Row],[MUNICIPIO]],'4.CAP_ENDMNT'!B:B,'4.CAP_ENDMNT'!F:F,0,0,1) -> 1.4118538e+10 | X43: =+_xlfn.XLOOKUP(PROYECTOS[[#This Row],[MUNICIPIO]],'4.CAP_ENDMNT'!B:B,'4.CAP_ENDMNT'!G:G,0,0,1) -> 2594281047 | Y43: =+_xlfn.XLOOKUP(PROYECTOS[[#This Row],[MUNICIPIO]],'4.CAP_ENDMNT'!B:B,'4.CAP_ENDMNT'!H:H,0,0,1) -> 1833333333 | Z43: =+_xlfn.XLOOKUP(PROYECTOS[[#This Row],[MUNICIPIO]],'4.CAP_ENDMNT'!B:B,'4.CAP_ENDMNT'!I:I,0,0,1) -> 4427614380 | AA43: =+_xlfn.XLOOKUP(PROYECTOS[[#This Row],[MUNICIPIO]],'4.CAP_ENDMNT'!B:B,'4.CAP_ENDMNT'!J:J,0,0,1) -> 0.2269597 | AB43: =+_xlfn.XLOOKUP(PROYECTOS[[#This Row],[MUNICIPIO]],'4.CAP_ENDMNT'!B:B,'4.CAP_ENDMNT'!K:K,0,0,1) -> 1.5080758e+10 | AC43: =+_xlfn.XLOOKUP(PROYECTOS[[#This Row],[MUNICIPIO]],'4.CAP_ENDMNT'!B:B,'4.CAP_ENDMNT'!L:L,0,0,1) -> 1.2064607e+10 | AD43: =+_xlfn.XLOOKUP(PROYECTOS[[#This Row],[MUNICIPIO]],'4.CAP_ENDMNT'!B:B,'4.CAP_ENDMNT'!M:M,0,0,1) -> 9.048455e+09 | AE43: =+_xlfn.XLOOKUP(PROYECTOS[[#This Row],[MUNICIPIO]],'4.CAP_ENDMNT'!B:B,'4.CAP_ENDMNT'!N:N,0,0,1) -> 0.58593202 | AF43: =+_xlfn.XLOOKUP(PROYECTOS[[#This Row],[MUNICIPIO]],'4.CAP_ENDMNT'!B:B,'4.CAP_ENDMNT'!O:O,0,0,1) -> 0.58851113 | AG43: =+_xlfn.XLOOKUP(PROYECTOS[[#This Row],[MUNICIPIO]],'4.CAP_ENDMNT'!B:B,'4.CAP_ENDMNT'!P:P,0,0,1) -> 0.8 | AH43: =+_xlfn.XLOOKUP(PROYECTOS[[#This Row],[MUNICIPIO]],'4.CAP_ENDMNT'!B:B,'4.CAP_ENDMNT'!Q:Q,0,0,1) -> Cumple | AI43: =+_xlfn.XLOOKUP(PROYECTOS[[#This Row],[MUNICIPIO]],'4.CAP_ENDMNT'!B:B,'4.CAP_ENDMNT'!V:V,0,0,1) -> 1.809691e+09 | AJ43: =+_xlfn.XLOOKUP(PROYECTOS[[#This Row],[MUNICIPIO]],'4.CAP_ENDMNT'!B:B,'4.CAP_ENDMNT'!Y:Y,0,0,1) -> -1.2348844e+10
A44: 48 | B44: Construcción de pavimento rígido en vías urbanas Barrio Obrero del municipio de Apartadó | C44: =+_xlfn.XLOOKUP(PROYECTOS[[#This Row],[ID_NECESIDAD]],'1.RADICADOS'!G:G,'1.RADICADOS'!C:C,0,0,1)*1 -> 45602 | D44: Apartadó | E44: =+_xlfn.XLOOKUP(PROYECTOS[[#This Row],[MUNICIPIO]],MUNICIPIOS!A:A,MUNICIPIOS!E:E,0,0,1) -> Urabá | F44: =+_xlfn.XLOOKUP(PROYECTOS[[#This Row],[MUNICIPIO]],MUNICIPIOS!A:A,MUNICIPIOS!F:F,0,0,1) -> -76.625279 | G44: =+_xlfn.XLOOKUP(PROYECTOS[[#This Row],[MUNICIPIO]],MUNICIPIOS!A:A,MUNICIPIOS!G:G,0,0,1) -> 7,882968 | H44: =+_xlfn.XLOOKUP(PROYECTOS[[#This Row],[MUNICIPIO]],MUNICIPIOS!A:A,MUNICIPIOS!B:B,0,0,1) -> 1 | I44: =+_xlfn.XLOOKUP(PROYECTOS[[#This Row],[MUNICIPIO]],MUNICIPIOS!A:A,MUNICIPIOS!C:C,0,0,1) -> 1 | J44: {=_xlfn.TEXTJOIN(" ", TRUE, IF(radicados[ID PROYECTOS]=A44, radicados[RADICADO], ""))} -> 2024010304650 2024010344153 | K44: 3 | L44: 7999391717 | M44: Pavimento Rígido | N44: Urbana | O44: Vía urbana mejorada | T44: =+_xlfn.XLOOKUP(PROYECTOS[[#This Row],[MUNICIPIO]],'4.CAP_ENDMNT'!B:B,'4.CAP_ENDMNT'!C:C,0,0,1) -> 3 | U44: =+_xlfn.XLOOKUP(PROYECTOS[[#This Row],[MUNICIPIO]],'4.CAP_ENDMNT'!B:B,'4.CAP_ENDMNT'!D:D,0,0,1) -> 7.7784648e+10 | V44: =+_xlfn.XLOOKUP(PROYECTOS[[#This Row],[MUNICIPIO]],'4.CAP_ENDMNT'!B:B,'4.CAP_ENDMNT'!E:E,0,0,1) -> 3.1716114e+10 | W44: =+_xlfn.XLOOKUP(PROYECTOS[[#This Row],[MUNICIPIO]],'4.CAP_ENDMNT'!B:B,'4.CAP_ENDMNT'!F:F,0,0,1) -> 4.6068534e+10 | X44: =+_xlfn.XLOOKUP(PROYECTOS[[#This Row],[MUNICIPIO]],'4.CAP_ENDMNT'!B:B,'4.CAP_ENDMNT'!G:G,0,0,1) -> 43139212620 | Y44: =+_xlfn.XLOOKUP(PROYECTOS[[#This Row],[MUNICIPIO]],'4.CAP_ENDMNT'!B:B,'4.CAP_ENDMNT'!H:H,0,0,1) -> 1.7341933e+10 | Z44: =+_xlfn.XLOOKUP(PROYECTOS[[#This Row],[MUNICIPIO]],'4.CAP_ENDMNT'!B:B,'4.CAP_ENDMNT'!I:I,0,0,1) -> 6.0481146e+10 | AA44: =+_xlfn.XLOOKUP(PROYECTOS[[#This Row],[MUNICIPIO]],'4.CAP_ENDMNT'!B:B,'4.CAP_ENDMNT'!J:J,0,0,1) -> 0.77754605 | AB44: =+_xlfn.XLOOKUP(PROYECTOS[[#This Row],[MUNICIPIO]],'4.CAP_ENDMNT'!B:B,'4.CAP_ENDMNT'!K:K,0,0,1) -> 1.7303503e+10 | AC44: =+_xlfn.XLOOKUP(PROYECTOS[[#This Row],[MUNICIPIO]],'4.CAP_ENDMNT'!B:B,'4.CAP_ENDMNT'!L:L,0,0,1) -> 1.3842802e+10 | AD44: =+_xlfn.XLOOKUP(PROYECTOS[[#This Row],[MUNICIPIO]],'4.CAP_ENDMNT'!B:B,'4.CAP_ENDMNT'!M:M,0,0,1) -> 1.0382102e+10 | AE44: =+_xlfn.XLOOKUP(PROYECTOS[[#This Row],[MUNICIPIO]],'4.CAP_ENDMNT'!B:B,'4.CAP_ENDMNT'!N:N,0,0,1) -> 0.71326712 | AF44: =+_xlfn.XLOOKUP(PROYECTOS[[#This Row],[MUNICIPIO]],'4.CAP_ENDMNT'!B:B,'4.CAP_ENDMNT'!O:O,0,0,1) -> 0.57328292 | AG44: =+_xlfn.XLOOKUP(PROYECTOS[[#This Row],[MUNICIPIO]],'4.CAP_ENDMNT'!B:B,'4.CAP_ENDMNT'!P:P,0,0,1) -> 0.7 | AH44: =+_xlfn.XLOOKUP(PROYECTOS[[#This Row],[MUNICIPIO]],'4.CAP_ENDMNT'!B:B,'4.CAP_ENDMNT'!Q:Q,0,0,1) -> Cumple | AI44: =+_xlfn.XLOOKUP(PROYECTOS[[#This Row],[MUNICIPIO]],'4.CAP_ENDMNT'!B:B,'4.CAP_ENDMNT'!V:V,0,0,1) -> 2.0764203e+09 | AJ44: =+_xlfn.XLOOKUP(PROYECTOS[[#This Row],[MUNICIPIO]],'4.CAP_ENDMNT'!B:B,'4.CAP_ENDMNT'!Y:Y,0,0,1) -> -1.3466841e+10
A45: 49 | B45: Parque principal de San Francisco Antioquia | C45: =+_xlfn.XLOOKUP(PROYECTOS[[#This Row],[ID_NECESIDAD]],'1.RADICADOS'!G:G,'1.RADICADOS'!C:C,0,0,1)*1 -> 45572 | D45: San Francisco | E45: =+_xlfn.XLOOKUP(PROYECTOS[[#This Row],[MUNICIPIO]],MUNICIPIOS!A:A,MUNICIPIOS!E:E,0,0,1) -> Oriente | F45: =+_xlfn.XLOOKUP(PROYECTOS[[#This Row],[MUNICIPIO]],MUNICIPIOS!A:A,MUNICIPIOS!F:F,0,0,1) -> -75.101562 | G45: =+_xlfn.XLOOKUP(PROYECTOS[[#This Row],[MUNICIPIO]],MUNICIPIOS!A:A,MUNICIPIOS!G:G,0,0,1) -> 5,963476 | H45: =+_xlfn.XLOOKUP(PROYECTOS[[#This Row],[MUNICIPIO]],MUNICIPIOS!A:A,MUNICIPIOS!B:B,0,0,1) -> 0 | I45: =+_xlfn.XLOOKUP(PROYECTOS[[#This Row],[MUNICIPIO]],MUNICIPIOS!A:A,MUNICIPIOS!C:C,0,0,1) -> 1 | J45: {=_xlfn.TEXTJOIN(" ", TRUE, IF(radicados[ID PROYECTOS]=A45, radicados[RADICADO], ""))} -> 2024010258944 | K45: 2 | M45: Parque | N45: N/A | O45: Espacio público adecuado | T45: =+_xlfn.XLOOKUP(PROYECTOS[[#This Row],[MUNICIPIO]],'4.CAP_ENDMNT'!B:B,'4.CAP_ENDMNT'!C:C,0,0,1) -> 6 | U45: =+_xlfn.XLOOKUP(PROYECTOS[[#This Row],[MUNICIPIO]],'4.CAP_ENDMNT'!B:B,'4.CAP_ENDMNT'!D:D,0,0,1) -> 7.7634871e+09 | V45: =+_xlfn.XLOOKUP(PROYECTOS[[#This Row],[MUNICIPIO]],'4.CAP_ENDMNT'!B:B,'4.CAP_ENDMNT'!E:E,0,0,1) -> 2.329929e+09 | W45: =+_xlfn.XLOOKUP(PROYECTOS[[#This Row],[MUNICIPIO]],'4.CAP_ENDMNT'!B:B,'4.CAP_ENDMNT'!F:F,0,0,1) -> 5.4335581e+09 | X45: =+_xlfn.XLOOKUP(PROYECTOS[[#This Row],[MUNICIPIO]],'4.CAP_ENDMNT'!B:B,'4.CAP_ENDMNT'!G:G,0,0,1) -> 1.2171074e+09 | Y45: =+_xlfn.XLOOKUP(PROYECTOS[[#This Row],[MUNICIPIO]],'4.CAP_ENDMNT'!B:B,'4.CAP_ENDMNT'!H:H,0,0,1) -> 0 | Z45: =+_xlfn.XLOOKUP(PROYECTOS[[#This Row],[MUNICIPIO]],'4.CAP_ENDMNT'!B:B,'4.CAP_ENDMNT'!I:I,0,0,1) -> 1.2171074e+09 | AA45: =+_xlfn.XLOOKUP(PROYECTOS[[#This Row],[MUNICIPIO]],'4.CAP_ENDMNT'!B:B,'4.CAP_ENDMNT'!J:J,0,0,1) -> 0.15677328 | AB45: =+_xlfn.XLOOKUP(PROYECTOS[[#This Row],[MUNICIPIO]],'4.CAP_ENDMNT'!B:B,'4.CAP_ENDMNT'!K:K,0,0,1) -> 6.5463797e+09 | AC45: =+_xlfn.XLOOKUP(PROYECTOS[[#This Row],[MUNICIPIO]],'4.CAP_ENDMNT'!B:B,'4.CAP_ENDMNT'!L:L,0,0,1) -> 5.2371038e+09 | AD45: =+_xlfn.XLOOKUP(PROYECTOS[[#This Row],[MUNICIPIO]],'4.CAP_ENDMNT'!B:B,'4.CAP_ENDMNT'!M:M,0,0,1) -> 3.9278278e+09 | AE45: =+_xlfn.XLOOKUP(PROYECTOS[[#This Row],[MUNICIPIO]],'4.CAP_ENDMNT'!B:B,'4.CAP_ENDMNT'!N:N,0,0,1) -> 1 | AF45: =+_xlfn.XLOOKUP(PROYECTOS[[#This Row],[MUNICIPIO]],'4.CAP_ENDMNT'!B:B,'4.CAP_ENDMNT'!O:O,0,0,1) -> 0.68141762 | AG45: =+_xlfn.XLOOKUP(PROYECTOS[[#This Row],[MUNICIPIO]],'4.CAP_ENDMNT'!B:B,'4.CAP_ENDMNT'!P:P,0,0,1) -> 0.8 | AH45: =+_xlfn.XLOOKUP(PROYECTOS[[#This Row],[MUNICIPIO]],'4.CAP_ENDMNT'!B:B,'4.CAP_ENDMNT'!Q:Q,0,0,1) -> Cumple | AI45: =+_xlfn.XLOOKUP(PROYECTOS[[#This Row],[MUNICIPIO]],'4.CAP_ENDMNT'!B:B,'4.CAP_ENDMNT'!V:V,0,0,1) -> 7.8556557e+08 | AJ45: =+_xlfn.XLOOKUP(PROYECTOS[[#This Row],[MUNICIPIO]],'4.CAP_ENDMNT'!B:B,'4.CAP_ENDMNT'!Y:Y,0,0,1) -> -1.0352205e+10
A46: 50 | B46: Plaza de mercado | C46: =+_xlfn.XLOOKUP(PROYECTOS[[#This Row],[ID_NECESIDAD]],'1.RADICADOS'!G:G,'1.RADICADOS'!C:C,0,0,1)*1 -> 45490 | D46: La Ceja | E46: =+_xlfn.XLOOKUP(PROYECTOS[[#This Row],[MUNICIPIO]],MUNICIPIOS!A:A,MUNICIPIOS!E:E,0,0,1) -> Oriente | F46: =+_xlfn.XLOOKUP(PROYECTOS[[#This Row],[MUNICIPIO]],MUNICIPIOS!A:A,MUNICIPIOS!F:F,0,0,1) -> -75.429433 | G46: =+_xlfn.XLOOKUP(PROYECTOS[[#This Row],[MUNICIPIO]],MUNICIPIOS!A:A,MUNICIPIOS!G:G,0,0,1) -> 6,028062 | H46: =+_xlfn.XLOOKUP(PROYECTOS[[#This Row],[MUNICIPIO]],MUNICIPIOS!A:A,MUNICIPIOS!B:B,0,0,1) -> 0 | I46: =+_xlfn.XLOOKUP(PROYECTOS[[#This Row],[MUNICIPIO]],MUNICIPIOS!A:A,MUNICIPIOS!C:C,0,0,1) -> 0 | J46: {=_xlfn.TEXTJOIN(" ", TRUE, IF(radicados[ID PROYECTOS]=A46, radicados[RADICADO], ""))} -> 2024010308663 | K46: 2 | M46: Plaza de Mercado | N46: N/A | O46: Equipamientos construidos | P46: Peticion recursos adicionales | T46: =+_xlfn.XLOOKUP(PROYECTOS[[#This Row],[MUNICIPIO]],'4.CAP_ENDMNT'!B:B,'4.CAP_ENDMNT'!C:C,0,0,1) -> 2 | U46: =+_xlfn.XLOOKUP(PROYECTOS[[#This Row],[MUNICIPIO]],'4.CAP_ENDMNT'!B:B,'4.CAP_ENDMNT'!D:D,0,0,1) -> 1.0269161e+11 | V46: =+_xlfn.XLOOKUP(PROYECTOS[[#This Row],[MUNICIPIO]],'4.CAP_ENDMNT'!B:B,'4.CAP_ENDMNT'!E:E,0,0,1) -> 2.9123622e+10 | W46: =+_xlfn.XLOOKUP(PROYECTOS[[#This Row],[MUNICIPIO]],'4.CAP_ENDMNT'!B:B,'4.CAP_ENDMNT'!F:F,0,0,1) -> 7.3567992e+10 | X46: =+_xlfn.XLOOKUP(PROYECTOS[[#This Row],[MUNICIPIO]],'4.CAP_ENDMNT'!B:B,'4.CAP_ENDMNT'!G:G,0,0,1) -> 5166195556 | Y46: =+_xlfn.XLOOKUP(PROYECTOS[[#This Row],[MUNICIPIO]],'4.CAP_ENDMNT'!B:B,'4.CAP_ENDMNT'!H:H,0,0,1) -> 27283390599 | Z46: =+_xlfn.XLOOKUP(PROYECTOS[[#This Row],[MUNICIPIO]],'4.CAP_ENDMNT'!B:B,'4.CAP_ENDMNT'!I:I,0,0,1) -> 32449586155 | AA46: =+_xlfn.XLOOKUP(PROYECTOS[[#This Row],[MUNICIPIO]],'4.CAP_ENDMNT'!B:B,'4.CAP_ENDMNT'!J:J,0,0,1) -> 0.31599061 | AB46: =+_xlfn.XLOOKUP(PROYECTOS[[#This Row],[MUNICIPIO]],'4.CAP_ENDMNT'!B:B,'4.CAP_ENDMNT'!K:K,0,0,1) -> 7.0242028e+10 | AC46: =+_xlfn.XLOOKUP(PROYECTOS[[#This Row],[MUNICIPIO]],'4.CAP_ENDMNT'!B:B,'4.CAP_ENDMNT'!L:L,0,0,1) -> 5.6193623e+10 | AD46: =+_xlfn.XLOOKUP(PROYECTOS[[#This Row],[MUNICIPIO]],'4.CAP_ENDMNT'!B:B,'4.CAP_ENDMNT'!M:M,0,0,1) -> 4.2145217e+10 | AE46: =+_xlfn.XLOOKUP(PROYECTOS[[#This Row],[MUNICIPIO]],'4.CAP_ENDMNT'!B:B,'4.CAP_ENDMNT'!N:N,0,0,1) -> 0.15920682 | AF46: =+_xlfn.XLOOKUP(PROYECTOS[[#This Row],[MUNICIPIO]],'4.CAP_ENDMNT'!B:B,'4.CAP_ENDMNT'!O:O,0,0,1) -> 0.28977188 | AG46: =+_xlfn.XLOOKUP(PROYECTOS[[#This Row],[MUNICIPIO]],'4.CAP_ENDMNT'!B:B,'4.CAP_ENDMNT'!P:P,0,0,1) -> 0.7 | AH46: =+_xlfn.XLOOKUP(PROYECTOS[[#This Row],[MUNICIPIO]],'4.CAP_ENDMNT'!B:B,'4.CAP_ENDMNT'!Q:Q,0,0,1) -> Cumple | AI46: =+_xlfn.XLOOKUP(PROYECTOS[[#This Row],[MUNICIPIO]],'4.CAP_ENDMNT'!B:B,'4.CAP_ENDMNT'!V:V,0,0,1) -> 8.4290434e+09 | AJ46: =+_xlfn.XLOOKUP(PROYECTOS[[#This Row],[MUNICIPIO]],'4.CAP_ENDMNT'!B:B,'4.CAP_ENDMNT'!Y:Y,0,0,1) -> 4.5609749e+10
A47: 51 | B47: Pavimentación en concreto rígido andenes peatonales y silvicultura en la calle 97 entre carrera 101 y 112 del municipio de Chigorodó Antioquia | C47: =+_xlfn.XLOOKUP(PROYECTOS[[#This Row],[ID_NECESIDAD]],'1.RADICADOS'!G:G,'1.RADICADOS'!C:C,0,0,1)*1 -> 45633 | D47: Chigorodó | E47: =+_xlfn.XLOOKUP(PROYECTOS[[#This Row],[MUNICIPIO]],MUNICIPIOS!A:A,MUNICIPIOS!E:E,0,0,1) -> Urabá | F47: =+_xlfn.XLOOKUP(PROYECTOS[[#This Row],[MUNICIPIO]],MUNICIPIOS!A:A,MUNICIPIOS!F:F,0,0,1) -> -76.681531 | G47: =+_xlfn.XLOOKUP(PROYECTOS[[#This Row],[MUNICIPIO]],MUNICIPIOS!A:A,MUNICIPIOS!G:G,0,0,1) -> 7,666147 | H47: =+_xlfn.XLOOKUP(PROYECTOS[[#This Row],[MUNICIPIO]],MUNICIPIOS!A:A,MUNICIPIOS!B:B,0,0,1) -> 1 | I47: =+_xlfn.XLOOKUP(PROYECTOS[[#This Row],[MUNICIPIO]],MUNICIPIOS!A:A,MUNICIPIOS!C:C,0,0,1) -> 1 | J47: {=_xlfn.TEXTJOIN(" ", TRUE, IF(radicados[ID PROYECTOS]=A47, radicados[RADICADO], ""))} -> 2024010308857 | K47: 3 | L47: 4215630027 | M47: Pavimento Rígido | N47: Urbana | O47: Vía urbana mejorada | T47: =+_xlfn.XLOOKUP(PROYECTOS[[#This Row],[MUNICIPIO]],'4.CAP_ENDMNT'!B:B,'4.CAP_ENDMNT'!C:C,0,0,1) -> 6 | U47: =+_xlfn.XLOOKUP(PROYECTOS[[#This Row],[MUNICIPIO]],'4.CAP_ENDMNT'!B:B,'4.CAP_ENDMNT'!D:D,0,0,1) -> 3.1480626e+10 | V47: =+_xlfn.XLOOKUP(PROYECTOS[[#This Row],[MUNICIPIO]],'4.CAP_ENDMNT'!B:B,'4.CAP_ENDMNT'!E:E,0,0,1) -> 1.2012746e+10 | W47: =+_xlfn.XLOOKUP(PROYECTOS[[#This Row],[MUNICIPIO]],'4.CAP_ENDMNT'!B:B,'4.CAP_ENDMNT'!F:F,0,0,1) -> 1.946788e+10 | X47: =+_xlfn.XLOOKUP(PROYECTOS[[#This Row],[MUNICIPIO]],'4.CAP_ENDMNT'!B:B,'4.CAP_ENDMNT'!G:G,0,0,1) -> 990257688 | Y47: =+_xlfn.XLOOKUP(PROYECTOS[[#This Row],[MUNICIPIO]],'4.CAP_ENDMNT'!B:B,'4.CAP_ENDMNT'!H:H,0,0,1) -> 4.2410464e+09 | Z47: =+_xlfn.XLOOKUP(PROYECTOS[[#This Row],[MUNICIPIO]],'4.CAP_ENDMNT'!B:B,'4.CAP_ENDMNT'!I:I,0,0,1) -> 5.2313041e+09 | AA47: =+_xlfn.XLOOKUP(PROYECTOS[[#This Row],[MUNICIPIO]],'4.CAP_ENDMNT'!B:B,'4.CAP_ENDMNT'!J:J,0,0,1) -> 0.16617535 | AB47: =+_xlfn.XLOOKUP(PROYECTOS[[#This Row],[MUNICIPIO]],'4.CAP_ENDMNT'!B:B,'4.CAP_ENDMNT'!K:K,0,0,1) -> 2.6249322e+10 | AC47: =+_xlfn.XLOOKUP(PROYECTOS[[#This Row],[MUNICIPIO]],'4.CAP_ENDMNT'!B:B,'4.CAP_ENDMNT'!L:L,0,0,1) -> 2.0999457e+10 | AD47: =+_xlfn.XLOOKUP(PROYECTOS[[#This Row],[MUNICIPIO]],'4.CAP_ENDMNT'!B:B,'4.CAP_ENDMNT'!M:M,0,0,1) -> 1.5749593e+10 | AE47: =+_xlfn.XLOOKUP(PROYECTOS[[#This Row],[MUNICIPIO]],'4.CAP_ENDMNT'!B:B,'4.CAP_ENDMNT'!N:N,0,0,1) -> 0.18929461 | AF47: =+_xlfn.XLOOKUP(PROYECTOS[[#This Row],[MUNICIPIO]],'4.CAP_ENDMNT'!B:B,'4.CAP_ENDMNT'!O:O,0,0,1) -> 0.57128724 | AG47: =+_xlfn.XLOOKUP(PROYECTOS[[#This Row],[MUNICIPIO]],'4.CAP_ENDMNT'!B:B,'4.CAP_ENDMNT'!P:P,0,0,1) -> 0.8 | AH47: =+_xlfn.XLOOKUP(PROYECTOS[[#This Row],[MUNICIPIO]],'4.CAP_ENDMNT'!B:B,'4.CAP_ENDMNT'!Q:Q,0,0,1) -> Cumple | AI47: =+_xlfn.XLOOKUP(PROYECTOS[[#This Row],[MUNICIPIO]],'4.CAP_ENDMNT'!B:B,'4.CAP_ENDMNT'!V:V,0,0,1) -> 3.1499186e+09 | AJ47: =+_xlfn.XLOOKUP(PROYECTOS[[#This Row],[MUNICIPIO]],'4.CAP_ENDMNT'!B:B,'4.CAP_ENDMNT'!Y:Y,0,0,1) -> -1.595771e+11
A48: 52 | B48: Intervención de la vía terciaria de acceso al corregimiento cedeño y sus veredas aledañas en el municipio de Yarumal Antioquia afectada por la ola invernal | C48: =+_xlfn.XLOOKUP(PROYECTOS[[#This Row],[ID_NECESIDAD]],'1.RADICADOS'!G:G,'1.RADICADOS'!C:C,0,0,1)*1 -> 45358 | D48: Yarumal | E48: =+_xlfn.XLOOKUP(PROYECTOS[[#This Row],[MUNICIPIO]],MUNICIPIOS!A:A,MUNICIPIOS!E:E,0,0,1) -> Norte | F48: =+_xlfn.XLOOKUP(PROYECTOS[[#This Row],[MUNICIPIO]],MUNICIPIOS!A:A,MUNICIPIOS!F:F,0,0,1) -> -75.418828 | G48: =+_xlfn.XLOOKUP(PROYECTOS[[#This Row],[MUNICIPIO]],MUNICIPIOS!A:A,MUNICIPIOS!G:G,0,0,1) -> 6.963832 | H48: =+_xlfn.XLOOKUP(PROYECTOS[[#This Row],[MUNICIPIO]],MUNICIPIOS!A:A,MUNICIPIOS!B:B,0,0,1) -> 0 | I48: =+_xlfn.XLOOKUP(PROYECTOS[[#This Row],[MUNICIPIO]],MUNICIPIOS!A:A,MUNICIPIOS!C:C,0,0,1) -> 1 | J48: {=_xlfn.TEXTJOIN(" ", TRUE, IF(radicados[ID PROYECTOS]=A48, radicados[RADICADO], ""))} -> 2024010313514 | K48: 3 | M48: Puntos de Atención Prioritaria | N48: Tercer Orden | O48: Vías terciarias mejoradas | P48: Priorizado 14/05/2025 | Q48: 1 | R48: SGR Regionales 60% | S48: Puentes y PAP 2025-1 | T48: =+_xlfn.XLOOKUP(PROYECTOS[[#This Row],[MUNICIPIO]],'4.CAP_ENDMNT'!B:B,'4.CAP_ENDMNT'!C:C,0,0,1) -> 5 | U48: =+_xlfn.XLOOKUP(PROYECTOS[[#This Row],[MUNICIPIO]],'4.CAP_ENDMNT'!B:B,'4.CAP_ENDMNT'!D:D,0,0,1) -> 3.620472e+10 | V48: =+_xlfn.XLOOKUP(PROYECTOS[[#This Row],[MUNICIPIO]],'4.CAP_ENDMNT'!B:B,'4.CAP_ENDMNT'!E:E,0,0,1) -> 1.1082624e+10 | W48: =+_xlfn.XLOOKUP(PROYECTOS[[#This Row],[MUNICIPIO]],'4.CAP_ENDMNT'!B:B,'4.CAP_ENDMNT'!F:F,0,0,1) -> 2.5122096e+10 | X48: =+_xlfn.XLOOKUP(PROYECTOS[[#This Row],[MUNICIPIO]],'4.CAP_ENDMNT'!B:B,'4.CAP_ENDMNT'!G:G,0,0,1) -> 1291156679 | Y48: =+_xlfn.XLOOKUP(PROYECTOS[[#This Row],[MUNICIPIO]],'4.CAP_ENDMNT'!B:B,'4.CAP_ENDMNT'!H:H,0,0,1) -> 1.2320356e+10 | Z48: =+_xlfn.XLOOKUP(PROYECTOS[[#This Row],[MUNICIPIO]],'4.CAP_ENDMNT'!B:B,'4.CAP_ENDMNT'!I:I,0,0,1) -> 1.3611513e+10 | AA48: =+_xlfn.XLOOKUP(PROYECTOS[[#This Row],[MUNICIPIO]],'4.CAP_ENDMNT'!B:B,'4.CAP_ENDMNT'!J:J,0,0,1) -> 0.37595962 | AB48: =+_xlfn.XLOOKUP(PROYECTOS[[#This Row],[MUNICIPIO]],'4.CAP_ENDMNT'!B:B,'4.CAP_ENDMNT'!K:K,0,0,1) -> 2.2593207e+10 | AC48: =+_xlfn.XLOOKUP(PROYECTOS[[#This Row],[MUNICIPIO]],'4.CAP_ENDMNT'!B:B,'4.CAP_ENDMNT'!L:L,0,0,1) -> 1.8074566e+10 | AD48: =+_xlfn.XLOOKUP(PROYECTOS[[#This Row],[MUNICIPIO]],'4.CAP_ENDMNT'!B:B,'4.CAP_ENDMNT'!M:M,0,0,1) -> 1.3555924e+10 | AE48: =+_xlfn.XLOOKUP(PROYECTOS[[#This Row],[MUNICIPIO]],'4.CAP_ENDMNT'!B:B,'4.CAP_ENDMNT'!N:N,0,0,1) -> 0.094857693 | AF48: =+_xlfn.XLOOKUP(PROYECTOS[[#This Row],[MUNICIPIO]],'4.CAP_ENDMNT'!B:B,'4.CAP_ENDMNT'!O:O,0,0,1) -> 0.39053077 | AG48: =+_xlfn.XLOOKUP(PROYECTOS[[#This Row],[MUNICIPIO]],'4.CAP_ENDMNT'!B:B,'4.CAP_ENDMNT'!P:P,0,0,1) -> 0.8 | AH48: =+_xlfn.XLOOKUP(PROYECTOS[[#This Row],[MUNICIPIO]],'4.CAP_ENDMNT'!B:B,'4.CAP_ENDMNT'!Q:Q,0,0,1) -> Cumple | AI48: =+_xlfn.XLOOKUP(PROYECTOS[[#This Row],[MUNICIPIO]],'4.CAP_ENDMNT'!B:B,'4.CAP_ENDMNT'!V:V,0,0,1) -> 2.7111849e+09 | AJ48: =+_xlfn.XLOOKUP(PROYECTOS[[#This Row],[MUNICIPIO]],'4.CAP_ENDMNT'!B:B,'4.CAP_ENDMNT'!Y:Y,0,0,1) -> -1.9241183e+11
A49: 53 | B49: Solicitud de pavimentación de vía Belmira Horizontes | C49: =+_xlfn.XLOOKUP(PROYECTOS[[#This Row],[ID_NECESIDAD]],'1.RADICADOS'!G:G,'1.RADICADOS'!C:C,0,0,1)*1 -> 45603 | D49: Sopetrán | E49: =+_xlfn.XLOOKUP(PROYECTOS[[#This Row],[MUNICIPIO]],MUNICIPIOS!A:A,MUNICIPIOS!E:E,0,0,1) -> Occidente | F49: =+_xlfn.XLOOKUP(PROYECTOS[[#This Row],[MUNICIPIO]],MUNICIPIOS!A:A,MUNICIPIOS!F:F,0,0,1) -> -75.747378 | G49: =+_xlfn.XLOOKUP(PROYECTOS[[#This Row],[MUNICIPIO]],MUNICIPIOS!A:A,MUNICIPIOS!G:G,0,0,1) -> 6.500745 | H49: =+_xlfn.XLOOKUP(PROYECTOS[[#This Row],[MUNICIPIO]],MUNICIPIOS!A:A,MUNICIPIOS!B:B,0,0,1) -> 0 | I49: =+_xlfn.XLOOKUP(PROYECTOS[[#This Row],[MUNICIPIO]],MUNICIPIOS!A:A,MUNICIPIOS!C:C,0,0,1) -> 0 | J49: {=_xlfn.TEXTJOIN(" ", TRUE, IF(radicados[ID PROYECTOS]=A49, radicados[RADICADO], ""))} -> 2024010295409 | K49: 1 | M49: Pavimento Flexible | N49: Tercer Orden | O49: Vías terciarias mejoradas | P49: Es una peticion de una lidereza de la comunidad | T49: =+_xlfn.XLOOKUP(PROYECTOS[[#This Row],[MUNICIPIO]],'4.CAP_ENDMNT'!B:B,'4.CAP_ENDMNT'!C:C,0,0,1) -> 6 | U49: =+_xlfn.XLOOKUP(PROYECTOS[[#This Row],[MUNICIPIO]],'4.CAP_ENDMNT'!B:B,'4.CAP_ENDMNT'!D:D,0,0,1) -> 1.6347842e+10 | V49: =+_xlfn.XLOOKUP(PROYECTOS[[#This Row],[MUNICIPIO]],'4.CAP_ENDMNT'!B:B,'4.CAP_ENDMNT'!E:E,0,0,1) -> 7.9016432e+09 | W49: =+_xlfn.XLOOKUP(PROYECTOS[[#This Row],[MUNICIPIO]],'4.CAP_ENDMNT'!B:B,'4.CAP_ENDMNT'!F:F,0,0,1) -> 8.4461989e+09 | X49: =+_xlfn.XLOOKUP(PROYECTOS[[#This Row],[MUNICIPIO]],'4.CAP_ENDMNT'!B:B,'4.CAP_ENDMNT'!G:G,0,0,1) -> 1.620906e+09 | Y49: =+_xlfn.XLOOKUP(PROYECTOS[[#This Row],[MUNICIPIO]],'4.CAP_ENDMNT'!B:B,'4.CAP_ENDMNT'!H:H,0,0,1) -> 2416666620 | Z49: =+_xlfn.XLOOKUP(PROYECTOS[[#This Row],[MUNICIPIO]],'4.CAP_ENDMNT'!B:B,'4.CAP_ENDMNT'!I:I,0,0,1) -> 4.0375726e+09 | AA49: =+_xlfn.XLOOKUP(PROYECTOS[[#This Row],[MUNICIPIO]],'4.CAP_ENDMNT'!B:B,'4.CAP_ENDMNT'!J:J,0,0,1) -> 0.24697893 | AB49: =+_xlfn.XLOOKUP(PROYECTOS[[#This Row],[MUNICIPIO]],'4.CAP_ENDMNT'!B:B,'4.CAP_ENDMNT'!K:K,0,0,1) -> 1.2310269e+10 | AC49: =+_xlfn.XLOOKUP(PROYECTOS[[#This Row],[MUNICIPIO]],'4.CAP_ENDMNT'!B:B,'4.CAP_ENDMNT'!L:L,0,0,1) -> 9.8482156e+09 | AD49: =+_xlfn.XLOOKUP(PROYECTOS[[#This Row],[MUNICIPIO]],'4.CAP_ENDMNT'!B:B,'4.CAP_ENDMNT'!M:M,0,0,1) -> 7.3861617e+09 | AE49: =+_xlfn.XLOOKUP(PROYECTOS[[#This Row],[MUNICIPIO]],'4.CAP_ENDMNT'!B:B,'4.CAP_ENDMNT'!N:N,0,0,1) -> 0.40145556 | AF49: =+_xlfn.XLOOKUP(PROYECTOS[[#This Row],[MUNICIPIO]],'4.CAP_ENDMNT'!B:B,'4.CAP_ENDMNT'!O:O,0,0,1) -> 0.58521535 | AG49: =+_xlfn.XLOOKUP(PROYECTOS[[#This Row],[MUNICIPIO]],'4.CAP_ENDMNT'!B:B,'4.CAP_ENDMNT'!P:P,0,0,1) -> 0.8 | AH49: =+_xlfn.XLOOKUP(PROYECTOS[[#This Row],[MUNICIPIO]],'4.CAP_ENDMNT'!B:B,'4.CAP_ENDMNT'!Q:Q,0,0,1) -> Cumple | AI49: =+_xlfn.XLOOKUP(PROYECTOS[[#This Row],[MUNICIPIO]],'4.CAP_ENDMNT'!B:B,'4.CAP_ENDMNT'!V:V,0,0,1) -> 1.4772323e+09 | AJ49: =+_xlfn.XLOOKUP(PROYECTOS[[#This Row],[MUNICIPIO]],'4.CAP_ENDMNT'!B:B,'4.CAP_ENDMNT'!Y:Y,0,0,1) -> -1.1946219e+10
A50: 54 | B50: Construcción de placa huella y obras complementarias en la vía Támesis - San Pablo (Tamesis - Valparaiso) | C50: =+_xlfn.XLOOKUP(PROYECTOS[[#This Row],[ID_NECESIDAD]],'1.RADICADOS'!G:G,'1.RADICADOS'!C:C,0,0,1)*1 -> 45344 | D50: Támesis | E50: =+_xlfn.XLOOKUP(PROYECTOS[[#This Row],[MUNICIPIO]],MUNICIPIOS!A:A,MUNICIPIOS!E:E,0,0,1) -> Suroeste | F50: =+_xlfn.XLOOKUP(PROYECTOS[[#This Row],[MUNICIPIO]],MUNICIPIOS!A:A,MUNICIPIOS!F:F,0,0,1) -> -75.714429 | G50: =+_xlfn.XLOOKUP(PROYECTOS[[#This Row],[MUNICIPIO]],MUNICIPIOS!A:A,MUNICIPIOS!G:G,0,0,1) -> 5.664645 | H50: =+_xlfn.XLOOKUP(PROYECTOS[[#This Row],[MUNICIPIO]],MUNICIPIOS!A:A,MUNICIPIOS!B:B,0,0,1) -> 0 | I50: =+_xlfn.XLOOKUP(PROYECTOS[[#This Row],[MUNICIPIO]],MUNICIPIOS!A:A,MUNICIPIOS!C:C,0,0,1) -> 0 | J50: {=_xlfn.TEXTJOIN(" ", TRUE, IF(radicados[ID PROYECTOS]=A50, radicados[RADICADO], ""))} -> 2024010078784 2024010309743 2024010402790 | K50: 3 | L50: 4369072228 | M50: Placa huella | N50: Segundo Orden | O50: Vías secundarias mejoradas | P50: Via 2.5km que comunica corregimientos de San Pablo y la vereda el Narajal | T50: =+_xlfn.XLOOKUP(PROYECTOS[[#This Row],[MUNICIPIO]],'4.CAP_ENDMNT'!B:B,'4.CAP_ENDMNT'!C:C,0,0,1) -> 6 | U50: =+_xlfn.XLOOKUP(PROYECTOS[[#This Row],[MUNICIPIO]],'4.CAP_ENDMNT'!B:B,'4.CAP_ENDMNT'!D:D,0,0,1) -> 1.3939578e+10 | V50: =+_xlfn.XLOOKUP(PROYECTOS[[#This Row],[MUNICIPIO]],'4.CAP_ENDMNT'!B:B,'4.CAP_ENDMNT'!E:E,0,0,1) -> 5.4086452e+09 | W50: =+_xlfn.XLOOKUP(PROYECTOS[[#This Row],[MUNICIPIO]],'4.CAP_ENDMNT'!B:B,'4.CAP_ENDMNT'!F:F,0,0,1) -> 8.5309327e+09 | X50: =+_xlfn.XLOOKUP(PROYECTOS[[#This Row],[MUNICIPIO]],'4.CAP_ENDMNT'!B:B,'4.CAP_ENDMNT'!G:G,0,0,1) -> 2408239973 | Y50: =+_xlfn.XLOOKUP(PROYECTOS[[#This Row],[MUNICIPIO]],'4.CAP_ENDMNT'!B:B,'4.CAP_ENDMNT'!H:H,0,0,1) -> 812109375 | Z50: =+_xlfn.XLOOKUP(PROYECTOS[[#This Row],[MUNICIPIO]],'4.CAP_ENDMNT'!B:B,'4.CAP_ENDMNT'!I:I,0,0,1) -> 3220349348 | AA50: =+_xlfn.XLOOKUP(PROYECTOS[[#This Row],[MUNICIPIO]],'4.CAP_ENDMNT'!B:B,'4.CAP_ENDMNT'!J:J,0,0,1) -> 0.23102201 | AB50: =+_xlfn.XLOOKUP(PROYECTOS[[#This Row],[MUNICIPIO]],'4.CAP_ENDMNT'!B:B,'4.CAP_ENDMNT'!K:K,0,0,1) -> 1.0719229e+10 | AC50: =+_xlfn.XLOOKUP(PROYECTOS[[#This Row],[MUNICIPIO]],'4.CAP_ENDMNT'!B:B,'4.CAP_ENDMNT'!L:L,0,0,1) -> 8.5753828e+09 | AD50: =+_xlfn.XLOOKUP(PROYECTOS[[#This Row],[MUNICIPIO]],'4.CAP_ENDMNT'!B:B,'4.CAP_ENDMNT'!M:M,0,0,1) -> 6.4315371e+09 | AE50: =+_xlfn.XLOOKUP(PROYECTOS[[#This Row],[MUNICIPIO]],'4.CAP_ENDMNT'!B:B,'4.CAP_ENDMNT'!N:N,0,0,1) -> 0.74781948 | AF50: =+_xlfn.XLOOKUP(PROYECTOS[[#This Row],[MUNICIPIO]],'4.CAP_ENDMNT'!B:B,'4.CAP_ENDMNT'!O:O,0,0,1) -> 0.4814897 | AG50: =+_xlfn.XLOOKUP(PROYECTOS[[#This Row],[MUNICIPIO]],'4.CAP_ENDMNT'!B:B,'4.CAP_ENDMNT'!P:P,0,0,1) -> 0.8 | AH50: =+_xlfn.XLOOKUP(PROYECTOS[[#This Row],[MUNICIPIO]],'4.CAP_ENDMNT'!B:B,'4.CAP_ENDMNT'!Q:Q,0,0,1) -> Cumple | AI50: =+_xlfn.XLOOKUP(PROYECTOS[[#This Row],[MUNICIPIO]],'4.CAP_ENDMNT'!B:B,'4.CAP_ENDMNT'!V:V,0,0,1) -> 1.2863074e+09 | AJ50: =+_xlfn.XLOOKUP(PROYECTOS[[#This Row],[MUNICIPIO]],'4.CAP_ENDMNT'!B:B,'4.CAP_ENDMNT'!Y:Y,0,0,1) -> -1.0772172e+10
A51: 55 | B51: Pavimentación de 700 metros de pavimento rígido en la vía La Danta - Autopista Medellín - Bogotá | C51: =+_xlfn.XLOOKUP(PROYECTOS[[#This Row],[ID_NECESIDAD]],'1.RADICADOS'!G:G,'1.RADICADOS'!C:C,0,0,1)*1 -> 45634 | D51: Sonsón | E51: =+_xlfn.XLOOKUP(PROYECTOS[[#This Row],[MUNICIPIO]],MUNICIPIOS!A:A,MUNICIPIOS!E:E,0,0,1) -> Oriente | F51: =+_xlfn.XLOOKUP(PROYECTOS[[#This Row],[MUNICIPIO]],MUNICIPIOS!A:A,MUNICIPIOS!F:F,0,0,1) -> -75.309596 | G51: =+_xlfn.XLOOKUP(PROYECTOS[[#This Row],[MUNICIPIO]],MUNICIPIOS!A:A,MUNICIPIOS!G:G,0,0,1) -> 5,714851 | H51: =+_xlfn.XLOOKUP(PROYECTOS[[#This Row],[MUNICIPIO]],MUNICIPIOS!A:A,MUNICIPIOS!B:B,0,0,1) -> 0 | I51: =+_xlfn.XLOOKUP(PROYECTOS[[#This Row],[MUNICIPIO]],MUNICIPIOS!A:A,MUNICIPIOS!C:C,0,0,1) -> 1 | J51: {=_xlfn.TEXTJOIN(" ", TRUE, IF(radicados[ID PROYECTOS]=A51, radicados[RADICADO], ""))} -> 2024010319437 | K51: 3 | L51: 684345500 | M51: Pavimento Rígido | N51: Tercer Orden | O51: Vías terciarias mejoradas | T51: =+_xlfn.XLOOKUP(PROYECTOS[[#This Row],[MUNICIPIO]],'4.CAP_ENDMNT'!B:B,'4.CAP_ENDMNT'!C:C,0,0,1) -> 5 | U51: =+_xlfn.XLOOKUP(PROYECTOS[[#This Row],[MUNICIPIO]],'4.CAP_ENDMNT'!B:B,'4.CAP_ENDMNT'!D:D,0,0,1) -> 3.5695768e+10 | V51: =+_xlfn.XLOOKUP(PROYECTOS[[#This Row],[MUNICIPIO]],'4.CAP_ENDMNT'!B:B,'4.CAP_ENDMNT'!E:E,0,0,1) -> 1.3532488e+10 | W51: =+_xlfn.XLOOKUP(PROYECTOS[[#This Row],[MUNICIPIO]],'4.CAP_ENDMNT'!B:B,'4.CAP_ENDMNT'!F:F,0,0,1) -> 2.2163279e+10 | X51: =+_xlfn.XLOOKUP(PROYECTOS[[#This Row],[MUNICIPIO]],'4.CAP_ENDMNT'!B:B,'4.CAP_ENDMNT'!G:G,0,0,1) -> 1067761948 | Y51: =+_xlfn.XLOOKUP(PROYECTOS[[#This Row],[MUNICIPIO]],'4.CAP_ENDMNT'!B:B,'4.CAP_ENDMNT'!H:H,0,0,1) -> 4932032890 | Z51: =+_xlfn.XLOOKUP(PROYECTOS[[#This Row],[MUNICIPIO]],'4.CAP_ENDMNT'!B:B,'4.CAP_ENDMNT'!I:I,0,0,1) -> 5999794838 | AA51: =+_xlfn.XLOOKUP(PROYECTOS[[#This Row],[MUNICIPIO]],'4.CAP_ENDMNT'!B:B,'4.CAP_ENDMNT'!J:J,0,0,1) -> 0.16808141 | AB51: =+_xlfn.XLOOKUP(PROYECTOS[[#This Row],[MUNICIPIO]],'4.CAP_ENDMNT'!B:B,'4.CAP_ENDMNT'!K:K,0,0,1) -> 2.9695973e+10 | AC51: =+_xlfn.XLOOKUP(PROYECTOS[[#This Row],[MUNICIPIO]],'4.CAP_ENDMNT'!B:B,'4.CAP_ENDMNT'!L:L,0,0,1) -> 2.3756778e+10 | AD51: =+_xlfn.XLOOKUP(PROYECTOS[[#This Row],[MUNICIPIO]],'4.CAP_ENDMNT'!B:B,'4.CAP_ENDMNT'!M:M,0,0,1) -> 1.7817584e+10 | AE51: =+_xlfn.XLOOKUP(PROYECTOS[[#This Row],[MUNICIPIO]],'4.CAP_ENDMNT'!B:B,'4.CAP_ENDMNT'!N:N,0,0,1) -> 0.17796641 | AF51: =+_xlfn.XLOOKUP(PROYECTOS[[#This Row],[MUNICIPIO]],'4.CAP_ENDMNT'!B:B,'4.CAP_ENDMNT'!O:O,0,0,1) -> 0.40167298 | AG51: =+_xlfn.XLOOKUP(PROYECTOS[[#This Row],[MUNICIPIO]],'4.CAP_ENDMNT'!B:B,'4.CAP_ENDMNT'!P:P,0,0,1) -> 0.8 | AH51: =+_xlfn.XLOOKUP(PROYECTOS[[#This Row],[MUNICIPIO]],'4.CAP_ENDMNT'!B:B,'4.CAP_ENDMNT'!Q:Q,0,0,1) -> Cumple | AI51: =+_xlfn.XLOOKUP(PROYECTOS[[#This Row],[MUNICIPIO]],'4.CAP_ENDMNT'!B:B,'4.CAP_ENDMNT'!V:V,0,0,1) -> 3.5635167e+09 | AJ51: =+_xlfn.XLOOKUP(PROYECTOS[[#This Row],[MUNICIPIO]],'4.CAP_ENDMNT'!B:B,'4.CAP_ENDMNT'!Y:Y,0,0,1) -> -4.6557238e+10
A52: 56 | B52: Mejoramiento del corredor turístico Cocorná - Maria Parda con la construcción de 2.6 km de pavimento rígido en el municipio de Cocorná Antioquia | C52: =+_xlfn.XLOOKUP(PROYECTOS[[#This Row],[ID_NECESIDAD]],'1.RADICADOS'!G:G,'1.RADICADOS'!C:C,0,0,1)*1 -> 45634 | D52: Cocorná | E52: =+_xlfn.XLOOKUP(PROYECTOS[[#This Row],[MUNICIPIO]],MUNICIPIOS!A:A,MUNICIPIOS!E:E,0,0,1) -> Oriente | F52: =+_xlfn.XLOOKUP(PROYECTOS[[#This Row],[MUNICIPIO]],MUNICIPIOS!A:A,MUNICIPIOS!F:F,0,0,1) -> -75.185483 | G52: =+_xlfn.XLOOKUP(PROYECTOS[[#This Row],[MUNICIPIO]],MUNICIPIOS!A:A,MUNICIPIOS!G:G,0,0,1) -> 6,058295 | H52: =+_xlfn.XLOOKUP(PROYECTOS[[#This Row],[MUNICIPIO]],MUNICIPIOS!A:A,MUNICIPIOS!B:B,0,0,1) -> 0 | I52: =+_xlfn.XLOOKUP(PROYECTOS[[#This Row],[MUNICIPIO]],MUNICIPIOS!A:A,MUNICIPIOS!C:C,0,0,1) -> 1 | J52: {=_xlfn.TEXTJOIN(" ", TRUE, IF(radicados[ID PROYECTOS]=A52, radicados[RADICADO], ""))} -> 2024010361194 | K52: 2 | M52: Pavimento Rígido | N52: Tercer Orden | O52: Vías terciarias mejoradas | P52: Carpeta adjunta no contiene nada | T52: =+_xlfn.XLOOKUP(PROYECTOS[[#This Row],[MUNICIPIO]],'4.CAP_ENDMNT'!B:B,'4.CAP_ENDMNT'!C:C,0,0,1) -> 6 | U52: =+_xlfn.XLOOKUP(PROYECTOS[[#This Row],[MUNICIPIO]],'4.CAP_ENDMNT'!B:B,'4.CAP_ENDMNT'!D:D,0,0,1) -> 1.2327691e+10 | V52: =+_xlfn.XLOOKUP(PROYECTOS[[#This Row],[MUNICIPIO]],'4.CAP_ENDMNT'!B:B,'4.CAP_ENDMNT'!E:E,0,0,1) -> 4.7236801e+09 | W52: =+_xlfn.XLOOKUP(PROYECTOS[[#This Row],[MUNICIPIO]],'4.CAP_ENDMNT'!B:B,'4.CAP_ENDMNT'!F:F,0,0,1) -> 7.6040105e+09 | X52: =+_xlfn.XLOOKUP(PROYECTOS[[#This Row],[MUNICIPIO]],'4.CAP_ENDMNT'!B:B,'4.CAP_ENDMNT'!G:G,0,0,1) -> 445297438 | Y52: =+_xlfn.XLOOKUP(PROYECTOS[[#This Row],[MUNICIPIO]],'4.CAP_ENDMNT'!B:B,'4.CAP_ENDMNT'!H:H,0,0,1) -> 33508702 | Z52: =+_xlfn.XLOOKUP(PROYECTOS[[#This Row],[MUNICIPIO]],'4.CAP_ENDMNT'!B:B,'4.CAP_ENDMNT'!I:I,0,0,1) -> 478806140 | AA52: =+_xlfn.XLOOKUP(PROYECTOS[[#This Row],[MUNICIPIO]],'4.CAP_ENDMNT'!B:B,'4.CAP_ENDMNT'!J:J,0,0,1) -> 0.038839889 | AB52: =+_xlfn.XLOOKUP(PROYECTOS[[#This Row],[MUNICIPIO]],'4.CAP_ENDMNT'!B:B,'4.CAP_ENDMNT'!K:K,0,0,1) -> 1.1848884e+10 | AC52: =+_xlfn.XLOOKUP(PROYECTOS[[#This Row],[MUNICIPIO]],'4.CAP_ENDMNT'!B:B,'4.CAP_ENDMNT'!L:L,0,0,1) -> 9.4791076e+09 | AD52: =+_xlfn.XLOOKUP(PROYECTOS[[#This Row],[MUNICIPIO]],'4.CAP_ENDMNT'!B:B,'4.CAP_ENDMNT'!M:M,0,0,1) -> 7.1093307e+09 | AE52: =+_xlfn.XLOOKUP(PROYECTOS[[#This Row],[MUNICIPIO]],'4.CAP_ENDMNT'!B:B,'4.CAP_ENDMNT'!N:N,0,0,1) -> 0.93001614 | AF52: =+_xlfn.XLOOKUP(PROYECTOS[[#This Row],[MUNICIPIO]],'4.CAP_ENDMNT'!B:B,'4.CAP_ENDMNT'!O:O,0,0,1) -> 0.63996046 | AG52: =+_xlfn.XLOOKUP(PROYECTOS[[#This Row],[MUNICIPIO]],'4.CAP_ENDMNT'!B:B,'4.CAP_ENDMNT'!P:P,0,0,1) -> 0.8 | AH52: =+_xlfn.XLOOKUP(PROYECTOS[[#This Row],[MUNICIPIO]],'4.CAP_ENDMNT'!B:B,'4.CAP_ENDMNT'!Q:Q,0,0,1) -> Cumple | AI52: =+_xlfn.XLOOKUP(PROYECTOS[[#This Row],[MUNICIPIO]],'4.CAP_ENDMNT'!B:B,'4.CAP_ENDMNT'!V:V,0,0,1) -> 1.4218661e+09 | AJ52: =+_xlfn.XLOOKUP(PROYECTOS[[#This Row],[MUNICIPIO]],'4.CAP_ENDMNT'!B:B,'4.CAP_ENDMNT'!Y:Y,0,0,1) -> 4.8094294e+09
